Workbook

Sheet Overview
A1: East, Central & Southern Africa — Company Expansion & Infrastructure Tracker
A3: Source: original web research (news, press releases, government/investment-authority sites), compiled September 2026 — this fills the FACT_COMPANY and FACT_INFRASTRUCTURE tables from your data model, which no ready-made government dataset covers the way UIS/WITS covers macro and trade indicators.
A4: Scope: all 19 countries in your data model's regional expansion — Kenya, Tanzania, Uganda, Rwanda, Ethiopia, Burundi, Comoros, Djibouti, DRC Congo, Eritrea, Madagascar, Malawi, Mauritius, Mozambique, Seychelles, Somalia, South Sudan, Zambia and Zimbabwe. Company entries are real, named companies with a documented, sourced expansion signal roughly 2019-2026 (older infrastructure projects are included where the signal is the most recent verifiable status update).
A6: How this workbook is organized
A7: Same structure as your other workbooks: one flat table per fact (Companies, Infrastructure), columns grouped and color-banded by theme, with a live-formula Opportunity Score on the Companies sheet. See the Methodology sheet for exactly how that score is built — it is fully transparent and recalculates if you edit the underlying data.
A11: Sheet | B11: Contents
A12: Methodology | B12: The Opportunity Score rubric — every scoring band spelled out, editable, and referenced live by formulas on the Companies sheet.
A13: Companies | B13: 109 real, sourced companies with a recent East Africa expansion signal — this is FACT_COMPANY.
A14: Infrastructure | B14: 66 real, sourced SEZs, industrial parks, ports, logistics hubs and data centres — this is FACT_INFRASTRUCTURE.
A16: Coverage by country
A17: Country | B17: Companies / Infrastructure projects found
A18: Burundi | B18: 2 companies, 1 infrastructure projects
A19: Comoros | B19: 2 companies, 2 infrastructure projects
A20: Djibouti | B20: 4 companies, 3 infrastructure projects
A21: DRC Congo | B21: 4 companies, 2 infrastructure projects
A22: Eritrea | B22: 1 companies, 1 infrastructure projects
A23: Ethiopia | B23: 12 companies, 7 infrastructure projects
A24: Kenya | B24: 14 companies, 9 infrastructure projects
A25: Madagascar | B25: 3 companies, 2 infrastructure projects
A26: Malawi | B26: 4 companies, 3 infrastructure projects
A27: Mauritius | B27: 3 companies, 2 infrastructure projects
A28: Mozambique | B28: 3 companies, 2 infrastructure projects
... A36: Zimbabwe | B36: 5 companies, 3 infrastructure projects
A38: Data notes
A39: • This data does not come from a single published dataset (unlike the UIS/WITS-based workbooks) — it was compiled entry-by-entry from live web research. Every row carries its own source title, URL and publication date; open the link before relying on a figure for a decision.
A40: • "Investment Est. (US$ Million)" on the Companies sheet is the compiler's best-effort numeric read of the "Investment (as disclosed)" text in the same row — ranges use the midpoint, EUR figures are converted at roughly 1.08 USD/EUR, and an "up to $X" or "initial $X (potential up to $Y)" figure uses the stated $X. Where nothing was publicly disclosed, both the text and the number are marked accordingly and the row still scores (see Methodology) rather than being dropped.
A41: • A company or project with no strong, sourced, recent signal in a given industry/country/type combination was left out rather than padded with a weak or stale example — so an empty combination usually means "not found", not "doesn't exist".
A42: • UAE-linked entities (DP World, Gulftainer, Majid Al Futtaim, G42) recur across several countries — this matches the DIM_COUNTRY inclusion of UAE as a major investor into East Africa rather than as a fifth target market for this table.
A43: • The Kenya Gross County Product workbook (separate file) is Kenya-only, sub-national GDP data — it does not overlap with or substitute for this company/infrastructure research.
A44: • Recency Score bands were set to a 2020-2023 window at your request. Because almost every signal in this workbook is actually dated 2023-2026, nearly all rows now score the maximum 25 points here — this sub-score currently does not differentiate rows the way Investment, Facility Type and Infrastructure Synergy do. Say the word if you'd like it rebased to the years the data actually spans.
A45: • Megabrand de-emphasis: at your request, several rows that previously led with a globally-famous parent brand now lead with the real, less-famous entity actually operating on the ground — e.g. Kenya's Coca-Cola row now profiles Amsons Group's Bamburi Cement acquisition, Oracle's row now profiles Huawei's Konza Technopolis cloud data centre, Volkswagen's Kenya row now leads with local assembler Kenya Vehicle Manufacturers (KVM), and Ethiopia's Heineken/Carrefour/Mastercard rows now lead with their actual local operating partners (Komari Beverage, Queens Supermarket, EagleLion/StarPay) rather than the multinational name. Seven of the fourteen megabrand rows you flagged were swapped or relabeled this way, backed by the same sourcing standard as the rest of the sheet; the remaining seven (Microsoft, AWS and Majid Al Futtaim in Kenya; Volkswagen and BioNTech in Rwanda; Vodacom in Tanzania; MTN in Uganda) are left as the original global entity because no equally well-sourced regional alternative could be verified this session — a research-tool budget limit was hit partway through. These are flagged for a follow-up pass rather than guessed at.

Sheet Methodology
A1: Opportunity Score Methodology
A3: Opportunity Score (0-100) is a transparent, additive index built entirely from data already on the Companies sheet, computed live by formula — it recalculates automatically if you edit the underlying rows or the point bands below. It combines four signals: how large the disclosed investment is, how recent the signal is, how durable the facility type is (a plant or data centre implies more committed presence than a single retail store), and whether the country already has a strong infrastructure ecosystem (SEZs, parks, ports, data centres) to support it. It is a starting filter for prioritizing outreach, not a definitive ranking — adjust the bands below to match your own judgment.
A8: 1. Investment Score (max 40 pts) — from Investment Est. (US$ Million)
A9: Band | B9: Points
A10: >= $100 million | B10: 40
A11: $20M to <$100M | B11: 32
A12: $5M to <$20M | B12: 24
A13: $1M to <$5M | B13: 16
A14: > $0 to <$1M | B14: 8
A15: Not disclosed | B15: 12
A17: 2. Recency Score (max 25 pts) — from Signal Year
A18: Band | B18: Points
A19: 2023 or later | B19: 25
A20: 2022 | B20: 20
A21: 2021 | B21: 14
A22: 2020 | B22: 8
A23: Before 2020 / unclear | B23: 5
A25: 3. Facility Type Score (max 20 pts) — from Facility Type
A26: Facility Type | B26: Points
A27: Manufacturing Plant | B27: 20
A28: Data Centre | B28: 20
A29: Hospital/Pharma Plant | B29: 18
A30: Construction Project | B30: 16
A31: Distribution Center | B31: 14
A32: R&D Centre | B32: 14
A33: Regional HQ / Network Infrastructure | B33: 12
A34: Regional HQ | B34: 10
A35: Retail Store/Mall | B35: 8
A36: (any other / unlisted) | B36: 12
A38: 4. Infrastructure Synergy Score (max 15 pts) — from count of Infrastructure-sheet projects in the same country
A39: Band | B39: Points
A40: 4 or more infrastructure projects in that country | B40: 15
A41: 2-3 infrastructure projects in that country | B41: 10
A42: 1 infrastructure project in that country | B42: 5
A43: 0 infrastructure projects in that country | B43: 0
A45: Opportunity Tier (from total Opportunity Score)
A46: >= 70 | B46: High
A47: 50-69 | B47: Medium
A48: < 50 | B48: Watch

Sheet Companies
A1: Company Profile | F1: Expansion Signal | K1: Opportunity Scoring | Q1: Source
A2: Country | B2: Company | C2: Industry | D2: HQ | E2: East Africa Presence | F2: Expansion Signal | G2: Signal Year | H2: Investment (as disclosed) | I2: Investment Est. (US$ Million) | J2: Facility Type | K2: Investment Score | L2: Recency Score | M2: Facility Type Score | N2: Infrastructure Synergy Score | O2: Opportunity Score | P2: Opportunity Tier | Q2: Source Title | R2: Source URL | S2: Source Date
A3: Burundi | B3: SOSUMO (Société Sucrière du Moso) | C3: Manufacturing | D3: Bujumbura, Burundi (state-owned) | E3: SOSUMO operates Burundi's only sugar factory and sugarcane plantations in the Moso region, supplying the domestic sugar market. | F3: Burundi's Council of Ministers reviewed and endorsed progress on SOSUMO's rehabilitation, modernization and extension project (roadmap approved June 9, 2021), aimed at expanding milling capacity contingent on securing sugarcane supply. | G3: 2021 | H3: 105,993,995,058 BIF (~US$53M at 2021 rates) | I3: 53 | J3: Manufacturing Plant | K3: =IF(I3="",12,IF(I3>=100,40,IF(I3>=20,32,IF(I3>=5,24,IF(I3>=1,16,8))))) -> 32 | L3: =IF(G3="",5,IF(G3>=2023,25,IF(G3>=2022,20,IF(G3>=2021,14,IF(G3>=2020,8,5))))) -> 14 | M3: =IFERROR(INDEX(Methodology!$B$27:$B$36,MATCH(J3,Methodology!$A$27:$A$36,0)),12) -> 20 | N3: =IF(COUNTIF(Infrastructure!$A:$A,A3)>=4,15,IF(COUNTIF(Infrastructure!$A:$A,A3)>=2,10,IF(COUNTIF(Infrastructure!$A:$A,A3)>=1,5,0))) -> 5 | O3: =K3+L3+M3+N3 -> 71 | P3: =IF(O3>=70,"High",IF(O3>=50,"Medium","Watch")) -> High | Q3: The SOSUMO rehabilitation, modernization and extension project is reaching a satisfactory stage | R3: https://english.abpinfo.bi/2021/06/12/the-sosumo-rehabilitation-modernization-and-extension-project-is-reaching-a-satisfactory-stage/ | S3: 2021-06-12
A4: Burundi | B4: Lumitel (Viettel Burundi S.A.) | C4: Technology | D4: Hanoi, Vietnam (Viettel Group) | E4: Lumitel is Burundi's leading mobile operator, a subsidiary of Vietnam's Viettel Group operating 2G/3G/4G mobile, fixed and mobile-money services nationwide since 2015. | F4: Lumitel and the World Bank/PAFEN signed a $10M+ public-private broadband expansion contract (Lumitel contributing $5.62M, World Bank $4.37M) to bring high-speed internet to 86 hills across 14 provinces, launched March 2, 2026; this follows an earlier announced plan to invest $20M to extend 4G coverage to 75% of the population by 2030. | G4: 2026 | H4: $10M+ (World Bank $4.37M + Lumitel $5.62M) for the 2026 broadband project; separately, $20M announced for 4G expansion through 2030 | I4: 10 | J4: Regional HQ / Network Infrastructure | K4: =IF(I4="",12,IF(I4>=100,40,IF(I4>=20,32,IF(I4>=5,24,IF(I4>=1,16,8))))) -> 24 | L4: =IF(G4="",5,IF(G4>=2023,25,IF(G4>=2022,20,IF(G4>=2021,14,IF(G4>=2020,8,5))))) -> 25 | M4: =IFERROR(INDEX(Methodology!$B$27:$B$36,MATCH(J4,Methodology!$A$27:$A$36,0)),12) -> 12 | N4: =IF(COUNTIF(Infrastructure!$A:$A,A4)>=4,15,IF(COUNTIF(Infrastructure!$A:$A,A4)>=2,10,IF(COUNTIF(Infrastructure!$A:$A,A4)>=1,5,0))) -> 5 | O4: =K4+L4+M4+N4 -> 66 | P4: =IF(O4>=70,"High",IF(O4>=50,"Medium","Watch")) -> Medium | Q4: Lumitel Burundi Launches $10M High-Speed Internet Project Across the Country | R4: https://techafricanews.com/2026/03/04/lumitel-burundi-launches-10m-high-speed-internet-project-across-the-country/ | S4: 2026-03-04
A5: Comoros | B5: AD Ports Group (via Serdal International joint venture) | C5: Logistics | D5: Abu Dhabi, United Arab Emirates | E5: AD Ports Group entered Comoros through Serdal International, a joint venture with Abu Dhabi-based Resources Investment, to operate maritime trade and passenger/vehicle ferry services between the islands. | F5: Serdal International launched a new passenger-and-vehicle ferry service (vessel 'Yameela', 190 passengers/45 vehicles) connecting Moroni (Grande Comore) and Mutsamudu (Anjouan) on September 12, 2025, in a ceremony attended by the Comorian President. | G5: 2025 | H5: Not disclosed | J5: Distribution Center | K5: =IF(I5="",12,IF(I5>=100,40,IF(I5>=20,32,IF(I5>=5,24,IF(I5>=1,16,8))))) -> 12 | L5: =IF(G5="",5,IF(G5>=2023,25,IF(G5>=2022,20,IF(G5>=2021,14,IF(G5>=2020,8,5))))) -> 25 | M5: =IFERROR(INDEX(Methodology!$B$27:$B$36,MATCH(J5,Methodology!$A$27:$A$36,0)),12) -> 14 | N5: =IF(COUNTIF(Infrastructure!$A:$A,A5)>=4,15,IF(COUNTIF(Infrastructure!$A:$A,A5)>=2,10,IF(COUNTIF(Infrastructure!$A:$A,A5)>=1,5,0))) -> 10 | O5: =K5+L5+M5+N5 -> 61 | P5: =IF(O5>=70,"High",IF(O5>=50,"Medium","Watch")) -> Medium | Q5: Serdal International Launches New Passenger and Auto Ferry Service in The Comoros | R5: https://www.adportsgroup.com/en/news-and-media/2025/09/12/serdal-international-launches-new-passenger-and-auto-ferry-service-in-the-comoros | S5: 2025-09-12
A6: Comoros | B6: Axian Telecom (Yas Comoros / Telecom Comores SA) | C6: Technology | D6: Antananarivo, Madagascar | E6: Axian Telecom, via its Comoros subsidiary Telecom Comores SA (branded Yas Comoros), is the country's second mobile network operator, providing mobile, fixed broadband and mobile-money services across the archipelago. | F6: IFC approved (Dec 17, 2024) and signed (May 30, 2025) a senior secured loan of up to €25M (~US$27M) to Telecom Comores SA to fund capital expenditure and a 2024-2026 mobile network expansion program, including 5G and fibre-to-the-home/office rollout, disbursed October 10, 2025. | G6: 2024 | H6: Up to €25 million (~US$27 million) | I6: 27 | J6: Regional HQ / Network Infrastructure | K6: =IF(I6="",12,IF(I6>=100,40,IF(I6>=20,32,IF(I6>=5,24,IF(I6>=1,16,8))))) -> 32 | L6: =IF(G6="",5,IF(G6>=2023,25,IF(G6>=2022,20,IF(G6>=2021,14,IF(G6>=2020,8,5))))) -> 25 | M6: =IFERROR(INDEX(Methodology!$B$27:$B$36,MATCH(J6,Methodology!$A$27:$A$36,0)),12) -> 12 | N6: =IF(COUNTIF(Infrastructure!$A:$A,A6)>=4,15,IF(COUNTIF(Infrastructure!$A:$A,A6)>=2,10,IF(COUNTIF(Infrastructure!$A:$A,A6)>=1,5,0))) -> 10 | O6: =K6+L6+M6+N6 -> 79 | P6: =IF(O6>=70,"High",IF(O6>=50,"Medium","Watch")) -> High | Q6: 49849 - Axian Comoros II & Tanzania | R6: https://disclosures.ifc.org/project-detail/ESRS/49849/axian-comoros-ii-tanzania | S6: 2025-10-10
A7: Djibouti | B7: Golden Africa Djibouti (HSA Group / Pacific Inter-Link) | C7: Manufacturing | D7: Sana'a, Yemen (HSA Group) | E7: Golden Africa operates an edible-oil refining and packing complex next to Doraleh port, exporting palm and sunflower oil products to Ethiopia, Somalia, Yemen and beyond. | F7: Following its ~$30M initial investment, the company announced a further $5 million investment in new machinery to raise monthly processing capacity, alongside plans for a soap manufacturing facility. | G7: 2019 | H7: $5 million (capacity-expansion phase); $30 million (original facility) | I7: 5 | J7: Manufacturing Plant | K7: =IF(I7="",12,IF(I7>=100,40,IF(I7>=20,32,IF(I7>=5,24,IF(I7>=1,16,8))))) -> 24 | L7: =IF(G7="",5,IF(G7>=2023,25,IF(G7>=2022,20,IF(G7>=2021,14,IF(G7>=2020,8,5))))) -> 5 | M7: =IFERROR(INDEX(Methodology!$B$27:$B$36,MATCH(J7,Methodology!$A$27:$A$36,0)),12) -> 20 | N7: =IF(COUNTIF(Infrastructure!$A:$A,A7)>=4,15,IF(COUNTIF(Infrastructure!$A:$A,A7)>=2,10,IF(COUNTIF(Infrastructure!$A:$A,A7)>=1,5,0))) -> 10 | O7: =K7+L7+M7+N7 -> 59 | P7: =IF(O7>=70,"High",IF(O7>=50,"Medium","Watch")) -> Medium | Q7: Palm oil: Golden Africa thinks big in East Africa | R7: https://www.theafricareport.com/22460/palm-oil-golden-africa-thinks-big-in-east-africa/ | S7: 2019
A8: Djibouti | B8: Saudi Ajyal Petroleum and Energy Company | C8: Manufacturing | D8: Saudi Arabia | E8: Saudi Ajyal is developing a large-scale oil refinery in the Djibouti Damerjog International Park (DDIP), positioned to serve regional Horn of Africa fuel demand. | F8: Cornerstone for a 300,000 barrels-per-day refinery on 300 hectares in DDIP was laid in June 2024, expected to create roughly 10,000 direct jobs. | G8: 2024 | H8: $12.7 billion | I8: 12700 | J8: Manufacturing Plant | K8: =IF(I8="",12,IF(I8>=100,40,IF(I8>=20,32,IF(I8>=5,24,IF(I8>=1,16,8))))) -> 40 | L8: =IF(G8="",5,IF(G8>=2023,25,IF(G8>=2022,20,IF(G8>=2021,14,IF(G8>=2020,8,5))))) -> 25 | M8: =IFERROR(INDEX(Methodology!$B$27:$B$36,MATCH(J8,Methodology!$A$27:$A$36,0)),12) -> 20 | N8: =IF(COUNTIF(Infrastructure!$A:$A,A8)>=4,15,IF(COUNTIF(Infrastructure!$A:$A,A8)>=2,10,IF(COUNTIF(Infrastructure!$A:$A,A8)>=1,5,0))) -> 10 | O8: =K8+L8+M8+N8 -> 95 | P8: =IF(O8>=70,"High",IF(O8>=50,"Medium","Watch")) -> High | Q8: Saudi Arabia expands footprint in Djibouti with major investment projects | R8: https://capitalethiopia.com/2024/07/01/saudi-arabia-expands-footprint-in-djibouti-with-major-investment-projects/ | S8: 2024-07-01
A9: Djibouti | B9: China Merchants Port Holdings Company Limited | C9: Logistics | D9: Hong Kong / Shenzhen, China | E9: China Merchants holds a 23.5% stake in the Port of Djibouti and is a key investor/co-developer in the Djibouti International Free Trade Zone (DIFTZ). | F9: China Merchants signed a deal on January 8, 2021 to fund a $3 billion expansion of Djibouti City port and DIFTZ, building on an initial $513 million phase that began October 8, 2020. | G9: 2021 | H9: $3 billion (expansion agreement); $513 million (initial phase) | I9: 3000 | J9: Distribution Center | K9: =IF(I9="",12,IF(I9>=100,40,IF(I9>=20,32,IF(I9>=5,24,IF(I9>=1,16,8))))) -> 40 | L9: =IF(G9="",5,IF(G9>=2023,25,IF(G9>=2022,20,IF(G9>=2021,14,IF(G9>=2020,8,5))))) -> 14 | M9: =IFERROR(INDEX(Methodology!$B$27:$B$36,MATCH(J9,Methodology!$A$27:$A$36,0)),12) -> 14 | N9: =IF(COUNTIF(Infrastructure!$A:$A,A9)>=4,15,IF(COUNTIF(Infrastructure!$A:$A,A9)>=2,10,IF(COUNTIF(Infrastructure!$A:$A,A9)>=1,5,0))) -> 10 | O9: =K9+L9+M9+N9 -> 78 | P9: =IF(O9>=70,"High",IF(O9>=50,"Medium","Watch")) -> High | Q9: China Merchants signs deal for $3bn expansion of Djibouti City port | R9: https://www.globalconstructionreview.com/china-merchants-signs-deal-3bn-expansion-djibouti/ | S9: 2021-01-08
A10: Djibouti | B10: PAIX Data Centres | C10: Technology | D10: Netherlands | E10: PAIX is entering Djibouti to build a cloud- and carrier-neutral data centre leveraging Djibouti's position as a landing point for roughly ten undersea cables. | F10: PAIX signed a joint-venture/MOU with the Djibouti Sovereign Wealth Fund (announced May 16, 2024) to build a ~50,000 sq ft, up to 5MW data centre, with the first phase expected to open in 2026. | G10: 2024 | H10: $50 million | I10: 50 | J10: Data Centre | K10: =IF(I10="",12,IF(I10>=100,40,IF(I10>=20,32,IF(I10>=5,24,IF(I10>=1,16,8))))) -> 32 | L10: =IF(G10="",5,IF(G10>=2023,25,IF(G10>=2022,20,IF(G10>=2021,14,IF(G10>=2020,8,5))))) -> 25 | M10: =IFERROR(INDEX(Methodology!$B$27:$B$36,MATCH(J10,Methodology!$A$27:$A$36,0)),12) -> 20 | N10: =IF(COUNTIF(Infrastructure!$A:$A,A10)>=4,15,IF(COUNTIF(Infrastructure!$A:$A,A10)>=2,10,IF(COUNTIF(Infrastructure!$A:$A,A10)>=1,5,0))) -> 10 | O10: =K10+L10+M10+N10 -> 87 | P10: =IF(O10>=70,"High",IF(O10>=50,"Medium","Watch")) -> High | Q10: PAIX to Construct Carrier-neutral Data Center in Djibouti | R10: https://www.submarinenetworks.com/en/stations/africa/djibouti/paix-to-construct-carrier-neutral-data-center-in-djibouti | S10: 2024-05-16
A11: DRC Congo | B11: CIMKO (Cimenterie Kongo) | C11: Manufacturing | D11: Songololo, Kongo-Central, DRC | E11: CIMKO operates DRC's largest integrated cement plant at Songololo, Kongo-Central, supplying the Kinshasa/western DRC market since 2018. | F11: CIMKO announced a $300m+ investment to double annual cement capacity from 1.4Mt to 3Mt by 2027, announced 5 December 2025. | G11: 2027 | H11: More than US$300 million | I11: 300 | J11: Manufacturing Plant | K11: =IF(I11="",12,IF(I11>=100,40,IF(I11>=20,32,IF(I11>=5,24,IF(I11>=1,16,8))))) -> 40 | L11: =IF(G11="",5,IF(G11>=2023,25,IF(G11>=2022,20,IF(G11>=2021,14,IF(G11>=2020,8,5))))) -> 25 | M11: =IFERROR(INDEX(Methodology!$B$27:$B$36,MATCH(J11,Methodology!$A$27:$A$36,0)),12) -> 20 | N11: =IF(COUNTIF(Infrastructure!$A:$A,A11)>=4,15,IF(COUNTIF(Infrastructure!$A:$A,A11)>=2,10,IF(COUNTIF(Infrastructure!$A:$A,A11)>=1,5,0))) -> 10 | O11: =K11+L11+M11+N11 -> 95 | P11: =IF(O11>=70,"High",IF(O11>=50,"Medium","Watch")) -> High | Q11: CIMKO to invest US$300m to double DRC cement capacity by 2027 | R11: https://www.cemnet.com/News/story/180401/cimko-to-invest-us-300m-to-double-drc-cement-capacity-by-2027.html | S11: 45265
A12: DRC Congo | B12: Africa Global Logistics (MSC Group) | C12: Logistics | D12: Geneva, Switzerland | E12: Following MSC's acquisition of Bolloré Africa Logistics, Africa Global Logistics operates freight-forwarding, dry-port and transport logistics infrastructure in DRC. | F12: MSC completed its $6.1 billion acquisition of Bolloré Africa Logistics, covering its DRC logistics operations, on 21 December 2022. | G12: 2022 | H12: US$6.1 billion (pan-African acquisition, not DRC-specific) | I12: 6100 | J12: Distribution Center | K12: =IF(I12="",12,IF(I12>=100,40,IF(I12>=20,32,IF(I12>=5,24,IF(I12>=1,16,8))))) -> 40 | L12: =IF(G12="",5,IF(G12>=2023,25,IF(G12>=2022,20,IF(G12>=2021,14,IF(G12>=2020,8,5))))) -> 20 | M12: =IFERROR(INDEX(Methodology!$B$27:$B$36,MATCH(J12,Methodology!$A$27:$A$36,0)),12) -> 14 | N12: =IF(COUNTIF(Infrastructure!$A:$A,A12)>=4,15,IF(COUNTIF(Infrastructure!$A:$A,A12)>=2,10,IF(COUNTIF(Infrastructure!$A:$A,A12)>=1,5,0))) -> 10 | O12: =K12+L12+M12+N12 -> 84 | P12: =IF(O12>=70,"High",IF(O12>=50,"Medium","Watch")) -> High | Q12: MSC Completes Acquisition of Bolloré Africa Logistics | R12: https://maritime-executive.com/article/msc-completes-acquisition-of-bollore-africa-logistics | S12: 2022-12-21
A13: DRC Congo | B13: Carrefour (via franchise partner Hyper Psaro) | C13: Retail | D13: Massy, France | E13: Carrefour entered the DRC market via a franchise partnership with Hyper Psaro, opening its first hypermarket in Kinshasa. | F13: Carrefour opened its first DRC hypermarket in Kinshasa, reported in coverage published 11 August 2025. | G13: 2025 | H13: Not disclosed | J13: Retail Store/Mall | K13: =IF(I13="",12,IF(I13>=100,40,IF(I13>=20,32,IF(I13>=5,24,IF(I13>=1,16,8))))) -> 12 | L13: =IF(G13="",5,IF(G13>=2023,25,IF(G13>=2022,20,IF(G13>=2021,14,IF(G13>=2020,8,5))))) -> 25 | M13: =IFERROR(INDEX(Methodology!$B$27:$B$36,MATCH(J13,Methodology!$A$27:$A$36,0)),12) -> 8 | N13: =IF(COUNTIF(Infrastructure!$A:$A,A13)>=4,15,IF(COUNTIF(Infrastructure!$A:$A,A13)>=2,10,IF(COUNTIF(Infrastructure!$A:$A,A13)>=1,5,0))) -> 10 | O13: =K13+L13+M13+N13 -> 55 | P13: =IF(O13>=70,"High",IF(O13>=50,"Medium","Watch")) -> Medium | Q13: First Carrefour supermarket opens in Democratic Republic of Congo | R13: https://africanmarketingconfederation.org/first-carrefour-supermarket-opens-in-democratic-republic-of-congo/ | S13: 45149
A14: DRC Congo | B14: Vodacom Congo (with Orange DRC) | C14: Technology | D14: Johannesburg, South Africa | E14: Vodacom and Orange are DRC's two largest mobile operators; together they formed a new rural towerco joint venture. | F14: Vodacom and Orange announced (14 January 2025) a joint venture to build up to 2,000 solar-powered base stations over six years to extend coverage to ~19 million people in rural DRC. | G14: 2025 | H14: Not disclosed | J14: Regional HQ / Network Infrastructure | K14: =IF(I14="",12,IF(I14>=100,40,IF(I14>=20,32,IF(I14>=5,24,IF(I14>=1,16,8))))) -> 12 | L14: =IF(G14="",5,IF(G14>=2023,25,IF(G14>=2022,20,IF(G14>=2021,14,IF(G14>=2020,8,5))))) -> 25 | M14: =IFERROR(INDEX(Methodology!$B$27:$B$36,MATCH(J14,Methodology!$A$27:$A$36,0)),12) -> 12 | N14: =IF(COUNTIF(Infrastructure!$A:$A,A14)>=4,15,IF(COUNTIF(Infrastructure!$A:$A,A14)>=2,10,IF(COUNTIF(Infrastructure!$A:$A,A14)>=1,5,0))) -> 10 | O14: =K14+L14+M14+N14 -> 59 | P14: =IF(O14>=70,"High",IF(O14>=50,"Medium","Watch")) -> Medium | Q14: Orange and Vodacom create a joint venture to expand network coverage in rural areas in the DRC | R14: https://www.vodacom.com/news-article.php?articleID=15301 | S14: 44940
A15: Eritrea | B15: Sichuan Road and Bridge Group | C15: Construction | D15: Chengdu, Sichuan, China | E15: Sichuan Road and Bridge Group acquired Australian miner Danakali's 50% stake in the Colluli potash project in Eritrea. | F15: Sichuan Road and Bridge Group completed its purchase of Danakali's 50% Colluli potash project stake, with a first $105 million instalment paid by 31 March 2023. | G15: 2023 | H15: US$105 million (first instalment) plus a further US$16 million tranche | I15: 105 | J15: Construction Project | K15: =IF(I15="",12,IF(I15>=100,40,IF(I15>=20,32,IF(I15>=5,24,IF(I15>=1,16,8))))) -> 40 | L15: =IF(G15="",5,IF(G15>=2023,25,IF(G15>=2022,20,IF(G15>=2021,14,IF(G15>=2020,8,5))))) -> 25 | M15: =IFERROR(INDEX(Methodology!$B$27:$B$36,MATCH(J15,Methodology!$A$27:$A$36,0)),12) -> 16 | N15: =IF(COUNTIF(Infrastructure!$A:$A,A15)>=4,15,IF(COUNTIF(Infrastructure!$A:$A,A15)>=2,10,IF(COUNTIF(Infrastructure!$A:$A,A15)>=1,5,0))) -> 5 | O15: =K15+L15+M15+N15 -> 86 | P15: =IF(O15>=70,"High",IF(O15>=50,"Medium","Watch")) -> High | Q15: Danakali sells stake in flagship Colluli potash project in Eritrea | R15: https://www.mining.com/danakali-sells-stake-in-flagship-colluli-potash-project-in-eritrea/ | S15: 2023-03-31
A16: Ethiopia | B16: Dangote Group | C16: Manufacturing | D16: Lagos, Nigeria | E16: Dangote has operated a cement plant in Mugher, Ethiopia since 2015 and has now signed a joint venture with Ethiopian Investment Holdings to build one of the world's largest fertiliser plants in Gode. | F16: Signed a JV (Dangote 60% / Ethiopian Investment Holdings 40%) to build a $2.5B fertiliser plant in Gode, southeast Ethiopia, targeting ~3 million tonnes/year production; signed August 29, 2025. | G16: 2025 | H16: $2.5 billion | I16: 2500 | J16: Manufacturing Plant | K16: =IF(I16="",12,IF(I16>=100,40,IF(I16>=20,32,IF(I16>=5,24,IF(I16>=1,16,8))))) -> 40 | L16: =IF(G16="",5,IF(G16>=2023,25,IF(G16>=2022,20,IF(G16>=2021,14,IF(G16>=2020,8,5))))) -> 25 | M16: =IFERROR(INDEX(Methodology!$B$27:$B$36,MATCH(J16,Methodology!$A$27:$A$36,0)),12) -> 20 | N16: =IF(COUNTIF(Infrastructure!$A:$A,A16)>=4,15,IF(COUNTIF(Infrastructure!$A:$A,A16)>=2,10,IF(COUNTIF(Infrastructure!$A:$A,A16)>=1,5,0))) -> 15 | O16: =K16+L16+M16+N16 -> 100 | P16: =IF(O16>=70,"High",IF(O16>=50,"Medium","Watch")) -> High | Q16: Nigeria: Dangote Group, Ethiopia Sign Deal to Build $2.5bn Fertiliser Plant | R16: https://allafrica.com/stories/202508290063.html | S16: August 29, 2023
A17: Ethiopia | B17: Komari Beverage (Arada) — acquired by Heineken N.V. | C17: Manufacturing | D17: Amhara Region, Ethiopia (parent: Heineken N.V., Amsterdam, Netherlands) | E17: Heineken has operated breweries in Ethiopia since 2011 (Kilinto, Harar, Bedele) as part of a EUR310M+ cumulative investment, and diversified via acquisition into the local spirits/hard-seltzer category. | F17: Acquired ownership of the Arada hard-seltzer brand from Ethiopian producer Komari Beverage (which built a $29M+ factory in Amhara region); deal concluded mid-October 2024. | G17: 2024 | H17: Not disclosed | J17: Manufacturing Plant | K17: =IF(I17="",12,IF(I17>=100,40,IF(I17>=20,32,IF(I17>=5,24,IF(I17>=1,16,8))))) -> 12 | L17: =IF(G17="",5,IF(G17>=2023,25,IF(G17>=2022,20,IF(G17>=2021,14,IF(G17>=2020,8,5))))) -> 25 | M17: =IFERROR(INDEX(Methodology!$B$27:$B$36,MATCH(J17,Methodology!$A$27:$A$36,0)),12) -> 20 | N17: =IF(COUNTIF(Infrastructure!$A:$A,A17)>=4,15,IF(COUNTIF(Infrastructure!$A:$A,A17)>=2,10,IF(COUNTIF(Infrastructure!$A:$A,A17)>=1,5,0))) -> 15 | O17: =K17+L17+M17+N17 -> 72 | P17: =IF(O17>=70,"High",IF(O17>=50,"Medium","Watch")) -> High | Q17: Heineken acquires Komari Beverage | R17: https://capitalethiopia.com/2024/10/14/heineken-acquires-komari-beverage/ | S17: October 14, 2024
A18: Ethiopia | B18: TOYO Co., Ltd (TOYO Solar) | C18: Manufacturing | D18: Tokyo, Japan (with production also in Vietnam) | E18: Built its first East African manufacturing base inside Hawassa's special economic zone, using Ethiopia's largely hydropower-based grid to supply its US solar module plant. | F18: Began commercial production at its 2GW (expanding to 4GW) TOPCon solar cell plant in Hawassa; production start April 2025. | G18: 2025 | H18: $60 million (initial phase) | I18: 60 | J18: Manufacturing Plant | K18: =IF(I18="",12,IF(I18>=100,40,IF(I18>=20,32,IF(I18>=5,24,IF(I18>=1,16,8))))) -> 32 | L18: =IF(G18="",5,IF(G18>=2023,25,IF(G18>=2022,20,IF(G18>=2021,14,IF(G18>=2020,8,5))))) -> 25 | M18: =IFERROR(INDEX(Methodology!$B$27:$B$36,MATCH(J18,Methodology!$A$27:$A$36,0)),12) -> 20 | N18: =IF(COUNTIF(Infrastructure!$A:$A,A18)>=4,15,IF(COUNTIF(Infrastructure!$A:$A,A18)>=2,10,IF(COUNTIF(Infrastructure!$A:$A,A18)>=1,5,0))) -> 15 | O18: =K18+L18+M18+N18 -> 92 | P18: =IF(O18>=70,"High",IF(O18>=50,"Medium","Watch")) -> High | Q18: Japan's Toyo begins production at 2 GW solar cell plant in Ethiopia | R18: https://www.pv-magazine.com/2025/04/23/japans-toyo-begins-production-at-2-gw-solar-cell-plant-in-ethiopia/ | S18: April 23, 2023
A19: Ethiopia | B19: DHL Group | C19: Logistics | D19: Bonn, Germany | E19: DHL Express operates in Ethiopia and was explicitly named alongside Nigeria as a priority market for gateway and aviation-capacity upgrades under DHL's new Africa investment plan. | F19: Announced EUR300M+ investment across sub-Saharan Africa, citing recent growth in Ethiopia and Nigeria and plans to upgrade gateways, add aviation uplift, and expand into second-tier cities; announced October 15, 2025. | G19: 2025 | H19: EUR300 million+ (regional; Ethiopia-specific allocation not disclosed) | J19: Distribution Center | K19: =IF(I19="",12,IF(I19>=100,40,IF(I19>=20,32,IF(I19>=5,24,IF(I19>=1,16,8))))) -> 12 | L19: =IF(G19="",5,IF(G19>=2023,25,IF(G19>=2022,20,IF(G19>=2021,14,IF(G19>=2020,8,5))))) -> 25 | M19: =IFERROR(INDEX(Methodology!$B$27:$B$36,MATCH(J19,Methodology!$A$27:$A$36,0)),12) -> 14 | N19: =IF(COUNTIF(Infrastructure!$A:$A,A19)>=4,15,IF(COUNTIF(Infrastructure!$A:$A,A19)>=2,10,IF(COUNTIF(Infrastructure!$A:$A,A19)>=1,5,0))) -> 15 | O19: =K19+L19+M19+N19 -> 66 | P19: =IF(O19>=70,"High",IF(O19>=50,"Medium","Watch")) -> Medium | Q19: DHL Group commits more than EUR300 million to accelerate trade growth across Africa | R19: https://group.dhl.com/en/media-relations/press-releases/2025/dhl-group-commits-more-than-300-million-to-accelerate-trade-growth-across-africa.html | S19: October 15, 2023
A20: Ethiopia | B20: Ethiopian Airlines Group | C20: Logistics | D20: Addis Ababa, Ethiopia | E20: Africa's largest airline/cargo group, operating from its Bole hub with a continent-wide freight network. | F20: Opened a new $55M e-commerce/cargo sorting hub at Bole International Airport built to serve Alibaba and Shein, with 150,000-tonne annual capacity; inaugurated February 29, 2024. | G20: 2024 | H20: $55 million | I20: 55 | J20: Distribution Center | K20: =IF(I20="",12,IF(I20>=100,40,IF(I20>=20,32,IF(I20>=5,24,IF(I20>=1,16,8))))) -> 32 | L20: =IF(G20="",5,IF(G20>=2023,25,IF(G20>=2022,20,IF(G20>=2021,14,IF(G20>=2020,8,5))))) -> 25 | M20: =IFERROR(INDEX(Methodology!$B$27:$B$36,MATCH(J20,Methodology!$A$27:$A$36,0)),12) -> 14 | N20: =IF(COUNTIF(Infrastructure!$A:$A,A20)>=4,15,IF(COUNTIF(Infrastructure!$A:$A,A20)>=2,10,IF(COUNTIF(Infrastructure!$A:$A,A20)>=1,5,0))) -> 15 | O20: =K20+L20+M20+N20 -> 86 | P20: =IF(O20>=70,"High",IF(O20>=50,"Medium","Watch")) -> High | Q20: Ethiopian Airlines Opens $55 Million Cargo Center At Addis Ababa Airport | R20: https://simpleflying.com/ethiopian-airlines-55-million-cargo-center-addis-ababa-airport/ | S20: February 2024
A21: Ethiopia | B21: Queens Supermarket PLC (Midroc Investment Group) — Carrefour franchise partner | C21: Retail | D21: Addis Ababa, Ethiopia (franchise partner of Carrefour Group, Massy, France) | E21: New market entrant; franchise agreement with Queens Supermarket PLC (a Midroc Investment Group subsidiary) will rebrand Queens' 13 existing stores and add new locations. | F21: Signed a franchise deal with Queens Supermarket/Midroc to enter Ethiopia - first Carrefour-branded stores from Q1 2026, with 17 additional stores planned by 2028; announced January 2026, following Ethiopia's opening of retail to foreign investment. | G21: 2026 | H21: Not disclosed | J21: Retail Store/Mall | K21: =IF(I21="",12,IF(I21>=100,40,IF(I21>=20,32,IF(I21>=5,24,IF(I21>=1,16,8))))) -> 12 | L21: =IF(G21="",5,IF(G21>=2023,25,IF(G21>=2022,20,IF(G21>=2021,14,IF(G21>=2020,8,5))))) -> 25 | M21: =IFERROR(INDEX(Methodology!$B$27:$B$36,MATCH(J21,Methodology!$A$27:$A$36,0)),12) -> 8 | N21: =IF(COUNTIF(Infrastructure!$A:$A,A21)>=4,15,IF(COUNTIF(Infrastructure!$A:$A,A21)>=2,10,IF(COUNTIF(Infrastructure!$A:$A,A21)>=1,5,0))) -> 15 | O21: =K21+L21+M21+N21 -> 60 | P21: =IF(O21>=70,"High",IF(O21>=50,"Medium","Watch")) -> Medium | Q21: Carrefour's entry marks a new era for foreign investment in the retail sector | R21: https://capitalethiopia.com/2026/01/11/carrefours-entry-marks-a-new-era-for-foreign-investment-in-the-retail-sector/ | S21: January 11, 2026
A22: Ethiopia | B22: Roha Group (Roha Medical Campus) | C22: Pharma | D22: United States | E22: Building Ethiopia's first JCI-accredited, 350-bed multispecialty hospital in Addis Ababa, positioned as the anchor of a planned African medical-tourism hub. | F22: Received first $42M equity tranche (of a $130M Phase 1) to fund construction of Roha Medical Campus hospital near Bole International Airport; announced February 22, 2024. | G22: 2024 | H22: $42 million (initial tranche; $130M Phase 1 total) | I22: 42 | J22: Hospital/Pharma Plant | K22: =IF(I22="",12,IF(I22>=100,40,IF(I22>=20,32,IF(I22>=5,24,IF(I22>=1,16,8))))) -> 32 | L22: =IF(G22="",5,IF(G22>=2023,25,IF(G22>=2022,20,IF(G22>=2021,14,IF(G22>=2020,8,5))))) -> 25 | M22: =IFERROR(INDEX(Methodology!$B$27:$B$36,MATCH(J22,Methodology!$A$27:$A$36,0)),12) -> 18 | N22: =IF(COUNTIF(Infrastructure!$A:$A,A22)>=4,15,IF(COUNTIF(Infrastructure!$A:$A,A22)>=2,10,IF(COUNTIF(Infrastructure!$A:$A,A22)>=1,5,0))) -> 15 | O22: =K22+L22+M22+N22 -> 90 | P22: =IF(O22>=70,"High",IF(O22>=50,"Medium","Watch")) -> High | Q22: Roha Medical Campus, a World-Class Hospital in Ethiopia, Gets $42 Million First Injection | R22: https://www.businesswire.com/news/home/20240222253596/en/Roha-Medical-Campus-a-World-Class-Hospital-in-Ethiopia-Gets-$42-Million-First-Injection | S22: February 22, 2024
A23: Ethiopia | B23: TechInvention Lifecare | C23: Pharma | D23: Mumbai, India | E23: New advisory partnership with Ethiopia's Ministry of Health to design the country's first local vaccine-manufacturing facility. | F23: Signed agreement with Ethiopia's Ministry of Health for feasibility studies, facility design, and technology-transfer support for a national vaccine plant; signed January 7, 2025, Addis Ababa. | G23: 2025 | H23: Not disclosed | J23: Hospital/Pharma Plant | K23: =IF(I23="",12,IF(I23>=100,40,IF(I23>=20,32,IF(I23>=5,24,IF(I23>=1,16,8))))) -> 12 | L23: =IF(G23="",5,IF(G23>=2023,25,IF(G23>=2022,20,IF(G23>=2021,14,IF(G23>=2020,8,5))))) -> 25 | M23: =IFERROR(INDEX(Methodology!$B$27:$B$36,MATCH(J23,Methodology!$A$27:$A$36,0)),12) -> 18 | N23: =IF(COUNTIF(Infrastructure!$A:$A,A23)>=4,15,IF(COUNTIF(Infrastructure!$A:$A,A23)>=2,10,IF(COUNTIF(Infrastructure!$A:$A,A23)>=1,5,0))) -> 15 | O23: =K23+L23+M23+N23 -> 70 | P23: =IF(O23>=70,"High",IF(O23>=50,"Medium","Watch")) -> High | Q23: TechInvention Joins Hands with Ethiopia to Boost Vaccine Manufacturing and Pandemic Preparedness | R23: https://ehealth.eletsonline.com/2025/01/techinvention-joins-hands-with-ethiopia-to-boost-vaccine-manufacturing-and-pandemic-preparedness/ | S23: 44927
A24: Ethiopia | B24: EagleLion System Technology (StarPay Financial Services / Choice Microfinance) — Mastercard partner | C24: Technology | D24: Addis Ababa, Ethiopia (partner network for Mastercard, Purchase, New York, USA) | E24: Expanding Ethiopian payments footprint through local fintech partnerships as the country's digital-payments market opens up. | F24: Signed dual strategic partnerships with StarPay Financial Services (reseller/distributor of Mastercard products) and Choice Microfinance (digital credit for underserved segments), both EagleLion subsidiaries; announced April 11, 2026. | G24: 2026 | H24: Not disclosed | J24: Regional HQ | K24: =IF(I24="",12,IF(I24>=100,40,IF(I24>=20,32,IF(I24>=5,24,IF(I24>=1,16,8))))) -> 12 | L24: =IF(G24="",5,IF(G24>=2023,25,IF(G24>=2022,20,IF(G24>=2021,14,IF(G24>=2020,8,5))))) -> 25 | M24: =IFERROR(INDEX(Methodology!$B$27:$B$36,MATCH(J24,Methodology!$A$27:$A$36,0)),12) -> 10 | N24: =IF(COUNTIF(Infrastructure!$A:$A,A24)>=4,15,IF(COUNTIF(Infrastructure!$A:$A,A24)>=2,10,IF(COUNTIF(Infrastructure!$A:$A,A24)>=1,5,0))) -> 15 | O24: =K24+L24+M24+N24 -> 62 | P24: =IF(O24>=70,"High",IF(O24>=50,"Medium","Watch")) -> Medium | Q24: Mastercard expands footprint through dual strategic partnerships | R24: https://capitalethiopia.com/2026/04/11/mastercard-expands-footprint-through-dual-strategic-partnerships/ | S24: April 11, 2023
A25: Ethiopia | B25: Raxio Group | C25: Technology | D25: Kampala, Uganda | E25: Pan-African data centre operator (Uganda, DRC, Mozambique, Cote d'Ivoire) that entered Ethiopia with its flagship East African facility. | F25: Launched ET1, a Tier III, 3MW/800-rack data centre in Addis Ababa's Ethio ICT Park; opened November 2023. | G25: 2023 | H25: Not disclosed | J25: Data Centre | K25: =IF(I25="",12,IF(I25>=100,40,IF(I25>=20,32,IF(I25>=5,24,IF(I25>=1,16,8))))) -> 12 | L25: =IF(G25="",5,IF(G25>=2023,25,IF(G25>=2022,20,IF(G25>=2021,14,IF(G25>=2020,8,5))))) -> 25 | M25: =IFERROR(INDEX(Methodology!$B$27:$B$36,MATCH(J25,Methodology!$A$27:$A$36,0)),12) -> 20 | N25: =IF(COUNTIF(Infrastructure!$A:$A,A25)>=4,15,IF(COUNTIF(Infrastructure!$A:$A,A25)>=2,10,IF(COUNTIF(Infrastructure!$A:$A,A25)>=1,5,0))) -> 15 | O25: =K25+L25+M25+N25 -> 72 | P25: =IF(O25>=70,"High",IF(O25>=50,"Medium","Watch")) -> High | Q25: Raxio launches data center in Addis Ababa, Ethiopia | R25: https://www.datacenterdynamics.com/en/news/raxio-launches-data-center-in-addis-ababa-ethiopia/ | S25: November 2023
A26: Ethiopia | B26: Safaricom Ethiopia (Safaricom PLC / Vodacom-Vodafone consortium) | C26: Technology | D26: Nairobi, Kenya | E26: Ethiopia's first competing mobile network operator since license launch in 2022; passed 10 million active customers by mid-2025 and continues nationwide network buildout. | F26: Secured a $138M syndicated loan from Standard Bank Group for continued Ethiopian network expansion; announced December 11, 2025. | G26: 2025 | H26: $138 million | I26: 138 | J26: Regional HQ / Network Infrastructure | K26: =IF(I26="",12,IF(I26>=100,40,IF(I26>=20,32,IF(I26>=5,24,IF(I26>=1,16,8))))) -> 40 | L26: =IF(G26="",5,IF(G26>=2023,25,IF(G26>=2022,20,IF(G26>=2021,14,IF(G26>=2020,8,5))))) -> 25 | M26: =IFERROR(INDEX(Methodology!$B$27:$B$36,MATCH(J26,Methodology!$A$27:$A$36,0)),12) -> 12 | N26: =IF(COUNTIF(Infrastructure!$A:$A,A26)>=4,15,IF(COUNTIF(Infrastructure!$A:$A,A26)>=2,10,IF(COUNTIF(Infrastructure!$A:$A,A26)>=1,5,0))) -> 15 | O26: =K26+L26+M26+N26 -> 92 | P26: =IF(O26>=70,"High",IF(O26>=50,"Medium","Watch")) -> High | Q26: Standard Bank, led by Sim Tshabalala, backs Safaricom Ethiopia with $138 million funding push | R26: https://www.billionaires.africa/2025/12/11/standard-bank-safaricom-ethiopia-138m-funding/ | S26: December 11, 2023
A27: Ethiopia | B27: China Civil Engineering Construction Corporation (CCECC) | C27: Construction | D27: Beijing, China | E27: Longtime Ethiopian infrastructure contractor (Addis Ababa-Djibouti railway, Hawassa & Dire Dawa industrial parks, Modjo dry port expansion); now building a new special economic zone. | F27: Broke ground on the Lume Free Trade Zone within the new Gada Special Economic Zone in Oromia (~65km SE of Addis Ababa), Ethiopia's second free trade zone; groundbreaking May 10, 2024. | G27: 2024 | H27: Not disclosed | J27: Construction Project | K27: =IF(I27="",12,IF(I27>=100,40,IF(I27>=20,32,IF(I27>=5,24,IF(I27>=1,16,8))))) -> 12 | L27: =IF(G27="",5,IF(G27>=2023,25,IF(G27>=2022,20,IF(G27>=2021,14,IF(G27>=2020,8,5))))) -> 25 | M27: =IFERROR(INDEX(Methodology!$B$27:$B$36,MATCH(J27,Methodology!$A$27:$A$36,0)),12) -> 16 | N27: =IF(COUNTIF(Infrastructure!$A:$A,A27)>=4,15,IF(COUNTIF(Infrastructure!$A:$A,A27)>=2,10,IF(COUNTIF(Infrastructure!$A:$A,A27)>=1,5,0))) -> 15 | O27: =K27+L27+M27+N27 -> 68 | P27: =IF(O27>=70,"High",IF(O27>=50,"Medium","Watch")) -> Medium | Q27: Ethiopia launches construction of Chinese-contracted economic zone | R27: https://eng.yidaiyilu.gov.cn/p/0M376K98.html | S27: May 10, 2024
A28: Kenya | B28: Amsons Industries (K) Ltd (Amsons Group) | C28: Manufacturing | D28: Dar es Salaam, Tanzania | E28: Amsons Group is a Tanzanian family-owned conglomerate active in cement, bulk petroleum, wheat milling and LPG across Tanzania, Burundi, DR Congo, Mozambique and Zambia, generating over $1 billion in annual turnover; its Kenyan subsidiary Amsons Industries (K) Ltd is moving to take control of Bamburi Cement, Kenya's largest cement producer. | F28: Launched a mandatory buyout offer for all shares of Bamburi Cement Plc at KSh65/share (a 44% premium), a deal valued at roughly KSh 23.59 billion, to acquire Holcim's 58.6% stake and delist Bamburi from the Nairobi Securities Exchange; announced July 15, 2024. | G28: 2024 | H28: KSh 23.59 billion (~US$180 million) | I28: 180 | J28: Manufacturing Plant | K28: =IF(I28="",12,IF(I28>=100,40,IF(I28>=20,32,IF(I28>=5,24,IF(I28>=1,16,8))))) -> 40 | L28: =IF(G28="",5,IF(G28>=2023,25,IF(G28>=2022,20,IF(G28>=2021,14,IF(G28>=2020,8,5))))) -> 25 | M28: =IFERROR(INDEX(Methodology!$B$27:$B$36,MATCH(J28,Methodology!$A$27:$A$36,0)),12) -> 20 | N28: =IF(COUNTIF(Infrastructure!$A:$A,A28)>=4,15,IF(COUNTIF(Infrastructure!$A:$A,A28)>=2,10,IF(COUNTIF(Infrastructure!$A:$A,A28)>=1,5,0))) -> 15 | O28: =K28+L28+M28+N28 -> 100 | P28: =IF(O28>=70,"High",IF(O28>=50,"Medium","Watch")) -> High | Q28: Inside Amsons Group's KShs 23.59bn Buyout Offer for Bamburi Cement | R28: https://kenyanwallstreet.com/inside-amsons-group-kshs-23-59bn-buyout-offer-for-bamburi-cement/ | S28: July 15, 2024
A29: Kenya | B29: Devki Group (Simba Cement) | C29: Manufacturing | D29: Nairobi, Kenya | E29: Major Kenyan industrial conglomerate producing cement and steel, with operations spanning Kenya, Uganda, DRC, Rwanda and Zambia. | F29: Launched the Cemtech Sebit Clinkerization Plant in West Pokot on April 8, 2024 - a 2-million-tonne-per-year clinker facility ending Kenya's reliance on imported clinker. | G29: 2024 | H29: $220 million (approx. Sh29 billion) | I29: 220 | J29: Manufacturing Plant | K29: =IF(I29="",12,IF(I29>=100,40,IF(I29>=20,32,IF(I29>=5,24,IF(I29>=1,16,8))))) -> 40 | L29: =IF(G29="",5,IF(G29>=2023,25,IF(G29>=2022,20,IF(G29>=2021,14,IF(G29>=2020,8,5))))) -> 25 | M29: =IFERROR(INDEX(Methodology!$B$27:$B$36,MATCH(J29,Methodology!$A$27:$A$36,0)),12) -> 20 | N29: =IF(COUNTIF(Infrastructure!$A:$A,A29)>=4,15,IF(COUNTIF(Infrastructure!$A:$A,A29)>=2,10,IF(COUNTIF(Infrastructure!$A:$A,A29)>=1,5,0))) -> 15 | O29: =K29+L29+M29+N29 -> 100 | P29: =IF(O29>=70,"High",IF(O29>=50,"Medium","Watch")) -> High | Q29: Devki Opens Sh29bn Clinker Factory in West Pokot | R29: https://www.constructionkenya.com/2941/pokot-cement-factory/ | S29: April 8, 2024
A30: Kenya | B30: Kenya Vehicle Manufacturers (KVM) — Volkswagen assembly partner | C30: Manufacturing | D30: Thika, Kenya (local assembly partner; Volkswagen AG HQ Wolfsburg, Germany) | E30: Assembles vehicles in Kenya through local partner Kenya Vehicle Manufacturers (KVM) in Thika. | F30: Resumed local vehicle assembly (Polo Vivo) at the KVM Thika plant in August 2025, restarting Volkswagen production in Kenya after roughly four decades, targeting about 5,000 units per year. | G30: 2025 | H30: Not disclosed | J30: Manufacturing Plant | K30: =IF(I30="",12,IF(I30>=100,40,IF(I30>=20,32,IF(I30>=5,24,IF(I30>=1,16,8))))) -> 12 | L30: =IF(G30="",5,IF(G30>=2023,25,IF(G30>=2022,20,IF(G30>=2021,14,IF(G30>=2020,8,5))))) -> 25 | M30: =IFERROR(INDEX(Methodology!$B$27:$B$36,MATCH(J30,Methodology!$A$27:$A$36,0)),12) -> 20 | N30: =IF(COUNTIF(Infrastructure!$A:$A,A30)>=4,15,IF(COUNTIF(Infrastructure!$A:$A,A30)>=2,10,IF(COUNTIF(Infrastructure!$A:$A,A30)>=1,5,0))) -> 15 | O30: =K30+L30+M30+N30 -> 72 | P30: =IF(O30>=70,"High",IF(O30>=50,"Medium","Watch")) -> High | Q30: Kenya's motor assembler resumes Volkswagen production | R30: https://www.the-star.co.ke/business/2025-08-22-kenya-motor-assembler-resumes-volkswagen-production | S30: August 22, 2025
A31: Kenya | B31: Milly Group (Milly Glass SEZ Limited) | C31: Manufacturing | D31: Mombasa, Kenya | E31: Kenyan group also operating a juice-processing factory in Malindi; new subsidiary building what is billed as Africa's first amber pharmaceutical-glass-bottle plant, serving Kenya, Tanzania, Uganda, Rwanda, Burundi and the wider COMESA region. | F31: Groundbreaking planned for end of August 2026 on an 80-tonne glass factory (15 acres) inside the Dongo Kundu SEZ, Mombasa, to produce ~300,000 pharmaceutical bottles; production targeted for July 2027. | G31: 2026 | H31: Not disclosed | J31: Manufacturing Plant | K31: =IF(I31="",12,IF(I31>=100,40,IF(I31>=20,32,IF(I31>=5,24,IF(I31>=1,16,8))))) -> 12 | L31: =IF(G31="",5,IF(G31>=2023,25,IF(G31>=2022,20,IF(G31>=2021,14,IF(G31>=2020,8,5))))) -> 25 | M31: =IFERROR(INDEX(Methodology!$B$27:$B$36,MATCH(J31,Methodology!$A$27:$A$36,0)),12) -> 20 | N31: =IF(COUNTIF(Infrastructure!$A:$A,A31)>=4,15,IF(COUNTIF(Infrastructure!$A:$A,A31)>=2,10,IF(COUNTIF(Infrastructure!$A:$A,A31)>=1,5,0))) -> 15 | O31: =K31+L31+M31+N31 -> 72 | P31: =IF(O31>=70,"High",IF(O31>=50,"Medium","Watch")) -> High | Q31: Kenyan firm to be first maker of pharmaceutical bottles in Africa | R31: https://www.the-star.co.ke/counties/coast/2026-07-25-kenyan-firm-to-be-first-maker-of-pharmaceutical-bottles-in-africa | S31: July 25, 2026
A32: Kenya | B32: DHL | C32: Logistics | D32: Bonn, Germany | E32: Major express/logistics operator in Kenya, positioning Nairobi as a rising African gateway comparable to South Africa. | F32: Announced a new carbon-neutral regional headquarters building in Nairobi as part of a EUR300 million (~Sh45 billion), five-year pan-African investment plan spanning e-commerce, perishables, energy and life-sciences logistics (reported October 2025). | G32: 2025 | H32: EUR300 million (Africa-wide five-year plan; Kenya-specific allocation not disclosed) | J32: Regional HQ | K32: =IF(I32="",12,IF(I32>=100,40,IF(I32>=20,32,IF(I32>=5,24,IF(I32>=1,16,8))))) -> 12 | L32: =IF(G32="",5,IF(G32>=2023,25,IF(G32>=2022,20,IF(G32>=2021,14,IF(G32>=2020,8,5))))) -> 25 | M32: =IFERROR(INDEX(Methodology!$B$27:$B$36,MATCH(J32,Methodology!$A$27:$A$36,0)),12) -> 10 | N32: =IF(COUNTIF(Infrastructure!$A:$A,A32)>=4,15,IF(COUNTIF(Infrastructure!$A:$A,A32)>=2,10,IF(COUNTIF(Infrastructure!$A:$A,A32)>=1,5,0))) -> 15 | O32: =K32+L32+M32+N32 -> 62 | P32: =IF(O32>=70,"High",IF(O32>=50,"Medium","Watch")) -> Medium | Q32: DHL eyes new Nairobi office in Sh45 billion Africa expansion bid | R32: https://www.businessdailyafrica.com/bd/corporate/companies/dhl-eyes-new-nairobi-office-in-sh45bn-africa-expansion-bid-5233152 | S32: October 2025
A33: Kenya | B33: DP World | C33: Logistics | D33: Dubai, UAE | E33: Operates container terminal services at the Port of Mombasa and is expanding into inland industrial/logistics real estate near the port. | F33: Signed an agreement with GulfCap Africa (August 2026) to co-develop a 222-hectare Mombasa Industrial Park special economic zone within 20km of the Port of Mombasa, for manufacturers, logistics providers and regional distribution businesses. | G33: 2026 | H33: Not disclosed | J33: Distribution Center | K33: =IF(I33="",12,IF(I33>=100,40,IF(I33>=20,32,IF(I33>=5,24,IF(I33>=1,16,8))))) -> 12 | L33: =IF(G33="",5,IF(G33>=2023,25,IF(G33>=2022,20,IF(G33>=2021,14,IF(G33>=2020,8,5))))) -> 25 | M33: =IFERROR(INDEX(Methodology!$B$27:$B$36,MATCH(J33,Methodology!$A$27:$A$36,0)),12) -> 14 | N33: =IF(COUNTIF(Infrastructure!$A:$A,A33)>=4,15,IF(COUNTIF(Infrastructure!$A:$A,A33)>=2,10,IF(COUNTIF(Infrastructure!$A:$A,A33)>=1,5,0))) -> 15 | O33: =K33+L33+M33+N33 -> 66 | P33: =IF(O33>=70,"High",IF(O33>=50,"Medium","Watch")) -> Medium | Q33: DP World to co-develop free zone in Kenya | R33: https://www.agbi.com/logistics/2026/08/dp-world-to-co-develop-free-zone-in-kenya/ | S33: August 2026
A34: Kenya | B34: Majid Al Futtaim (Carrefour) | C34: Retail | D34: Dubai, UAE | E34: Kenya's largest hypermarket operator under the Carrefour franchise, growing to 34 outlets nationwide with over 2,800 direct employees by 2025. | F34: Opened its 30th Carrefour store in Kenya at Waris Mall, Ruai (1,500 sqm, ~40 jobs) by September 2025, part of eight new store openings that year. | G34: 2025 | H34: Not disclosed | J34: Retail Store/Mall | K34: =IF(I34="",12,IF(I34>=100,40,IF(I34>=20,32,IF(I34>=5,24,IF(I34>=1,16,8))))) -> 12 | L34: =IF(G34="",5,IF(G34>=2023,25,IF(G34>=2022,20,IF(G34>=2021,14,IF(G34>=2020,8,5))))) -> 25 | M34: =IFERROR(INDEX(Methodology!$B$27:$B$36,MATCH(J34,Methodology!$A$27:$A$36,0)),12) -> 8 | N34: =IF(COUNTIF(Infrastructure!$A:$A,A34)>=4,15,IF(COUNTIF(Infrastructure!$A:$A,A34)>=2,10,IF(COUNTIF(Infrastructure!$A:$A,A34)>=1,5,0))) -> 15 | O34: =K34+L34+M34+N34 -> 60 | P34: =IF(O34>=70,"High",IF(O34>=50,"Medium","Watch")) -> Medium | Q34: Majid Al Futtaim Opens 30th Carrefour Store in Kenya, Creates 40 Jobs | R34: https://www.eabusinesstimes.com/majid-al-futtaim-opens-30th-carrefour-store-in-kenya-creates-40-jobs/ | S34: 2025
A35: Kenya | B35: Naivas Limited | C35: Retail | D35: Nairobi, Kenya | E35: Kenya's largest homegrown supermarket chain; FY2025 revenue $751.4 million (+21.6% YoY), net profit $16.1 million (+43.4% YoY). | F35: Opened its 112th store in Mihango, Nairobi (announced December 2025), part of a plan to add up to 10 stores per year toward a 200-store target. | G35: 2025 | H35: Not disclosed | J35: Retail Store/Mall | K35: =IF(I35="",12,IF(I35>=100,40,IF(I35>=20,32,IF(I35>=5,24,IF(I35>=1,16,8))))) -> 12 | L35: =IF(G35="",5,IF(G35>=2023,25,IF(G35>=2022,20,IF(G35>=2021,14,IF(G35>=2020,8,5))))) -> 25 | M35: =IFERROR(INDEX(Methodology!$B$27:$B$36,MATCH(J35,Methodology!$A$27:$A$36,0)),12) -> 8 | N35: =IF(COUNTIF(Infrastructure!$A:$A,A35)>=4,15,IF(COUNTIF(Infrastructure!$A:$A,A35)>=2,10,IF(COUNTIF(Infrastructure!$A:$A,A35)>=1,5,0))) -> 15 | O35: =K35+L35+M35+N35 -> 60 | P35: =IF(O35>=70,"High",IF(O35>=50,"Medium","Watch")) -> Medium | Q35: Carrefour and Naivas drive Kenya's retail expansion | R35: https://khusoko.com/2025/12/16/carrefour-and-naivas-drive-kenyas-retail-expansion/ | S35: December 16, 2025
A36: Kenya | B36: Crown Healthcare | C36: Pharma | D36: Nairobi, Kenya | E36: Kenyan healthcare distributor expanding into pharmaceutical manufacturing, with distribution reach into Nigeria, Tanzania, Uganda and Rwanda. | F36: Secured $10 million from Impact Fund Denmark (announced December 15, 2025) to build a large-scale generic-medicines manufacturing plant, expected to create about 600 jobs, cutting reliance on Kenya's ~80% imported medicines. | G36: 2025 | H36: $10 million | I36: 10 | J36: Hospital/Pharma Plant | K36: =IF(I36="",12,IF(I36>=100,40,IF(I36>=20,32,IF(I36>=5,24,IF(I36>=1,16,8))))) -> 24 | L36: =IF(G36="",5,IF(G36>=2023,25,IF(G36>=2022,20,IF(G36>=2021,14,IF(G36>=2020,8,5))))) -> 25 | M36: =IFERROR(INDEX(Methodology!$B$27:$B$36,MATCH(J36,Methodology!$A$27:$A$36,0)),12) -> 18 | N36: =IF(COUNTIF(Infrastructure!$A:$A,A36)>=4,15,IF(COUNTIF(Infrastructure!$A:$A,A36)>=2,10,IF(COUNTIF(Infrastructure!$A:$A,A36)>=1,5,0))) -> 15 | O36: =K36+L36+M36+N36 -> 82 | P36: =IF(O36>=70,"High",IF(O36>=50,"Medium","Watch")) -> High | Q36: Kenyan entrepreneur Shilen Thakerar's Crown Healthcare to build new pharma plant with $10 million | R36: https://www.billionaires.africa/2025/12/15/kenyan-entrepreneur-shilen-thakerars-crown-healthcare-to-build-new-pharma-plant-with-10-million/ | S36: December 15, 2025
A37: Kenya | B37: Amazon Web Services (AWS) | C37: Technology | D37: Seattle, USA | E37: Operates a Nairobi-based Development Centre - AWS's second in Africa after Cape Town - housing R&D, cloud support and software engineering teams. | F37: Launched its second African Development Centre on Riverside Drive, Nairobi, October 5, 2023. | G37: 2023 | H37: Not disclosed | J37: R&D Centre | K37: =IF(I37="",12,IF(I37>=100,40,IF(I37>=20,32,IF(I37>=5,24,IF(I37>=1,16,8))))) -> 12 | L37: =IF(G37="",5,IF(G37>=2023,25,IF(G37>=2022,20,IF(G37>=2021,14,IF(G37>=2020,8,5))))) -> 25 | M37: =IFERROR(INDEX(Methodology!$B$27:$B$36,MATCH(J37,Methodology!$A$27:$A$36,0)),12) -> 14 | N37: =IF(COUNTIF(Infrastructure!$A:$A,A37)>=4,15,IF(COUNTIF(Infrastructure!$A:$A,A37)>=2,10,IF(COUNTIF(Infrastructure!$A:$A,A37)>=1,5,0))) -> 15 | O37: =K37+L37+M37+N37 -> 66 | P37: =IF(O37>=70,"High",IF(O37>=50,"Medium","Watch")) -> Medium | Q37: AWS Launches its second African Development Centre in Kenya | R37: https://techtrendske.co.ke/2023/10/05/aws-launches-its-second-african-development-centre-in-kenya/ | S37: October 5, 2023
A38: Kenya | B38: Huawei Technologies | C38: Technology | D38: Shenzhen, China | E38: Huawei has operated in Kenya for over two decades, partnering with the Kenyan government on national ICT infrastructure, most notably building the Konza Technopolis National Cloud Data Centre and Government Cloud alongside network infrastructure for local telecom operators. | F38: Committed to build a National Cloud data centre, smart ICT/surveillance systems and a Government Cloud at Konza Technopolis, financed via Chinese concessional loans; Phase 1 (containerized National Data Centre) completed July 2020, valued at KSh 17.5 billion. | G38: 2020 | H38: KSh 17.5 billion (~US$173 million) | I38: 173 | J38: Data Centre | K38: =IF(I38="",12,IF(I38>=100,40,IF(I38>=20,32,IF(I38>=5,24,IF(I38>=1,16,8))))) -> 40 | L38: =IF(G38="",5,IF(G38>=2023,25,IF(G38>=2022,20,IF(G38>=2021,14,IF(G38>=2020,8,5))))) -> 8 | M38: =IFERROR(INDEX(Methodology!$B$27:$B$36,MATCH(J38,Methodology!$A$27:$A$36,0)),12) -> 20 | N38: =IF(COUNTIF(Infrastructure!$A:$A,A38)>=4,15,IF(COUNTIF(Infrastructure!$A:$A,A38)>=2,10,IF(COUNTIF(Infrastructure!$A:$A,A38)>=1,5,0))) -> 15 | O38: =K38+L38+M38+N38 -> 83 | P38: =IF(O38>=70,"High",IF(O38>=50,"Medium","Watch")) -> High | Q38: Phase One National Data Center at Konza Completed | R38: https://techweez.com/2020/07/20/phase-one-national-data-center-konza-completed/ | S38: July 20, 2020
A39: Kenya | B39: Microsoft (with G42) | C39: Technology | D39: Redmond, USA (partner G42 HQ'd in Abu Dhabi, UAE) | E39: Establishing Kenya as its flagship East African digital hub, including a new Azure cloud region and an Innovation Lab in Nairobi. | F39: Announced (with G42) a $1 billion comprehensive digital ecosystem initiative on May 22, 2024, including a geothermal-powered data centre in Olkaria and a new Azure East Africa Cloud Region. | G39: 2024 | H39: $1 billion | I39: 1000 | J39: Data Centre | K39: =IF(I39="",12,IF(I39>=100,40,IF(I39>=20,32,IF(I39>=5,24,IF(I39>=1,16,8))))) -> 40 | L39: =IF(G39="",5,IF(G39>=2023,25,IF(G39>=2022,20,IF(G39>=2021,14,IF(G39>=2020,8,5))))) -> 25 | M39: =IFERROR(INDEX(Methodology!$B$27:$B$36,MATCH(J39,Methodology!$A$27:$A$36,0)),12) -> 20 | N39: =IF(COUNTIF(Infrastructure!$A:$A,A39)>=4,15,IF(COUNTIF(Infrastructure!$A:$A,A39)>=2,10,IF(COUNTIF(Infrastructure!$A:$A,A39)>=1,5,0))) -> 15 | O39: =K39+L39+M39+N39 -> 100 | P39: =IF(O39>=70,"High",IF(O39>=50,"Medium","Watch")) -> High | Q39: Microsoft and G42 announce $1 billion comprehensive digital ecosystem initiative for Kenya | R39: https://news.microsoft.com/source/2024/05/22/microsoft-and-g42-announce-1-billion-comprehensive-digital-ecosystem-initiative-for-kenya/ | S39: May 22, 2024
A40: Kenya | B40: China Road and Bridge Corporation (CRBC) | C40: Construction | D40: Beijing, China | E40: Long-time Kenyan infrastructure contractor (built the SGR railway); returning to major road projects after a Chinese-lending pause that began around 2019. | F40: Launched Phase One ($863 million) of a $1.5 billion Nairobi-Mau Summit highway upgrade with Kenya's NSSF as equity partner, announced November 28, 2025; construction due by end-2027, followed by a 28-year toll concession. | G40: 2025 | H40: $863 million (Phase One of the overall $1.5 billion project) | I40: 863 | J40: Construction Project | K40: =IF(I40="",12,IF(I40>=100,40,IF(I40>=20,32,IF(I40>=5,24,IF(I40>=1,16,8))))) -> 40 | L40: =IF(G40="",5,IF(G40>=2023,25,IF(G40>=2022,20,IF(G40>=2021,14,IF(G40>=2020,8,5))))) -> 25 | M40: =IFERROR(INDEX(Methodology!$B$27:$B$36,MATCH(J40,Methodology!$A$27:$A$36,0)),12) -> 16 | N40: =IF(COUNTIF(Infrastructure!$A:$A,A40)>=4,15,IF(COUNTIF(Infrastructure!$A:$A,A40)>=2,10,IF(COUNTIF(Infrastructure!$A:$A,A40)>=1,5,0))) -> 15 | O40: =K40+L40+M40+N40 -> 96 | P40: =IF(O40>=70,"High",IF(O40>=50,"Medium","Watch")) -> High | Q40: Kenya turns to China for $1.5 billion highway expansion | R40: https://www.cnbcafrica.com/2025/kenya-turns-to-china-for-1-5-billion-highway-expansion | S40: November 28, 2025
A41: Kenya | B41: Shandong Hi-Speed Road and Bridge International | C41: Construction | D41: Jinan, Shandong, China | E41: New entrant to Kenya's road-concession market via the Nairobi-Mau Summit highway corridor's second phase. | F41: Contracted for Phase Two ($678.56 million) of the Nairobi-Mau Summit highway project, developing a 94km six-lane stretch, announced alongside CRBC's Phase One, November 28, 2025. | G41: 2025 | H41: $678.56 million | I41: 678.6 | J41: Construction Project | K41: =IF(I41="",12,IF(I41>=100,40,IF(I41>=20,32,IF(I41>=5,24,IF(I41>=1,16,8))))) -> 40 | L41: =IF(G41="",5,IF(G41>=2023,25,IF(G41>=2022,20,IF(G41>=2021,14,IF(G41>=2020,8,5))))) -> 25 | M41: =IFERROR(INDEX(Methodology!$B$27:$B$36,MATCH(J41,Methodology!$A$27:$A$36,0)),12) -> 16 | N41: =IF(COUNTIF(Infrastructure!$A:$A,A41)>=4,15,IF(COUNTIF(Infrastructure!$A:$A,A41)>=2,10,IF(COUNTIF(Infrastructure!$A:$A,A41)>=1,5,0))) -> 15 | O41: =K41+L41+M41+N41 -> 96 | P41: =IF(O41>=70,"High",IF(O41>=50,"Medium","Watch")) -> High | Q41: Kenya turns to China for $1.5 billion highway expansion | R41: https://www.cnbcafrica.com/2025/kenya-turns-to-china-for-1-5-billion-highway-expansion | S41: November 28, 2025
A42: Madagascar | B42: Energy Fuels Inc. | C42: Manufacturing | D42: Lakewood, Colorado, USA | E42: Energy Fuels is advancing the Toliara Project in southwestern Madagascar, a titanium, zirconium and rare-earth mineral sands project. | F42: Energy Fuels and the Government of Madagascar executed an MOU on 5 December 2024 to further advance the Toliara project toward a final investment decision. | G42: 2024 | H42: Multi-billion-dollar project potential; ~US$80 million committed to development/community/social funding | I42: 80 | J42: Manufacturing Plant | K42: =IF(I42="",12,IF(I42>=100,40,IF(I42>=20,32,IF(I42>=5,24,IF(I42>=1,16,8))))) -> 32 | L42: =IF(G42="",5,IF(G42>=2023,25,IF(G42>=2022,20,IF(G42>=2021,14,IF(G42>=2020,8,5))))) -> 25 | M42: =IFERROR(INDEX(Methodology!$B$27:$B$36,MATCH(J42,Methodology!$A$27:$A$36,0)),12) -> 20 | N42: =IF(COUNTIF(Infrastructure!$A:$A,A42)>=4,15,IF(COUNTIF(Infrastructure!$A:$A,A42)>=2,10,IF(COUNTIF(Infrastructure!$A:$A,A42)>=1,5,0))) -> 10 | O42: =K42+L42+M42+N42 -> 87 | P42: =IF(O42>=70,"High",IF(O42>=50,"Medium","Watch")) -> High | Q42: Energy Fuels and Madagascar Government Execute Memorandum of Understanding to Further Advance Toliara Critical Mineral Project in Madagascar | R42: https://investors.energyfuels.com/2024-12-05-Energy-Fuels-and-Madagascar-Government-Execute-Memorandum-of-Understanding-to-Further-Advance-Toliara-Critical-Mineral-Project-in-Madagascar | S42: 2024-12-05
A43: Madagascar | B43: Super U (with Habibo Group) | C43: Retail | D43: France (Système U) | E43: Super U entered Madagascar's retail market by taking over Shoprite's 10-store supermarket network. | F43: Super U announced (reported September 2021) the takeover of Shoprite's 10 Madagascar stores, following Shoprite's exit from the market. | G43: 2021 | H43: Not disclosed | J43: Retail Store/Mall | K43: =IF(I43="",12,IF(I43>=100,40,IF(I43>=20,32,IF(I43>=5,24,IF(I43>=1,16,8))))) -> 12 | L43: =IF(G43="",5,IF(G43>=2023,25,IF(G43>=2022,20,IF(G43>=2021,14,IF(G43>=2020,8,5))))) -> 14 | M43: =IFERROR(INDEX(Methodology!$B$27:$B$36,MATCH(J43,Methodology!$A$27:$A$36,0)),12) -> 8 | N43: =IF(COUNTIF(Infrastructure!$A:$A,A43)>=4,15,IF(COUNTIF(Infrastructure!$A:$A,A43)>=2,10,IF(COUNTIF(Infrastructure!$A:$A,A43)>=1,5,0))) -> 10 | O43: =K43+L43+M43+N43 -> 44 | P43: =IF(O43>=70,"High",IF(O43>=50,"Medium","Watch")) -> Watch | Q43: Super U takes over 10 Shoprite stores in Madagascar | R43: https://trendtype.com/news/super-u-takes-over-10-shoprite-stores-in-madagascar/ | S43: 2021-09-19
A44: Madagascar | B44: Orange Madagascar | C44: Technology | D44: Antananarivo, Madagascar | E44: Orange Madagascar is one of the country's leading mobile network operators. | F44: Orange Madagascar renewed its comprehensive telecom license for ~€30 million (acquired December 2023) and is deploying 500 new 2G/3G sites via a 10-year partnership with NuRAN Wireless. | G44: 2023 | H44: €30 million (license renewal) | I44: 32.4 | J44: Regional HQ / Network Infrastructure | K44: =IF(I44="",12,IF(I44>=100,40,IF(I44>=20,32,IF(I44>=5,24,IF(I44>=1,16,8))))) -> 32 | L44: =IF(G44="",5,IF(G44>=2023,25,IF(G44>=2022,20,IF(G44>=2021,14,IF(G44>=2020,8,5))))) -> 25 | M44: =IFERROR(INDEX(Methodology!$B$27:$B$36,MATCH(J44,Methodology!$A$27:$A$36,0)),12) -> 12 | N44: =IF(COUNTIF(Infrastructure!$A:$A,A44)>=4,15,IF(COUNTIF(Infrastructure!$A:$A,A44)>=2,10,IF(COUNTIF(Infrastructure!$A:$A,A44)>=1,5,0))) -> 10 | O44: =K44+L44+M44+N44 -> 79 | P44: =IF(O44>=70,"High",IF(O44>=50,"Medium","Watch")) -> High | Q44: Orange Madagascar boosts telecom network coverage with new license and investments | R44: https://www.ecofinagency.com/telecom/2601-45164-orange-madagascar-boosts-telecom-network-coverage-with-new-license-and-investments | S44: 2024-01-26
A45: Malawi | B45: Bakhresa Malawi Limited | C45: Manufacturing | D45: Dar es Salaam, Tanzania | E45: Bakhresa Malawi, part of Tanzania's Bakhresa Group, is a major grain-milling and edible-oil processor with facilities in Blantyre. | F45: Commissioned a new K175 billion (~US$100 million) cooking-oil refinery and soya solvent-extraction plant in Blantyre on 10 July 2025. | G45: 2025 | H45: K175 billion (~US$100 million) | I45: 100 | J45: Manufacturing Plant | K45: =IF(I45="",12,IF(I45>=100,40,IF(I45>=20,32,IF(I45>=5,24,IF(I45>=1,16,8))))) -> 40 | L45: =IF(G45="",5,IF(G45>=2023,25,IF(G45>=2022,20,IF(G45>=2021,14,IF(G45>=2020,8,5))))) -> 25 | M45: =IFERROR(INDEX(Methodology!$B$27:$B$36,MATCH(J45,Methodology!$A$27:$A$36,0)),12) -> 20 | N45: =IF(COUNTIF(Infrastructure!$A:$A,A45)>=4,15,IF(COUNTIF(Infrastructure!$A:$A,A45)>=2,10,IF(COUNTIF(Infrastructure!$A:$A,A45)>=1,5,0))) -> 10 | O45: =K45+L45+M45+N45 -> 95 | P45: =IF(O45>=70,"High",IF(O45>=50,"Medium","Watch")) -> High | Q45: Bakhresa commissions K175 billion plant | R45: https://mwnation.com/bakhresa-commissions-k175-billion-plant/ | S45: 2025-07-10
A46: Malawi | B46: Portland Cement Malawi (Huaxin Cement) | C46: Manufacturing | D46: Wuhan, China | E46: Portland Cement Malawi, majority-owned by China's Huaxin Cement, runs the country's newest integrated cement plant in Balaka. | F46: Commissioned a US$100 million integrated cement plant in Balaka on 5 December 2025, adding 800,000 tonnes/year of capacity. | G46: 2025 | H46: US$100 million | I46: 100 | J46: Manufacturing Plant | K46: =IF(I46="",12,IF(I46>=100,40,IF(I46>=20,32,IF(I46>=5,24,IF(I46>=1,16,8))))) -> 40 | L46: =IF(G46="",5,IF(G46>=2023,25,IF(G46>=2022,20,IF(G46>=2021,14,IF(G46>=2020,8,5))))) -> 25 | M46: =IFERROR(INDEX(Methodology!$B$27:$B$36,MATCH(J46,Methodology!$A$27:$A$36,0)),12) -> 20 | N46: =IF(COUNTIF(Infrastructure!$A:$A,A46)>=4,15,IF(COUNTIF(Infrastructure!$A:$A,A46)>=2,10,IF(COUNTIF(Infrastructure!$A:$A,A46)>=1,5,0))) -> 10 | O46: =K46+L46+M46+N46 -> 95 | P46: =IF(O46>=70,"High",IF(O46>=50,"Medium","Watch")) -> High | Q46: Huaxin Building Materials and Portland Cement Malawi launch US$100m cement plant | R46: https://www.globalcement.com/news/20187-huaxin-building-materials-and-portland-cement-malawi-launch-us-100m-cement-plant | S46: 2025-12-05
A47: Malawi | B47: Bolloré Logistics Malawi | C47: Logistics | D47: Paris, France | E47: Bolloré Logistics Malawi is the Malawi unit of the pan-African Bolloré Logistics freight-forwarding network. | F47: Won and completed the logistics contract for Malawi's 60MW Golomoti Solar project, shipping 221 TEUs via the Port of Beira between March and December 2021. | G47: 2021 | H47: Not disclosed | J47: Distribution Center | K47: =IF(I47="",12,IF(I47>=100,40,IF(I47>=20,32,IF(I47>=5,24,IF(I47>=1,16,8))))) -> 12 | L47: =IF(G47="",5,IF(G47>=2023,25,IF(G47>=2022,20,IF(G47>=2021,14,IF(G47>=2020,8,5))))) -> 14 | M47: =IFERROR(INDEX(Methodology!$B$27:$B$36,MATCH(J47,Methodology!$A$27:$A$36,0)),12) -> 14 | N47: =IF(COUNTIF(Infrastructure!$A:$A,A47)>=4,15,IF(COUNTIF(Infrastructure!$A:$A,A47)>=2,10,IF(COUNTIF(Infrastructure!$A:$A,A47)>=1,5,0))) -> 10 | O47: =K47+L47+M47+N47 -> 50 | P47: =IF(O47>=70,"High",IF(O47>=50,"Medium","Watch")) -> Medium | Q47: Bolloré Logistics Malawi successfully completes logistics for the Golomoti Solar project | R47: https://www.ecofinagency.com/public-management/2803-43488-bollore-logistics-malawi-successfully-completes-logistics-for-the-golomoti-solar-project | S47: 2021-12
A48: Malawi | B48: Chint Electric Co. Ltd | C48: Construction | D48: Yueqing, Zhejiang, China | E48: Chint Electric acted as EPC contractor for Malawi state utility EGENCO's new solar programme. | F48: Built and commissioned the first 10MW phase of the Nanjoka solar plant (of a planned 50MW project) on 10 August 2026. | G48: 2026 | H48: US$13.55 million | I48: 13.6 | J48: Construction Project | K48: =IF(I48="",12,IF(I48>=100,40,IF(I48>=20,32,IF(I48>=5,24,IF(I48>=1,16,8))))) -> 24 | L48: =IF(G48="",5,IF(G48>=2023,25,IF(G48>=2022,20,IF(G48>=2021,14,IF(G48>=2020,8,5))))) -> 25 | M48: =IFERROR(INDEX(Methodology!$B$27:$B$36,MATCH(J48,Methodology!$A$27:$A$36,0)),12) -> 16 | N48: =IF(COUNTIF(Infrastructure!$A:$A,A48)>=4,15,IF(COUNTIF(Infrastructure!$A:$A,A48)>=2,10,IF(COUNTIF(Infrastructure!$A:$A,A48)>=1,5,0))) -> 10 | O48: =K48+L48+M48+N48 -> 75 | P48: =IF(O48>=70,"High",IF(O48>=50,"Medium","Watch")) -> High | Q48: Malawi Adds 10 MW Solar Plant to Reduce Reliance on Hydropower | R48: https://www.ecofinagency.com/news-industry/1008-58074-malawi-adds-10-mw-solar-plant-to-reduce-reliance-on-hydropower | S48: 2026-08-10
A49: Mauritius | B49: Medine Group (Cascavelle Shopping Mall) | C49: Retail | D49: Bambous, Mauritius | E49: Medine Group operates Cascavelle Shopping Mall in the island's western region, one of Mauritius's largest retail and leisure destinations. | F49: Announced a Rs 2.6 billion extension of Cascavelle Mall that will triple its footprint, adding 19,500m² and 66 new retail outlets, reported 18 July 2024. | G49: 2024 | H49: Rs 2.6 billion (~US$57 million) | I49: 57 | J49: Retail Store/Mall | K49: =IF(I49="",12,IF(I49>=100,40,IF(I49>=20,32,IF(I49>=5,24,IF(I49>=1,16,8))))) -> 32 | L49: =IF(G49="",5,IF(G49>=2023,25,IF(G49>=2022,20,IF(G49>=2021,14,IF(G49>=2020,8,5))))) -> 25 | M49: =IFERROR(INDEX(Methodology!$B$27:$B$36,MATCH(J49,Methodology!$A$27:$A$36,0)),12) -> 8 | N49: =IF(COUNTIF(Infrastructure!$A:$A,A49)>=4,15,IF(COUNTIF(Infrastructure!$A:$A,A49)>=2,10,IF(COUNTIF(Infrastructure!$A:$A,A49)>=1,5,0))) -> 10 | O49: =K49+L49+M49+N49 -> 75 | P49: =IF(O49>=70,"High",IF(O49>=50,"Medium","Watch")) -> High | Q49: Cascavelle Shopping Mall: Medine Group invests Rs 2.6 billion for extension | R49: https://www.propertycloud.mu/blog/cascavelle-shopping-mall-medine-group-invests-rs-26-billion-for-extension | S49: 2024-07-18
A50: Mauritius | B50: IBL Group (Nouvelle Clinique Bon Pasteur) | C50: Pharma | D50: Port Louis, Mauritius | E50: IBL Group's healthcare arm, Life Together, runs three private clinics in Mauritius, including Nouvelle Clinique Bon Pasteur. | F50: Confirmed it is modernising Bon Pasteur clinic into a community hospital with new intensive-care and maternity services, per an interview published 6 October 2025. | G50: 2025 | H50: Not disclosed | J50: Hospital/Pharma Plant | K50: =IF(I50="",12,IF(I50>=100,40,IF(I50>=20,32,IF(I50>=5,24,IF(I50>=1,16,8))))) -> 12 | L50: =IF(G50="",5,IF(G50>=2023,25,IF(G50>=2022,20,IF(G50>=2021,14,IF(G50>=2020,8,5))))) -> 25 | M50: =IFERROR(INDEX(Methodology!$B$27:$B$36,MATCH(J50,Methodology!$A$27:$A$36,0)),12) -> 18 | N50: =IF(COUNTIF(Infrastructure!$A:$A,A50)>=4,15,IF(COUNTIF(Infrastructure!$A:$A,A50)>=2,10,IF(COUNTIF(Infrastructure!$A:$A,A50)>=1,5,0))) -> 10 | O50: =K50+L50+M50+N50 -> 65 | P50: =IF(O50>=70,"High",IF(O50>=50,"Medium","Watch")) -> Medium | Q50: Mauritius remains our core market | R50: https://iblgroup.com/newsroom/mauritius-remains-our-core-market/ | S50: 2025-10-06
A51: Mauritius | B51: Emtel Ltd | C51: Technology | D51: Ebène, Mauritius | E51: Emtel is Mauritius's first private mobile network operator. | F51: Launched Mauritius's first live 5G network (60% population coverage at launch) on 31 July 2023 and announced a BSS modernisation partnership with Tecnotree. | G51: 2023 | H51: Not disclosed | J51: Regional HQ / Network Infrastructure | K51: =IF(I51="",12,IF(I51>=100,40,IF(I51>=20,32,IF(I51>=5,24,IF(I51>=1,16,8))))) -> 12 | L51: =IF(G51="",5,IF(G51>=2023,25,IF(G51>=2022,20,IF(G51>=2021,14,IF(G51>=2020,8,5))))) -> 25 | M51: =IFERROR(INDEX(Methodology!$B$27:$B$36,MATCH(J51,Methodology!$A$27:$A$36,0)),12) -> 12 | N51: =IF(COUNTIF(Infrastructure!$A:$A,A51)>=4,15,IF(COUNTIF(Infrastructure!$A:$A,A51)>=2,10,IF(COUNTIF(Infrastructure!$A:$A,A51)>=1,5,0))) -> 10 | O51: =K51+L51+M51+N51 -> 59 | P51: =IF(O51>=70,"High",IF(O51>=50,"Medium","Watch")) -> Medium | Q51: Emtel Mauritius launches 5G, taps Tecnotree for digital transformation | R51: https://developingtelecoms.com/telecom-technology/telecom-cloud-virtualization/15320-emtel-mauritius-selects-tecnotree-for-bss-transformation.html | S51: 2023-08-02
A52: Mozambique | B52: Cimentos de Moçambique (Huaxin Cement) | C52: Manufacturing | D52: Wuhan, China | E52: Cimentos de Moçambique, majority-owned by China's Huaxin Cement, operates the country's cement plant in Nacala, Nampula province. | F52: Completed a US$110 million expansion at its Nacala plant, tripling cement/clinker capacity from 0.4 to 1.2 million tonnes/year, reported 28 July 2026. | G52: 2026 | H52: US$110 million | I52: 110 | J52: Manufacturing Plant | K52: =IF(I52="",12,IF(I52>=100,40,IF(I52>=20,32,IF(I52>=5,24,IF(I52>=1,16,8))))) -> 40 | L52: =IF(G52="",5,IF(G52>=2023,25,IF(G52>=2022,20,IF(G52>=2021,14,IF(G52>=2020,8,5))))) -> 25 | M52: =IFERROR(INDEX(Methodology!$B$27:$B$36,MATCH(J52,Methodology!$A$27:$A$36,0)),12) -> 20 | N52: =IF(COUNTIF(Infrastructure!$A:$A,A52)>=4,15,IF(COUNTIF(Infrastructure!$A:$A,A52)>=2,10,IF(COUNTIF(Infrastructure!$A:$A,A52)>=1,5,0))) -> 10 | O52: =K52+L52+M52+N52 -> 95 | P52: =IF(O52>=70,"High",IF(O52>=50,"Medium","Watch")) -> High | Q52: Cimentos de Moçambique triples capacity at Nacala plant through US$110m expansion | R52: https://www.globalcement.com/news/21049-cimentos-de-mocambique-triples-capacity-at-nacala-plant-through-us-110m-expansion | S52: 2026-07-28
A53: Mozambique | B53: Eni S.p.A. (Coral Sul FLNG) | C53: Manufacturing | D53: Rome, Italy | E53: Eni operates the Coral Sul floating LNG facility off Mozambique's Rovuma Basin — the country's first LNG production. | F53: Coral Sul FLNG has been producing LNG since 2022, and Eni's approved Coral Norte development (3.55 million tonnes/year, production expected H2 2028) was cited as of August 2026. | G53: 2022 | H53: Not disclosed | J53: Manufacturing Plant | K53: =IF(I53="",12,IF(I53>=100,40,IF(I53>=20,32,IF(I53>=5,24,IF(I53>=1,16,8))))) -> 12 | L53: =IF(G53="",5,IF(G53>=2023,25,IF(G53>=2022,20,IF(G53>=2021,14,IF(G53>=2020,8,5))))) -> 20 | M53: =IFERROR(INDEX(Methodology!$B$27:$B$36,MATCH(J53,Methodology!$A$27:$A$36,0)),12) -> 20 | N53: =IF(COUNTIF(Infrastructure!$A:$A,A53)>=4,15,IF(COUNTIF(Infrastructure!$A:$A,A53)>=2,10,IF(COUNTIF(Infrastructure!$A:$A,A53)>=1,5,0))) -> 10 | O53: =K53+L53+M53+N53 -> 62 | P53: =IF(O53>=70,"High",IF(O53>=50,"Medium","Watch")) -> Medium | Q53: Mozambique: Southern Africa's emerging industrial platform | R53: https://www.cnbcafrica.com/2026/mozambique-southern-africas-emerging-industrial-platform | S53: 2026-08-14
A54: Mozambique | B54: DP World (Maputo Port Development Company) | C54: Logistics | D54: Dubai, United Arab Emirates | E54: DP World, alongside Mozambique's CFM and Grindrod, operates the Maputo Port Development Company running the Port of Maputo under a concession extended to 2058. | F54: Underway on a US$165 million first-phase project (part of a wider US$1.1 billion plan to 2033) to expand Maputo Port's container capacity, reported September 2025. | G54: 2033 | H54: US$165 million (phase one); US$1.1 billion (full programme to 2033) | I54: 165 | J54: Distribution Center | K54: =IF(I54="",12,IF(I54>=100,40,IF(I54>=20,32,IF(I54>=5,24,IF(I54>=1,16,8))))) -> 40 | L54: =IF(G54="",5,IF(G54>=2023,25,IF(G54>=2022,20,IF(G54>=2021,14,IF(G54>=2020,8,5))))) -> 25 | M54: =IFERROR(INDEX(Methodology!$B$27:$B$36,MATCH(J54,Methodology!$A$27:$A$36,0)),12) -> 14 | N54: =IF(COUNTIF(Infrastructure!$A:$A,A54)>=4,15,IF(COUNTIF(Infrastructure!$A:$A,A54)>=2,10,IF(COUNTIF(Infrastructure!$A:$A,A54)>=1,5,0))) -> 10 | O54: =K54+L54+M54+N54 -> 89 | P54: =IF(O54>=70,"High",IF(O54>=50,"Medium","Watch")) -> High | Q54: Maputo port targets expansion and role as regional logistics hub | R54: https://african.business/2025/09/trade-investment/maputo-port-targets-role-as-regional-logistics-hub | S54: 2025-09
A55: Rwanda | B55: Cimerwa Plc | C55: Manufacturing | D55: Kigali/Bugarama, Rwanda (majority-owned by National Cement Holdings, Kenya, since Nov 2023) | E55: Rwanda's leading cement producer, operating the country's only integrated cement plant in Bugarama, Rusizi district. | F55: Rwandan government signed a 15-year quarry deal enabling Cimerwa to build a new $190M clinker plant in Musanze to end clinker imports; announced late September/October 2025. | G55: 2025 | H55: $190 million (approx. Rwf 275 billion) | I55: 190 | J55: Manufacturing Plant | K55: =IF(I55="",12,IF(I55>=100,40,IF(I55>=20,32,IF(I55>=5,24,IF(I55>=1,16,8))))) -> 40 | L55: =IF(G55="",5,IF(G55>=2023,25,IF(G55>=2022,20,IF(G55>=2021,14,IF(G55>=2020,8,5))))) -> 25 | M55: =IFERROR(INDEX(Methodology!$B$27:$B$36,MATCH(J55,Methodology!$A$27:$A$36,0)),12) -> 20 | N55: =IF(COUNTIF(Infrastructure!$A:$A,A55)>=4,15,IF(COUNTIF(Infrastructure!$A:$A,A55)>=2,10,IF(COUNTIF(Infrastructure!$A:$A,A55)>=1,5,0))) -> 15 | O55: =K55+L55+M55+N55 -> 100 | P55: =IF(O55>=70,"High",IF(O55>=50,"Medium","Watch")) -> High | Q55: Rwanda: Cimerwa's $190m Clinker Plant to Cut Imports, Save Rwanda Billions | R55: https://allafrica.com/stories/202510010022.html | S55: 2025-10-01
A56: Rwanda | B56: RK Industries Ltd | C56: Manufacturing | D56: Dar es Salaam, Tanzania (Indian-owned group) | E56: Regional manufacturer expanding into Rwanda; opened Rwanda's first-ever toothpaste factory inside the Kigali Special Economic Zone. | F56: Inaugurated Rwanda's first toothpaste factory ('ProSmile' brand) in Kigali Special Economic Zone, November 22, 2024. | G56: 2024 | H56: $5 million | I56: 5 | J56: Manufacturing Plant | K56: =IF(I56="",12,IF(I56>=100,40,IF(I56>=20,32,IF(I56>=5,24,IF(I56>=1,16,8))))) -> 24 | L56: =IF(G56="",5,IF(G56>=2023,25,IF(G56>=2022,20,IF(G56>=2021,14,IF(G56>=2020,8,5))))) -> 25 | M56: =IFERROR(INDEX(Methodology!$B$27:$B$36,MATCH(J56,Methodology!$A$27:$A$36,0)),12) -> 20 | N56: =IF(COUNTIF(Infrastructure!$A:$A,A56)>=4,15,IF(COUNTIF(Infrastructure!$A:$A,A56)>=2,10,IF(COUNTIF(Infrastructure!$A:$A,A56)>=1,5,0))) -> 15 | O56: =K56+L56+M56+N56 -> 84 | P56: =IF(O56>=70,"High",IF(O56>=50,"Medium","Watch")) -> High | Q56: FEATURED: RK Industries opens Rwanda's first toothpaste factory | R56: https://www.newtimes.co.rw/article/22073/news/featured/featured-rk-industries-opens-rwandas-first-toothpaste-factory | S56: 2024-11-24
A57: Rwanda | B57: Volkswagen AG (Volkswagen Mobility Solutions Rwanda) | C57: Manufacturing | D57: Wolfsburg, Germany | E57: Operates Rwanda's Volkswagen vehicle assembly plant and mobility/ride-hailing business (Move) in Kigali, its first sub-Saharan assembly plant outside South Africa/Nigeria/Ghana/Kenya cluster. | F57: Confirmed it will relocate its Rwanda assembly, retail and mobility operations to a larger facility within Kigali Special Economic Zone to support expansion, effective April 1, 2026; investment amount not disclosed. | G57: 2026 | H57: Not disclosed | J57: Manufacturing Plant | K57: =IF(I57="",12,IF(I57>=100,40,IF(I57>=20,32,IF(I57>=5,24,IF(I57>=1,16,8))))) -> 12 | L57: =IF(G57="",5,IF(G57>=2023,25,IF(G57>=2022,20,IF(G57>=2021,14,IF(G57>=2020,8,5))))) -> 25 | M57: =IFERROR(INDEX(Methodology!$B$27:$B$36,MATCH(J57,Methodology!$A$27:$A$36,0)),12) -> 20 | N57: =IF(COUNTIF(Infrastructure!$A:$A,A57)>=4,15,IF(COUNTIF(Infrastructure!$A:$A,A57)>=2,10,IF(COUNTIF(Infrastructure!$A:$A,A57)>=1,5,0))) -> 15 | O57: =K57+L57+M57+N57 -> 72 | P57: =IF(O57>=70,"High",IF(O57>=50,"Medium","Watch")) -> High | Q57: Volkswagen: We're in Rwanda to stay | R57: https://www.theeastafrican.co.ke/tea/business-tech/volkswagen-we-re-in-rwanda-to-stay-5402574 | S57: 2025
A58: Rwanda | B58: AGL Rwanda (Africa Global Logistics, MSC Group) | C58: Logistics | D58: Marseille, France (AGL, part of the MSC Group) | E58: Operates 21,000 sqm of bonded/duty-free warehousing across six sites in Rwanda's Kigali Special Economic Zone, a major freight-forwarding and customs logistics operator. | F58: Laid the foundation stone for a 5,000 sqm warehouse extension with cold-chain capability in the Kigali Special Economic Zone, April 15, 2024. | G58: 2024 | H58: $10 million | I58: 10 | J58: Distribution Center | K58: =IF(I58="",12,IF(I58>=100,40,IF(I58>=20,32,IF(I58>=5,24,IF(I58>=1,16,8))))) -> 24 | L58: =IF(G58="",5,IF(G58>=2023,25,IF(G58>=2022,20,IF(G58>=2021,14,IF(G58>=2020,8,5))))) -> 25 | M58: =IFERROR(INDEX(Methodology!$B$27:$B$36,MATCH(J58,Methodology!$A$27:$A$36,0)),12) -> 14 | N58: =IF(COUNTIF(Infrastructure!$A:$A,A58)>=4,15,IF(COUNTIF(Infrastructure!$A:$A,A58)>=2,10,IF(COUNTIF(Infrastructure!$A:$A,A58)>=1,5,0))) -> 15 | O58: =K58+L58+M58+N58 -> 78 | P58: =IF(O58>=70,"High",IF(O58>=50,"Medium","Watch")) -> High | Q58: AGL Rwanda lays the foundation stone for the extension of its logistics warehouse in Kigali | R58: https://logistafrica.com/en/logistic/agl-rwanda-lays-the-foundation-stone-for-the-extension-of-its-logistics-warehouse-in-kigali/ | S58: 2024-04-15
A59: Rwanda | B59: Zipline International Inc. | C59: Logistics | D59: South San Francisco, California, USA | E59: Has operated autonomous drone delivery of blood and medical supplies in Rwanda since 2016; Rwanda became the first country to achieve nationwide autonomous logistics coverage, including Africa's first urban drone delivery network in Kigali. | F59: Rwanda and the U.S. State Department signed a $150 million 'pay-for-performance' expansion deal deploying Platform 2 urban delivery drones in Kigali and a new distribution hub in Karongi District, plus Zipline's first international AI/robotics testing facility; announced February 6, 2026. | G59: 2026 | H59: $150 million | I59: 150 | J59: Distribution Center | K59: =IF(I59="",12,IF(I59>=100,40,IF(I59>=20,32,IF(I59>=5,24,IF(I59>=1,16,8))))) -> 40 | L59: =IF(G59="",5,IF(G59>=2023,25,IF(G59>=2022,20,IF(G59>=2021,14,IF(G59>=2020,8,5))))) -> 25 | M59: =IFERROR(INDEX(Methodology!$B$27:$B$36,MATCH(J59,Methodology!$A$27:$A$36,0)),12) -> 14 | N59: =IF(COUNTIF(Infrastructure!$A:$A,A59)>=4,15,IF(COUNTIF(Infrastructure!$A:$A,A59)>=2,10,IF(COUNTIF(Infrastructure!$A:$A,A59)>=1,5,0))) -> 15 | O59: =K59+L59+M59+N59 -> 94 | P59: =IF(O59>=70,"High",IF(O59>=50,"Medium","Watch")) -> High | Q59: Rwanda Signs $150 Million Expansion Deal With US-Based Zipline for Nationwide Drone Medical Deliveries | R59: https://empowerafrica.com/rwanda-signs-150-million-expansion-deal-with-us-based-zipline-for-nationwide-drone-medical-deliveries/ | S59: 2026-02-06
A60: Rwanda | B60: Groupe Duval (Inzovu Mall / U Express) | C60: Retail | D60: Paris, France (Groupe Duval); U Express is a Systeme U (France) supermarket brand | E60: Developing Kigali's largest shopping mall (Inzovu Mall, Kimihurura) and bringing the French U Express supermarket chain into Rwanda as anchor tenant, with plans for 10 stores nationwide over 5 years. | F60: Construction of the $68-71M, 40,000 sqm Inzovu Mall began August 2023 (IFC and Proparco each providing $17.5M); first U Express store slated to open at the mall in early 2026, with completion/public opening late 2025. | G60: 2023 | H60: $68-71 million (Inzovu Mall project) | I60: 69.5 | J60: Retail Store/Mall | K60: =IF(I60="",12,IF(I60>=100,40,IF(I60>=20,32,IF(I60>=5,24,IF(I60>=1,16,8))))) -> 32 | L60: =IF(G60="",5,IF(G60>=2023,25,IF(G60>=2022,20,IF(G60>=2021,14,IF(G60>=2020,8,5))))) -> 25 | M60: =IFERROR(INDEX(Methodology!$B$27:$B$36,MATCH(J60,Methodology!$A$27:$A$36,0)),12) -> 8 | N60: =IF(COUNTIF(Infrastructure!$A:$A,A60)>=4,15,IF(COUNTIF(Infrastructure!$A:$A,A60)>=2,10,IF(COUNTIF(Infrastructure!$A:$A,A60)>=1,5,0))) -> 15 | O60: =K60+L60+M60+N60 -> 80 | P60: =IF(O60>=70,"High",IF(O60>=50,"Medium","Watch")) -> High | Q60: Inzovu Mall developer, French supermarket chain to open 10 stores in Rwanda | R60: https://en.igihe.com/business-62/article/inzovu-mall-developer-french-supermarket-chain-to-open-10-stores-in-rwanda | S60: 2024
A61: Rwanda | B61: Simba Supermarket Ltd | C61: Retail | D61: Kigali, Rwanda | E61: Rwandan-owned supermarket chain, one of the country's largest retail grocery operators with a nationwide branch network. | F61: Opened its 13th branch, in Rubavu, as part of continued nationwide expansion; reported March 16, 2025. | G61: 2025 | H61: Not disclosed | J61: Retail Store/Mall | K61: =IF(I61="",12,IF(I61>=100,40,IF(I61>=20,32,IF(I61>=5,24,IF(I61>=1,16,8))))) -> 12 | L61: =IF(G61="",5,IF(G61>=2023,25,IF(G61>=2022,20,IF(G61>=2021,14,IF(G61>=2020,8,5))))) -> 25 | M61: =IFERROR(INDEX(Methodology!$B$27:$B$36,MATCH(J61,Methodology!$A$27:$A$36,0)),12) -> 8 | N61: =IF(COUNTIF(Infrastructure!$A:$A,A61)>=4,15,IF(COUNTIF(Infrastructure!$A:$A,A61)>=2,10,IF(COUNTIF(Infrastructure!$A:$A,A61)>=1,5,0))) -> 15 | O61: =K61+L61+M61+N61 -> 60 | P61: =IF(O61>=70,"High",IF(O61>=50,"Medium","Watch")) -> Medium | Q61: Simba Supermarket Expands to Rubavu, Boosting Local Economy and Employment | R61: https://taarifa.rw/index.php/2025/03/16/simba-supermarket-expands-to-rubavu-boosting-local-economy-and-employment/ | S61: 2025-03-16
A62: Rwanda | B62: African Pharmaceutical Technology Foundation (APTF) | C62: Pharma | D62: Kigali, Rwanda (pan-African regional body, backed by African Development Fund) | E62: Rwanda-headquartered foundation established with Rwanda's Ministry of Health to build regional pharmaceutical manufacturing capacity and collective medicine procurement for Africa. | F62: African Development Fund board approved $12M financing for APTF's rapid operationalization in Kigali; financing approved February 2024, project launched in Kigali May 2024. | G62: 2024 | H62: $12 million | I62: 12 | J62: R&D Centre | K62: =IF(I62="",12,IF(I62>=100,40,IF(I62>=20,32,IF(I62>=5,24,IF(I62>=1,16,8))))) -> 24 | L62: =IF(G62="",5,IF(G62>=2023,25,IF(G62>=2022,20,IF(G62>=2021,14,IF(G62>=2020,8,5))))) -> 25 | M62: =IFERROR(INDEX(Methodology!$B$27:$B$36,MATCH(J62,Methodology!$A$27:$A$36,0)),12) -> 14 | N62: =IF(COUNTIF(Infrastructure!$A:$A,A62)>=4,15,IF(COUNTIF(Infrastructure!$A:$A,A62)>=2,10,IF(COUNTIF(Infrastructure!$A:$A,A62)>=1,5,0))) -> 15 | O62: =K62+L62+M62+N62 -> 78 | P62: =IF(O62>=70,"High",IF(O62>=50,"Medium","Watch")) -> High | Q62: The $12M Regional Pharmaceutical Project Launched in Kigali | R62: https://www.ktpress.rw/2024/05/the-12m-regional-pharmaceutical-project-launched-in-kigali/ | S62: 2024-05
A63: Rwanda | B63: BioNTech SE | C63: Pharma | D63: Mainz, Germany | E63: Operates Africa's first end-to-end mRNA vaccine manufacturing facility in Kigali (inaugurated 2023), built to produce vaccines for malaria, TB, HIV and mpox using modular 'BioNTainer' units; anchor tenant of Rwanda's emerging pharma manufacturing base. | F63: EU Commission and European Investment Bank signed a blended-finance agreement (EUR35M grant + up to EUR60M EIB loan) to scale up the Kigali mRNA facility, announced/signed October 8-13, 2025. | G63: 2025 | H63: Up to EUR95 million (EU/EIB) on top of BioNTech's original ~$150 million facility build | I63: 102.6 | J63: Hospital/Pharma Plant | K63: =IF(I63="",12,IF(I63>=100,40,IF(I63>=20,32,IF(I63>=5,24,IF(I63>=1,16,8))))) -> 40 | L63: =IF(G63="",5,IF(G63>=2023,25,IF(G63>=2022,20,IF(G63>=2021,14,IF(G63>=2020,8,5))))) -> 25 | M63: =IFERROR(INDEX(Methodology!$B$27:$B$36,MATCH(J63,Methodology!$A$27:$A$36,0)),12) -> 18 | N63: =IF(COUNTIF(Infrastructure!$A:$A,A63)>=4,15,IF(COUNTIF(Infrastructure!$A:$A,A63)>=2,10,IF(COUNTIF(Infrastructure!$A:$A,A63)>=1,5,0))) -> 15 | O63: =K63+L63+M63+N63 -> 98 | P63: =IF(O63>=70,"High",IF(O63>=50,"Medium","Watch")) -> High | Q63: EIB and European Commission join forces with BioNTech to build a sustainable vaccine ecosystem in Africa | R63: https://www.eib.org/en/press/all/2025-380-eib-and-european-commission-join-forces-with-biontech-to-build-a-sustainable-vaccine-ecosystem-in-africa | S63: 2025-10-13
A64: Rwanda | B64: Africa Data Centres (Cassava Technologies) | C64: Technology | D64: Johannesburg, South Africa (Cassava Technologies, part of Econet Group) | E64: Building its first data centre in Kigali as part of Cassava Technologies' $500 million plan to build 10 data centres across Africa, supporting Rwanda's digital transformation agenda. | F64: Broke ground on a purpose-built 2MW data centre in Kigali, Q1 2023. | G64: 2023 | H64: Not disclosed | J64: Data Centre | K64: =IF(I64="",12,IF(I64>=100,40,IF(I64>=20,32,IF(I64>=5,24,IF(I64>=1,16,8))))) -> 12 | L64: =IF(G64="",5,IF(G64>=2023,25,IF(G64>=2022,20,IF(G64>=2021,14,IF(G64>=2020,8,5))))) -> 25 | M64: =IFERROR(INDEX(Methodology!$B$27:$B$36,MATCH(J64,Methodology!$A$27:$A$36,0)),12) -> 20 | N64: =IF(COUNTIF(Infrastructure!$A:$A,A64)>=4,15,IF(COUNTIF(Infrastructure!$A:$A,A64)>=2,10,IF(COUNTIF(Infrastructure!$A:$A,A64)>=1,5,0))) -> 15 | O64: =K64+L64+M64+N64 -> 72 | P64: =IF(O64>=70,"High",IF(O64>=50,"Medium","Watch")) -> High | Q64: Africa Data Centres to build its first data centre in Kigali, Rwanda | R64: https://www.africadatacentres.com/africa-data-centres-to-build-its-first-data-centre-in-kigali-rwanda/ | S64: 2023
A65: Rwanda | B65: Paratus Rwanda (Paratus Group) | C65: Technology | D65: Windhoek, Namibia (pan-African network operator) | E65: Paratus Rwanda is a pan-African telecom infrastructure and connectivity provider that opened operations in Rwanda in October 2025, offering fibre, satellite and cloud connectivity including Starlink services (Starlink for Business) to Rwandan enterprises. | F65: Opened operations in Rwanda ("Paratus opens in Rwanda"), October 22, 2025, and has continued expanding its local team and Starlink-based connectivity offering, including a showcase of its Starlink for Business suite at AfPIF 2026 (August 24, 2026). | G65: 2025 | H65: Not disclosed | J65: Regional HQ / Network Infrastructure | K65: =IF(I65="",12,IF(I65>=100,40,IF(I65>=20,32,IF(I65>=5,24,IF(I65>=1,16,8))))) -> 12 | L65: =IF(G65="",5,IF(G65>=2023,25,IF(G65>=2022,20,IF(G65>=2021,14,IF(G65>=2020,8,5))))) -> 25 | M65: =IFERROR(INDEX(Methodology!$B$27:$B$36,MATCH(J65,Methodology!$A$27:$A$36,0)),12) -> 12 | N65: =IF(COUNTIF(Infrastructure!$A:$A,A65)>=4,15,IF(COUNTIF(Infrastructure!$A:$A,A65)>=2,10,IF(COUNTIF(Infrastructure!$A:$A,A65)>=1,5,0))) -> 15 | O65: =K65+L65+M65+N65 -> 64 | P65: =IF(O65>=70,"High",IF(O65>=50,"Medium","Watch")) -> Medium | Q65: Paratus opens in Rwanda | R65: https://paratus.co.rw/news/ | S65: October 22, 2025
A66: Rwanda | B66: ARISE Integrated Industrial Platforms (ARISE IIP) | C66: Construction | D66: Ebene, Mauritius (backed by Africa Finance Corporation) | E66: Pan-African industrial-zone developer; co-developing Rwanda's Bugesera Special Economic Zone (BSEZ) through joint venture BSEZ Ltd with the Government of Rwanda. | F66: Bank of Kigali ($33M) and Development Bank of Rwanda ($19M) injected a combined $52 million into the 335-hectare Bugesera Industrial Park/SEZ (part of a $100M project launched in 2023, Phase 1 of 75 hectares already operational), targeting light manufacturing, agro-processing, pharma and logistics tenants; reported August 2025. | G66: 2023 | H66: $52 million (recent tranche); $100 million total project | I66: 52 | J66: Construction Project | K66: =IF(I66="",12,IF(I66>=100,40,IF(I66>=20,32,IF(I66>=5,24,IF(I66>=1,16,8))))) -> 32 | L66: =IF(G66="",5,IF(G66>=2023,25,IF(G66>=2022,20,IF(G66>=2021,14,IF(G66>=2020,8,5))))) -> 25 | M66: =IFERROR(INDEX(Methodology!$B$27:$B$36,MATCH(J66,Methodology!$A$27:$A$36,0)),12) -> 16 | N66: =IF(COUNTIF(Infrastructure!$A:$A,A66)>=4,15,IF(COUNTIF(Infrastructure!$A:$A,A66)>=2,10,IF(COUNTIF(Infrastructure!$A:$A,A66)>=1,5,0))) -> 15 | O66: =K66+L66+M66+N66 -> 88 | P66: =IF(O66>=70,"High",IF(O66>=50,"Medium","Watch")) -> High | Q66: BK, BRD Inject $52M into Bugesera Industrial Park | R66: https://www.ktpress.rw/2025/08/bk-brd-inject-52m-into-bugesera-industrial-park/ | S66: 2025-08
A67: Rwanda | B67: Mota-Engil | C67: Construction | D67: Porto, Portugal | E67: Lead construction contractor for Rwanda's flagship Bugesera International Airport project near Kigali, including the passenger terminal and cargo terminal (the largest steel structure of its kind in Rwanda). | F67: Continued major construction works on the ~$2 billion Bugesera International Airport (Mota-Engil's original contract from 2016 covering an $818M first phase), with visible progress reported through 2025 and phased completion targeted for 2024/2025 (8M passenger capacity) and 2028 (full build-out). | G67: 2016 | H67: $818 million (Mota-Engil's original construction phases); total project ~$2 billion | I67: 818 | J67: Construction Project | K67: =IF(I67="",12,IF(I67>=100,40,IF(I67>=20,32,IF(I67>=5,24,IF(I67>=1,16,8))))) -> 40 | L67: =IF(G67="",5,IF(G67>=2023,25,IF(G67>=2022,20,IF(G67>=2021,14,IF(G67>=2020,8,5))))) -> 5 | M67: =IFERROR(INDEX(Methodology!$B$27:$B$36,MATCH(J67,Methodology!$A$27:$A$36,0)),12) -> 16 | N67: =IF(COUNTIF(Infrastructure!$A:$A,A67)>=4,15,IF(COUNTIF(Infrastructure!$A:$A,A67)>=2,10,IF(COUNTIF(Infrastructure!$A:$A,A67)>=1,5,0))) -> 15 | O67: =K67+L67+M67+N67 -> 76 | P67: =IF(O67>=70,"High",IF(O67>=50,"Medium","Watch")) -> High | Q67: Bugesera International Airport construction takes shape | R67: https://en.igihe.com/news/article/bugesera-international-airport-construction-takes-shape | S67: 2025-05
A68: Seychelles | B68: Thai Union Group (Indian Ocean Tuna Ltd) | C68: Manufacturing | D68: Bangkok, Thailand | E68: Thai Union owns a majority (60%) stake in Indian Ocean Tuna Ltd, which operates one of the world's largest tuna canneries in Victoria, Seychelles. | F68: Thai Union announced a further EUR 10 million investment into the Seychelles cannery (on top of a prior EUR 40 million upgrade), announced late April/early May 2022. | G68: 2022 | H68: EUR 10 million additional (approx. USD 10.2 million) | I68: 10.8 | J68: Manufacturing Plant | K68: =IF(I68="",12,IF(I68>=100,40,IF(I68>=20,32,IF(I68>=5,24,IF(I68>=1,16,8))))) -> 24 | L68: =IF(G68="",5,IF(G68>=2023,25,IF(G68>=2022,20,IF(G68>=2021,14,IF(G68>=2020,8,5))))) -> 20 | M68: =IFERROR(INDEX(Methodology!$B$27:$B$36,MATCH(J68,Methodology!$A$27:$A$36,0)),12) -> 20 | N68: =IF(COUNTIF(Infrastructure!$A:$A,A68)>=4,15,IF(COUNTIF(Infrastructure!$A:$A,A68)>=2,10,IF(COUNTIF(Infrastructure!$A:$A,A68)>=1,5,0))) -> 5 | O68: =K68+L68+M68+N68 -> 69 | P68: =IF(O68>=70,"High",IF(O68>=50,"Medium","Watch")) -> Medium | Q68: Thai Union to invest another €10m in Seychelles tuna plant | R68: https://www.undercurrentnews.com/2022/05/04/thai-union-to-invest-another-e10m-in-seychelles-tuna-plant/ | S68: 2022-05-04
A69: Seychelles | B69: Seychelles Trading Company (STC) | C69: Retail | D69: Victoria, Seychelles | E69: STC is Seychelles' major state-owned wholesale, import, distribution and retail group. | F69: STC inaugurated a new state-of-the-art SCR 110 million cold storage facility at Bois de Rose on 13 June 2025. | G69: 2025 | H69: SCR 110 million (self-financed) | J69: Distribution Center | K69: =IF(I69="",12,IF(I69>=100,40,IF(I69>=20,32,IF(I69>=5,24,IF(I69>=1,16,8))))) -> 12 | L69: =IF(G69="",5,IF(G69>=2023,25,IF(G69>=2022,20,IF(G69>=2021,14,IF(G69>=2020,8,5))))) -> 25 | M69: =IFERROR(INDEX(Methodology!$B$27:$B$36,MATCH(J69,Methodology!$A$27:$A$36,0)),12) -> 14 | N69: =IF(COUNTIF(Infrastructure!$A:$A,A69)>=4,15,IF(COUNTIF(Infrastructure!$A:$A,A69)>=2,10,IF(COUNTIF(Infrastructure!$A:$A,A69)>=1,5,0))) -> 5 | O69: =K69+L69+M69+N69 -> 56 | P69: =IF(O69>=70,"High",IF(O69>=50,"Medium","Watch")) -> Medium | Q69: Seychelles Trading Company Unveils State-of-the-Art Cold Storage Facility to Strengthen National Food Security | R69: https://www.statehouse.gov.sc/news/6499/seychelles-trading-company-unveils-state-of-the-art-cold-storage-facility-to-strengthen-national-food-security | S69: 2025-06-13
A70: Seychelles | B70: Cable & Wireless Seychelles | C70: Technology | D70: Victoria, Seychelles | E70: Cable & Wireless Seychelles is one of the country's two main telecom/ISP operators. | F70: Inaugurated the 'Bon Espoir' Data Centre, Seychelles' first Tier IV data centre, unveiled 22 November 2024. | G70: 2024 | H70: Not disclosed | J70: Data Centre | K70: =IF(I70="",12,IF(I70>=100,40,IF(I70>=20,32,IF(I70>=5,24,IF(I70>=1,16,8))))) -> 12 | L70: =IF(G70="",5,IF(G70>=2023,25,IF(G70>=2022,20,IF(G70>=2021,14,IF(G70>=2020,8,5))))) -> 25 | M70: =IFERROR(INDEX(Methodology!$B$27:$B$36,MATCH(J70,Methodology!$A$27:$A$36,0)),12) -> 20 | N70: =IF(COUNTIF(Infrastructure!$A:$A,A70)>=4,15,IF(COUNTIF(Infrastructure!$A:$A,A70)>=2,10,IF(COUNTIF(Infrastructure!$A:$A,A70)>=1,5,0))) -> 5 | O70: =K70+L70+M70+N70 -> 62 | P70: =IF(O70>=70,"High",IF(O70>=50,"Medium","Watch")) -> Medium | Q70: Cable & Wireless inaugurates state-of-the-art data centre | R70: https://www.nation.sc/articles/24190/cable--wireless-inaugurates-state-of-the-art-data-centre | S70: 2024-11-22
A71: Somalia | B71: IFFCO Somaliland | C71: Manufacturing | D71: Sharjah/Dubai, United Arab Emirates | E71: IFFCO, a Gulf-based FMCG/edible-oils conglomerate, entered Somaliland by signing a 25-year lease to build a large edible-oil packing plant inside DP World's Berbera Economic Zone. | F71: IFFCO announced construction of a 300,000 sq ft edible oil packing plant at the Berbera Economic Zone, announced 8 November 2022. | G71: 2022 | H71: Not disclosed | J71: Manufacturing Plant | K71: =IF(I71="",12,IF(I71>=100,40,IF(I71>=20,32,IF(I71>=5,24,IF(I71>=1,16,8))))) -> 12 | L71: =IF(G71="",5,IF(G71>=2023,25,IF(G71>=2022,20,IF(G71>=2021,14,IF(G71>=2020,8,5))))) -> 20 | M71: =IFERROR(INDEX(Methodology!$B$27:$B$36,MATCH(J71,Methodology!$A$27:$A$36,0)),12) -> 20 | N71: =IF(COUNTIF(Infrastructure!$A:$A,A71)>=4,15,IF(COUNTIF(Infrastructure!$A:$A,A71)>=2,10,IF(COUNTIF(Infrastructure!$A:$A,A71)>=1,5,0))) -> 10 | O71: =K71+L71+M71+N71 -> 62 | P71: =IF(O71>=70,"High",IF(O71>=50,"Medium","Watch")) -> Medium | Q71: IFFCO to develop 300,000 square feet edible oil packing plant at DP World's Berbera Economic Zone, Somaliland | R71: https://www.dpworld.com/news/releases/iffco-develops-edible-oil-packing-plant-at-dp-worlds-economic-zone-somaliland/ | S71: 2022-11-08
A72: Somalia | B72: Hayat Market (Safa International Group) | C72: Retail | D72: Mogadishu, Somalia | E72: Hayat Market is a modern supermarket chain in Mogadishu operated by UAE-based Safa International Group. | F72: Since opening its first branch in April 2020, Hayat Market expanded to at least five branches across Mogadishu districts by 2025, named Best Supermarket Chain of the Year at the 2024 East Africa Somali Awards. | G72: 2020 | H72: Not disclosed | J72: Retail Store/Mall | K72: =IF(I72="",12,IF(I72>=100,40,IF(I72>=20,32,IF(I72>=5,24,IF(I72>=1,16,8))))) -> 12 | L72: =IF(G72="",5,IF(G72>=2023,25,IF(G72>=2022,20,IF(G72>=2021,14,IF(G72>=2020,8,5))))) -> 8 | M72: =IFERROR(INDEX(Methodology!$B$27:$B$36,MATCH(J72,Methodology!$A$27:$A$36,0)),12) -> 8 | N72: =IF(COUNTIF(Infrastructure!$A:$A,A72)>=4,15,IF(COUNTIF(Infrastructure!$A:$A,A72)>=2,10,IF(COUNTIF(Infrastructure!$A:$A,A72)>=1,5,0))) -> 10 | O72: =K72+L72+M72+N72 -> 38 | P72: =IF(O72>=70,"High",IF(O72>=50,"Medium","Watch")) -> Watch | Q72: Hayat Market | R72: https://en.wikipedia.org/wiki/Hayat_Market | S72: 2025
A73: Somalia | B73: Rotana Hotel Management (with Riverside Holding) | C73: Construction | D73: Abu Dhabi, United Arab Emirates | E73: Rotana is entering the Somali market in partnership with local developer Riverside Holding. | F73: Announced construction of the Mogadishu Rotana, Somalia's first five-star hotel (321 keys), targeting completion in 2026. | G73: 2026 | H73: Not disclosed | J73: Construction Project | K73: =IF(I73="",12,IF(I73>=100,40,IF(I73>=20,32,IF(I73>=5,24,IF(I73>=1,16,8))))) -> 12 | L73: =IF(G73="",5,IF(G73>=2023,25,IF(G73>=2022,20,IF(G73>=2021,14,IF(G73>=2020,8,5))))) -> 25 | M73: =IFERROR(INDEX(Methodology!$B$27:$B$36,MATCH(J73,Methodology!$A$27:$A$36,0)),12) -> 16 | N73: =IF(COUNTIF(Infrastructure!$A:$A,A73)>=4,15,IF(COUNTIF(Infrastructure!$A:$A,A73)>=2,10,IF(COUNTIF(Infrastructure!$A:$A,A73)>=1,5,0))) -> 10 | O73: =K73+L73+M73+N73 -> 63 | P73: =IF(O73>=70,"High",IF(O73>=50,"Medium","Watch")) -> Medium | Q73: Rotana Unveils Plans for Mogadishu Rotana – The First-Ever Five-Star Hotel in Somalia | R73: https://alephhospitality.com/news/rotana-unveils-plans-for-mogadishu-rotana-the-first-ever-five-star-hotel-in-somalia/ | S73: 2024
A74: South Sudan | B74: Trinity Energy Group | C74: Manufacturing | D74: Juba, South Sudan | E74: Trinity Energy is a leading indigenous South Sudanese energy company operating fuel import, storage and distribution infrastructure. | F74: Advancing a planned USD 500 million, initially 60,000 bpd domestic oil refinery at Paloch, Upper Nile State; as of July 2024 had completed feasibility studies and secured land/concession. | G74: 2024 | H74: USD 500 million (announced project cost) | J74: Manufacturing Plant | K74: =IF(I74="",12,IF(I74>=100,40,IF(I74>=20,32,IF(I74>=5,24,IF(I74>=1,16,8))))) -> 12 | L74: =IF(G74="",5,IF(G74>=2023,25,IF(G74>=2022,20,IF(G74>=2021,14,IF(G74>=2020,8,5))))) -> 25 | M74: =IFERROR(INDEX(Methodology!$B$27:$B$36,MATCH(J74,Methodology!$A$27:$A$36,0)),12) -> 20 | N74: =IF(COUNTIF(Infrastructure!$A:$A,A74)>=4,15,IF(COUNTIF(Infrastructure!$A:$A,A74)>=2,10,IF(COUNTIF(Infrastructure!$A:$A,A74)>=1,5,0))) -> 10 | O74: =K74+L74+M74+N74 -> 67 | P74: =IF(O74>=70,"High",IF(O74>=50,"Medium","Watch")) -> Medium | Q74: South Sudan's Trinity Energy eyes domestic refinery despite local industry woes | R74: https://african.business/2024/07/resources/south-sudans-trinity-energy-eyes-domestic-refinery-despite-local-industry-woes | S74: 2024-07-10
A75: South Sudan | B75: Brilliant Pharmaceutical Company (BPC) | C75: Pharma | D75: Juba, South Sudan | E75: Brilliant Pharmaceutical Company is an indigenous South Sudanese pharmaceutical supplier based in Muniki, Juba. | F75: Became fully operational and was officially launched on 12 October 2025, supplying anti-malarial and antibiotic products domestically. | G75: 2025 | H75: Not disclosed | J75: Hospital/Pharma Plant | K75: =IF(I75="",12,IF(I75>=100,40,IF(I75>=20,32,IF(I75>=5,24,IF(I75>=1,16,8))))) -> 12 | L75: =IF(G75="",5,IF(G75>=2023,25,IF(G75>=2022,20,IF(G75>=2021,14,IF(G75>=2020,8,5))))) -> 25 | M75: =IFERROR(INDEX(Methodology!$B$27:$B$36,MATCH(J75,Methodology!$A$27:$A$36,0)),12) -> 18 | N75: =IF(COUNTIF(Infrastructure!$A:$A,A75)>=4,15,IF(COUNTIF(Infrastructure!$A:$A,A75)>=2,10,IF(COUNTIF(Infrastructure!$A:$A,A75)>=1,5,0))) -> 10 | O75: =K75+L75+M75+N75 -> 65 | P75: =IF(O75>=70,"High",IF(O75>=50,"Medium","Watch")) -> Medium | Q75: Brilliant Pharmaceutical Company opens in Juba | R75: https://www.onecitizendaily.com/index.php/2025/10/13/brilliant-pharmaceutical-company-opens-in-juba/ | S75: 2025-10-13
A76: South Sudan | B76: Bayobab (MTN Group) | C76: Technology | D76: Johannesburg, South Africa | E76: Bayobab is MTN Group's pan-African wholesale infrastructure business, newly licensed to build and operate fibre networks in South Sudan. | F76: South Sudan's National Communications Authority issued Bayobab a 15-year license (issued 16 October 2025, announced 28 November 2025) as part of its wider USD 320 million 'Project East 2 West' continental fibre corridor. | G76: 2025 | H76: Part of a broader USD 320 million pan-African initiative; South Sudan-specific figure not disclosed | J76: Regional HQ / Network Infrastructure | K76: =IF(I76="",12,IF(I76>=100,40,IF(I76>=20,32,IF(I76>=5,24,IF(I76>=1,16,8))))) -> 12 | L76: =IF(G76="",5,IF(G76>=2023,25,IF(G76>=2022,20,IF(G76>=2021,14,IF(G76>=2020,8,5))))) -> 25 | M76: =IFERROR(INDEX(Methodology!$B$27:$B$36,MATCH(J76,Methodology!$A$27:$A$36,0)),12) -> 12 | N76: =IF(COUNTIF(Infrastructure!$A:$A,A76)>=4,15,IF(COUNTIF(Infrastructure!$A:$A,A76)>=2,10,IF(COUNTIF(Infrastructure!$A:$A,A76)>=1,5,0))) -> 10 | O76: =K76+L76+M76+N76 -> 59 | P76: =IF(O76>=70,"High",IF(O76>=50,"Medium","Watch")) -> Medium | Q76: MTN's Bayobab licenced to operate fibre networks in South Sudan | R76: https://developingtelecoms.com/telecom-technology/optical-fixed-networks/19414-mtns-bayobab-licenced-to-operate-fibre-networks-in-south-sudan.html | S76: 2025-11-28
A77: South Sudan | B77: Shandong Hi-Speed Group (SDHS) | C77: Construction | D77: Jinan, Shandong, China | E77: Shandong Hi-Speed Group is a Chinese state-owned infrastructure conglomerate contracted for major South Sudanese highway construction. | F77: Signed/renewed a contract (announced 3 December 2020) to build the 392 km Juba-Rumbek highway, including 10 bridges, 35 box culverts and 21 viaducts. | G77: 2020 | H77: Not disclosed | J77: Construction Project | K77: =IF(I77="",12,IF(I77>=100,40,IF(I77>=20,32,IF(I77>=5,24,IF(I77>=1,16,8))))) -> 12 | L77: =IF(G77="",5,IF(G77>=2023,25,IF(G77>=2022,20,IF(G77>=2021,14,IF(G77>=2020,8,5))))) -> 8 | M77: =IFERROR(INDEX(Methodology!$B$27:$B$36,MATCH(J77,Methodology!$A$27:$A$36,0)),12) -> 16 | N77: =IF(COUNTIF(Infrastructure!$A:$A,A77)>=4,15,IF(COUNTIF(Infrastructure!$A:$A,A77)>=2,10,IF(COUNTIF(Infrastructure!$A:$A,A77)>=1,5,0))) -> 10 | O77: =K77+L77+M77+N77 -> 46 | P77: =IF(O77>=70,"High",IF(O77>=50,"Medium","Watch")) -> Watch | Q77: South Sudan, Chinese firm renew contract for road construction | R77: https://pachodo.org/news-from-various-sources/26220-south-sudan-chinese-firm-renew-contract-for-road-construction | S77: 2020-12-03
A78: Tanzania | B78: Amsons Group | C78: Manufacturing | D78: Dar es Salaam, Tanzania | E78: Tanzania-founded (2000) conglomerate with cement, construction, transport, flour and container-depot interests; expanding aggressively into Kenya (Bamburi Cement acquisition) and Zambia. | F78: Announced $320 million greenfield cement plant investment in Tanzania (1.6Mt/yr capacity), adding to its existing Camel Cement grinding plant and 65% stake in Mbeya Cement, November 2024. | G78: 2024 | H78: $320 million | I78: 320 | J78: Manufacturing Plant | K78: =IF(I78="",12,IF(I78>=100,40,IF(I78>=20,32,IF(I78>=5,24,IF(I78>=1,16,8))))) -> 40 | L78: =IF(G78="",5,IF(G78>=2023,25,IF(G78>=2022,20,IF(G78>=2021,14,IF(G78>=2020,8,5))))) -> 25 | M78: =IFERROR(INDEX(Methodology!$B$27:$B$36,MATCH(J78,Methodology!$A$27:$A$36,0)),12) -> 20 | N78: =IF(COUNTIF(Infrastructure!$A:$A,A78)>=4,15,IF(COUNTIF(Infrastructure!$A:$A,A78)>=2,10,IF(COUNTIF(Infrastructure!$A:$A,A78)>=1,5,0))) -> 15 | O78: =K78+L78+M78+N78 -> 100 | P78: =IF(O78>=70,"High",IF(O78>=50,"Medium","Watch")) -> High | Q78: Amsons Group takes aim at East Africa | R78: https://www.globalcement.com/news/analysis/18696-amsons-group-takes-aim-at-east-africa | S78: November 2024
A79: Tanzania | B79: Bakhresa Group | C79: Manufacturing | D79: Dar es Salaam, Tanzania (pan-African operations across ~11 countries) | E79: Tanzania's largest privately owned conglomerate, with flour milling, beverages, sugar and shipping operations across East and Central Africa. | F79: Announced $500 million expansion of its Mwandege facility (Mkuranga District, Pwani Region) to double soft-drink/juice production capacity, part of its 50th-anniversary investment push, targeted for completion by 2026. | G79: 2026 | H79: $500 million | I79: 500 | J79: Manufacturing Plant | K79: =IF(I79="",12,IF(I79>=100,40,IF(I79>=20,32,IF(I79>=5,24,IF(I79>=1,16,8))))) -> 40 | L79: =IF(G79="",5,IF(G79>=2023,25,IF(G79>=2022,20,IF(G79>=2021,14,IF(G79>=2020,8,5))))) -> 25 | M79: =IFERROR(INDEX(Methodology!$B$27:$B$36,MATCH(J79,Methodology!$A$27:$A$36,0)),12) -> 20 | N79: =IF(COUNTIF(Infrastructure!$A:$A,A79)>=4,15,IF(COUNTIF(Infrastructure!$A:$A,A79)>=2,10,IF(COUNTIF(Infrastructure!$A:$A,A79)>=1,5,0))) -> 15 | O79: =K79+L79+M79+N79 -> 100 | P79: =IF(O79>=70,"High",IF(O79>=50,"Medium","Watch")) -> High | Q79: Tanzanian businessman Bakhresa to invest $500 million in major factory expansion | R79: https://www.thecitizen.co.tz/tanzania/news/national/tanzanian-businessman-bakhresa-to-invest-500-million-in-major-factory-expansion-5147966 | S79: 2025
A80: Tanzania | B80: Dangote Cement Plc | C80: Manufacturing | D80: Lagos, Nigeria | E80: Operates Tanzania's largest cement manufacturing plant and is one of Africa's largest cement producers, with Tanzania a key part of its regional East/Southern Africa growth strategy. | F80: Tanzania government is courting Dangote for further multi-billion-dollar investments in fertiliser, power and industrial infrastructure, building on its existing ~$800M cement plant (2026). | G80: 2026 | H80: $800 million (existing plant); additional fertiliser/power investment amount Not disclosed | J80: Manufacturing Plant | K80: =IF(I80="",12,IF(I80>=100,40,IF(I80>=20,32,IF(I80>=5,24,IF(I80>=1,16,8))))) -> 12 | L80: =IF(G80="",5,IF(G80>=2023,25,IF(G80>=2022,20,IF(G80>=2021,14,IF(G80>=2020,8,5))))) -> 25 | M80: =IFERROR(INDEX(Methodology!$B$27:$B$36,MATCH(J80,Methodology!$A$27:$A$36,0)),12) -> 20 | N80: =IF(COUNTIF(Infrastructure!$A:$A,A80)>=4,15,IF(COUNTIF(Infrastructure!$A:$A,A80)>=2,10,IF(COUNTIF(Infrastructure!$A:$A,A80)>=1,5,0))) -> 15 | O80: =K80+L80+M80+N80 -> 72 | P80: =IF(O80>=70,"High",IF(O80>=50,"Medium","Watch")) -> High | Q80: After $800m Cement Plant, Tanzania Seeks Bigger Dangote Investments in Energy and Industry | R80: https://www.legit.ng/business-economy/energy/1724147-after-800m-cement-plant-tanzania-seeks-bigger-dangote-investments-energy-industry/ | S80: 2026
A81: Tanzania | B81: DP World | C81: Logistics | D81: Dubai, United Arab Emirates | E81: Global port and logistics operator now managing key multi-purpose terminals at the Port of Dar es Salaam under a long-term concession, positioning Tanzania as a regional trade gateway for landlocked neighbours. | F81: Signed a 30-year concession with Tanzania Ports Authority to operate multi-purpose terminals at Dar es Salaam Port, with an initial investment exceeding $250M (potentially up to $1B across the concession, including hinterland logistics and a possible SEZ), October 22, 2023. | G81: 2023 | H81: $250 million initial (up to $1 billion potential over 30-year term) | I81: 250 | J81: Distribution Center | K81: =IF(I81="",12,IF(I81>=100,40,IF(I81>=20,32,IF(I81>=5,24,IF(I81>=1,16,8))))) -> 40 | L81: =IF(G81="",5,IF(G81>=2023,25,IF(G81>=2022,20,IF(G81>=2021,14,IF(G81>=2020,8,5))))) -> 25 | M81: =IFERROR(INDEX(Methodology!$B$27:$B$36,MATCH(J81,Methodology!$A$27:$A$36,0)),12) -> 14 | N81: =IF(COUNTIF(Infrastructure!$A:$A,A81)>=4,15,IF(COUNTIF(Infrastructure!$A:$A,A81)>=2,10,IF(COUNTIF(Infrastructure!$A:$A,A81)>=1,5,0))) -> 15 | O81: =K81+L81+M81+N81 -> 94 | P81: =IF(O81>=70,"High",IF(O81>=50,"Medium","Watch")) -> High | Q81: DP World Signs 30-Year Concession to Operate Multi-Purpose Dar es Salaam Port in Tanzania | R81: https://www.dpworld.com/en/news/dp-world-signs-30-year-concession-to-operate-multi-purpose-dar-es-salaam-port-in-tanzania | S81: October 22, 2023
A82: Tanzania | B82: Scan Global Logistics | C82: Logistics | D82: Copenhagen, Denmark | E82: Global freight forwarder that opened its first Tanzania office in Dar es Salaam to complete its East African network, serving landlocked markets including Rwanda, Burundi, Zambia and the DRC via the Port of Dar es Salaam. | F82: Opened a new Dar es Salaam office (ocean/air freight, project logistics, warehousing, customs clearance) with Jan Andersson appointed Managing Director, February 3, 2025. | G82: 2025 | H82: Not disclosed | J82: Regional HQ | K82: =IF(I82="",12,IF(I82>=100,40,IF(I82>=20,32,IF(I82>=5,24,IF(I82>=1,16,8))))) -> 12 | L82: =IF(G82="",5,IF(G82>=2023,25,IF(G82>=2022,20,IF(G82>=2021,14,IF(G82>=2020,8,5))))) -> 25 | M82: =IFERROR(INDEX(Methodology!$B$27:$B$36,MATCH(J82,Methodology!$A$27:$A$36,0)),12) -> 10 | N82: =IF(COUNTIF(Infrastructure!$A:$A,A82)>=4,15,IF(COUNTIF(Infrastructure!$A:$A,A82)>=2,10,IF(COUNTIF(Infrastructure!$A:$A,A82)>=1,5,0))) -> 15 | O82: =K82+L82+M82+N82 -> 62 | P82: =IF(O82>=70,"High",IF(O82>=50,"Medium","Watch")) -> Medium | Q82: Scan Global Logistics expands into Tanzania to complete its access to East Africa | R82: https://www.scangl.com/news/scan-global-logistics-expands-into-tanzania-to-complete-its-access-to-east-africa/ | S82: February 3, 2025
A83: Tanzania | B83: Woolworths Holdings (Woolworths Tanzania) | C83: Retail | D83: Cape Town, South Africa | E83: South African retail group operating apparel/homeware stores in Tanzania - five outlets nationwide including four in Dar es Salaam (PPF Towers, Mlimani City, Palm Village, Kunduchi Mall) plus TFA Mall in Arusha. | F83: Opened a new store at Kunduchi Mall, Dar es Salaam, its fifth Tanzania outlet, with further expansion planned into Dodoma and Mwanza, January 30, 2026. | G83: 2026 | H83: Not disclosed | J83: Retail Store/Mall | K83: =IF(I83="",12,IF(I83>=100,40,IF(I83>=20,32,IF(I83>=5,24,IF(I83>=1,16,8))))) -> 12 | L83: =IF(G83="",5,IF(G83>=2023,25,IF(G83>=2022,20,IF(G83>=2021,14,IF(G83>=2020,8,5))))) -> 25 | M83: =IFERROR(INDEX(Methodology!$B$27:$B$36,MATCH(J83,Methodology!$A$27:$A$36,0)),12) -> 8 | N83: =IF(COUNTIF(Infrastructure!$A:$A,A83)>=4,15,IF(COUNTIF(Infrastructure!$A:$A,A83)>=2,10,IF(COUNTIF(Infrastructure!$A:$A,A83)>=1,5,0))) -> 15 | O83: =K83+L83+M83+N83 -> 60 | P83: =IF(O83>=70,"High",IF(O83>=50,"Medium","Watch")) -> Medium | Q83: Woolworths Tanzania opens new store at Kunduchi Mall | R83: https://www.thecitizen.co.tz/tanzania/business/woolworths-tanzania-opens-new-store-at-kunduchi-mall-5342838 | S83: January 30, 2026
A84: Tanzania | B84: TOL Gases Plc (Tanzania Oxygen Limited) | C84: Pharma | D84: Dar es Salaam, Tanzania | E84: Tanzania's leading industrial/medical gas producer, listed on the Dar es Salaam Stock Exchange, now anchoring a regional medical-oxygen production hub alongside Kenyan producers Hewatele and Synergy. | F84: Broke ground on a $22 million liquid medical-oxygen production facility in Dar es Salaam (part of a Unitaid/CHAI/PATH/MedAccess-backed regional expansion tripling East African oxygen output), March 20, 2025. | G84: 2025 | H84: $22 million | I84: 22 | J84: Hospital/Pharma Plant | K84: =IF(I84="",12,IF(I84>=100,40,IF(I84>=20,32,IF(I84>=5,24,IF(I84>=1,16,8))))) -> 32 | L84: =IF(G84="",5,IF(G84>=2023,25,IF(G84>=2022,20,IF(G84>=2021,14,IF(G84>=2020,8,5))))) -> 25 | M84: =IFERROR(INDEX(Methodology!$B$27:$B$36,MATCH(J84,Methodology!$A$27:$A$36,0)),12) -> 18 | N84: =IF(COUNTIF(Infrastructure!$A:$A,A84)>=4,15,IF(COUNTIF(Infrastructure!$A:$A,A84)>=2,10,IF(COUNTIF(Infrastructure!$A:$A,A84)>=1,5,0))) -> 15 | O84: =K84+L84+M84+N84 -> 90 | P84: =IF(O84>=70,"High",IF(O84>=50,"Medium","Watch")) -> High | Q84: Unitaid and partners expand Africa's first regional oxygen production network into Tanzania | R84: https://www.clintonhealthaccess.org/news/unitaid-and-partners-expand-africas-first-regional-oxygen-production-network-into-tanzania/ | S84: March 20, 2025
A85: Tanzania | B85: Vodacom Tanzania | C85: Technology | D85: Dar es Salaam, Tanzania (parent: Vodacom Group, Johannesburg, South Africa) | E85: Tanzania's largest telecom operator by subscribers, part of the pan-African Vodacom Group, running mobile network, 4G/5G and M-Pesa financial services infrastructure nationwide. | F85: Committed over $100 million to network/IT modernization (thousands of sites upgraded, M-Pesa platform improvements, expanded 4G) as part of its Vision 2030 strategy - one of the largest infrastructure investments in its 25-year history, announced September 16, 2025. | G85: 2030 | H85: $100+ million | I85: 100 | J85: Regional HQ / Network Infrastructure | K85: =IF(I85="",12,IF(I85>=100,40,IF(I85>=20,32,IF(I85>=5,24,IF(I85>=1,16,8))))) -> 40 | L85: =IF(G85="",5,IF(G85>=2023,25,IF(G85>=2022,20,IF(G85>=2021,14,IF(G85>=2020,8,5))))) -> 25 | M85: =IFERROR(INDEX(Methodology!$B$27:$B$36,MATCH(J85,Methodology!$A$27:$A$36,0)),12) -> 12 | N85: =IF(COUNTIF(Infrastructure!$A:$A,A85)>=4,15,IF(COUNTIF(Infrastructure!$A:$A,A85)>=2,10,IF(COUNTIF(Infrastructure!$A:$A,A85)>=1,5,0))) -> 15 | O85: =K85+L85+M85+N85 -> 92 | P85: =IF(O85>=70,"High",IF(O85>=50,"Medium","Watch")) -> High | Q85: Vodacom Tanzania unveils one of its biggest investments in history: $100 million in infrastructure | R85: https://www.thecitizen.co.tz/tanzania/business/vodacom-tanzania-unveils-one-of-its-biggest-investments-in-history-100-million-in-infrastructure-5194710 | S85: September 16, 2025
A86: Tanzania | B86: Wingu Africa | C86: Technology | D86: Dar es Salaam, Tanzania (regional data centre operator) | E86: Operates Tanzania's most-interconnected data centre (13 operators), a Tier 3 carrier-neutral facility in the Mbezi Industrial Area, Dar es Salaam, serving cloud, fintech and AI workloads. | F86: Broke ground on a phase-two expansion adding 80 high-density racks (110 total) and scaling toward 3MW capacity, a $50 million investment, groundbreaking week of March 20, 2025. | G86: 2025 | H86: $50 million | I86: 50 | J86: Data Centre | K86: =IF(I86="",12,IF(I86>=100,40,IF(I86>=20,32,IF(I86>=5,24,IF(I86>=1,16,8))))) -> 32 | L86: =IF(G86="",5,IF(G86>=2023,25,IF(G86>=2022,20,IF(G86>=2021,14,IF(G86>=2020,8,5))))) -> 25 | M86: =IFERROR(INDEX(Methodology!$B$27:$B$36,MATCH(J86,Methodology!$A$27:$A$36,0)),12) -> 20 | N86: =IF(COUNTIF(Infrastructure!$A:$A,A86)>=4,15,IF(COUNTIF(Infrastructure!$A:$A,A86)>=2,10,IF(COUNTIF(Infrastructure!$A:$A,A86)>=1,5,0))) -> 15 | O86: =K86+L86+M86+N86 -> 92 | P86: =IF(O86>=70,"High",IF(O86>=50,"Medium","Watch")) -> High | Q86: Tanzania's digital shift gathers pace with $50 million data centre | R86: https://www.thecitizen.co.tz/tanzania/news/national/tanzania-s-digital-shift-gathers-pace-with-50-million-data-centre-4970620 | S86: March 19, 2025
A87: Tanzania | B87: Arab Contractors & Elsewedy Electric (Egyptian consortium) | C87: Construction | D87: Cairo, Egypt | E87: Egyptian state-linked construction firm (Arab Contractors) and listed electrical engineering group (Elsewedy Electric, EGX: SWDY) jointly delivered Tanzania's largest-ever infrastructure project. | F87: Completed and handed over the 2,115MW Julius Nyerere Hydropower Project (Rufiji District) - a TZS 7.45 trillion (~$3.35B) domestically financed mega-dam - inaugurated August 22, 2026, after construction from 2019. | G87: 2026 | H87: ~$3.35 billion (TZS 7.452 trillion) | I87: 3350 | J87: Construction Project | K87: =IF(I87="",12,IF(I87>=100,40,IF(I87>=20,32,IF(I87>=5,24,IF(I87>=1,16,8))))) -> 40 | L87: =IF(G87="",5,IF(G87>=2023,25,IF(G87>=2022,20,IF(G87>=2021,14,IF(G87>=2020,8,5))))) -> 25 | M87: =IFERROR(INDEX(Methodology!$B$27:$B$36,MATCH(J87,Methodology!$A$27:$A$36,0)),12) -> 16 | N87: =IF(COUNTIF(Infrastructure!$A:$A,A87)>=4,15,IF(COUNTIF(Infrastructure!$A:$A,A87)>=2,10,IF(COUNTIF(Infrastructure!$A:$A,A87)>=1,5,0))) -> 15 | O87: =K87+L87+M87+N87 -> 96 | P87: =IF(O87>=70,"High",IF(O87>=50,"Medium","Watch")) -> High | Q87: Tanzania Electricity Surplus Hits 2,375 MW As Julius Nyerere Hydropower Project Is Officially Launched | R87: https://www.tanzaniainvest.com/energy/jnhpp-julius-nyerere-hydropower-project-launch | S87: August 22, 2026
A88: Tanzania | B88: China Civil Engineering Construction Corporation (CCECC) & China Railway 15th Bureau | C88: Construction | D88: Beijing, China | E88: Chinese state-owned construction majors active across multiple Tanzanian transport infrastructure projects, including bridges and rail works under the Belt and Road framework. | F88: Completed the Magufuli Bridge, a 4.66km dual-carriageway bridge spanning southern Lake Victoria replacing a ferry crossing, officially opened to traffic June 19, 2025, after 5 years of construction. | G88: 2025 | H88: Not disclosed | J88: Construction Project | K88: =IF(I88="",12,IF(I88>=100,40,IF(I88>=20,32,IF(I88>=5,24,IF(I88>=1,16,8))))) -> 12 | L88: =IF(G88="",5,IF(G88>=2023,25,IF(G88>=2022,20,IF(G88>=2021,14,IF(G88>=2020,8,5))))) -> 25 | M88: =IFERROR(INDEX(Methodology!$B$27:$B$36,MATCH(J88,Methodology!$A$27:$A$36,0)),12) -> 16 | N88: =IF(COUNTIF(Infrastructure!$A:$A,A88)>=4,15,IF(COUNTIF(Infrastructure!$A:$A,A88)>=2,10,IF(COUNTIF(Infrastructure!$A:$A,A88)>=1,5,0))) -> 15 | O88: =K88+L88+M88+N88 -> 68 | P88: =IF(O88>=70,"High",IF(O88>=50,"Medium","Watch")) -> Medium | Q88: Magufuli Bridge opens to traffic in Tanzania, amid accelerated China-Africa trade and economic cooperation | R88: https://www.globaltimes.cn/page/202506/1336592.shtml | S88: June 19, 2025
A89: Tanzania | B89: Yapi Merkezi | C89: Construction | D89: Istanbul, Turkey | E89: Turkish rail infrastructure contractor building the majority of Tanzania's Standard Gauge Railway (SGR) across multiple lots, its largest single project portfolio in Africa. | F89: Secured a $2.2 billion Standard Chartered-arranged syndicated loan (part of a $2.33bn package with export credit agencies) to finance SGR Lots 3 and 4 (Makutupora-Tabora-Isaka), signing scheduled April 28, 2026. | G89: 2026 | H89: $2.2 billion (loan facility) | I89: 2200 | J89: Construction Project | K89: =IF(I89="",12,IF(I89>=100,40,IF(I89>=20,32,IF(I89>=5,24,IF(I89>=1,16,8))))) -> 40 | L89: =IF(G89="",5,IF(G89>=2023,25,IF(G89>=2022,20,IF(G89>=2021,14,IF(G89>=2020,8,5))))) -> 25 | M89: =IFERROR(INDEX(Methodology!$B$27:$B$36,MATCH(J89,Methodology!$A$27:$A$36,0)),12) -> 16 | N89: =IF(COUNTIF(Infrastructure!$A:$A,A89)>=4,15,IF(COUNTIF(Infrastructure!$A:$A,A89)>=2,10,IF(COUNTIF(Infrastructure!$A:$A,A89)>=1,5,0))) -> 15 | O89: =K89+L89+M89+N89 -> 96 | P89: =IF(O89>=70,"High",IF(O89>=50,"Medium","Watch")) -> High | Q89: Tanzania SGR Project by Yapi Merkezi Secures $2.2bn Loan from Standard Chartered | R89: https://constructionreviewonline.com/tanzania-sgr-project-by-yapi-merkezi-secures-2-2bn-loan-from-standard-chartered/ | S89: April 2026
A90: Uganda | B90: Itracom Fertilizers Uganda-SMC Ltd | C90: Manufacturing | D90: Bujumbura, Burundi (Itracom Group, regional East African conglomerate) | E90: Itracom already operates a 350,000-tonne fertilizer plant in Burundi and a 1-million-tonne facility in Tanzania; Uganda is its newest East African production base. | F90: Signed agreement with the Ugandan government to build a US$180 million organic fertilizer factory on 133 acres at Kampiringisa, with 250,000 tonnes/year capacity, announced August 21, 2025. | G90: 2025 | H90: US$180 million | I90: 180 | J90: Manufacturing Plant | K90: =IF(I90="",12,IF(I90>=100,40,IF(I90>=20,32,IF(I90>=5,24,IF(I90>=1,16,8))))) -> 40 | L90: =IF(G90="",5,IF(G90>=2023,25,IF(G90>=2022,20,IF(G90>=2021,14,IF(G90>=2020,8,5))))) -> 25 | M90: =IFERROR(INDEX(Methodology!$B$27:$B$36,MATCH(J90,Methodology!$A$27:$A$36,0)),12) -> 20 | N90: =IF(COUNTIF(Infrastructure!$A:$A,A90)>=4,15,IF(COUNTIF(Infrastructure!$A:$A,A90)>=2,10,IF(COUNTIF(Infrastructure!$A:$A,A90)>=1,5,0))) -> 15 | O90: =K90+L90+M90+N90 -> 100 | P90: =IF(O90>=70,"High",IF(O90>=50,"Medium","Watch")) -> High | Q90: Itracom Fertilizer Signs Landmark Agreement to Establish Organic Fertilizer Factory in Uganda worth US$180million | R90: https://www.agriculture.go.ug/2025/08/21/itracom-fertilizer-signs-landmark-agreement-to-establish-organic-fertilizer-factory-in-uganda-worth-us180million/ | S90: August 21, 2025
A91: Uganda | B91: Roofings Limited | C91: Manufacturing | D91: Kampala, Uganda | E91: Uganda's largest indigenous steel manufacturer, with plants in Namanve and other sites producing roofing sheets, pipes and steel products distributed across East Africa. | F91: President Museveni inaugurated a new Phase IV cold-rolling, galvanising and colour-coating steel complex at Namanve, doubling cold-rolled capacity to 300,000 tonnes/year, August 2026. | G91: 2026 | H91: US$120 million | I91: 120 | J91: Manufacturing Plant | K91: =IF(I91="",12,IF(I91>=100,40,IF(I91>=20,32,IF(I91>=5,24,IF(I91>=1,16,8))))) -> 40 | L91: =IF(G91="",5,IF(G91>=2023,25,IF(G91>=2022,20,IF(G91>=2021,14,IF(G91>=2020,8,5))))) -> 25 | M91: =IFERROR(INDEX(Methodology!$B$27:$B$36,MATCH(J91,Methodology!$A$27:$A$36,0)),12) -> 20 | N91: =IF(COUNTIF(Infrastructure!$A:$A,A91)>=4,15,IF(COUNTIF(Infrastructure!$A:$A,A91)>=2,10,IF(COUNTIF(Infrastructure!$A:$A,A91)>=1,5,0))) -> 15 | O91: =K91+L91+M91+N91 -> 100 | P91: =IF(O91>=70,"High",IF(O91>=50,"Medium","Watch")) -> High | Q91: President Museveni inaugurates $120 million Roofings steel complex | R91: https://ugandainvest.go.ug/president-museveni-inaugurates-120-million-roofings-steel-complex/ | S91: August 2026
A92: Uganda | B92: Yaobai International Holding (West China Cement) | C92: Manufacturing | D92: China (Xi'an/Shaanxi-based West China Cement group) | E92: New entrant to Uganda via a purpose-built clinker/cement complex targeting Ugandan, South Sudanese, western Kenyan and eastern DRC markets. | F92: President Museveni commissioned the Yaobai cement clinker factory at Nanduget, Moroto District (Karamoja), with capacity of up to 2 million tonnes of clinker and 3 million tonnes of cement annually, creating 3,500+ jobs, April 24, 2026. | G92: 2026 | H92: Over US$300 million | I92: 300 | J92: Manufacturing Plant | K92: =IF(I92="",12,IF(I92>=100,40,IF(I92>=20,32,IF(I92>=5,24,IF(I92>=1,16,8))))) -> 40 | L92: =IF(G92="",5,IF(G92>=2023,25,IF(G92>=2022,20,IF(G92>=2021,14,IF(G92>=2020,8,5))))) -> 25 | M92: =IFERROR(INDEX(Methodology!$B$27:$B$36,MATCH(J92,Methodology!$A$27:$A$36,0)),12) -> 20 | N92: =IF(COUNTIF(Infrastructure!$A:$A,A92)>=4,15,IF(COUNTIF(Infrastructure!$A:$A,A92)>=2,10,IF(COUNTIF(Infrastructure!$A:$A,A92)>=1,5,0))) -> 15 | O92: =K92+L92+M92+N92 -> 100 | P92: =IF(O92>=70,"High",IF(O92>=50,"Medium","Watch")) -> High | Q92: Uganda Moves to Cut Clinker Importation as President Museveni Commissions Yaobai Factory | R92: https://statehouse.go.ug/uganda-moves-to-cut-clinker-importation-as-president-museveni-commissions-yaobai-factory/ | S92: April 24, 2026
A93: Uganda | B93: Gulftainer Co. Ltd | C93: Logistics | D93: Sharjah, UAE | E93: New entrant to Uganda, proposing to develop and operate the Bukasa Inland Port (Mukono District) in partnership with the Sharjah Chamber of Commerce and Industry. | F93: Met President Museveni to advance plans for developing the Bukasa Inland Port on Lake Victoria for cargo storage, customs clearance and consolidation serving Kenya, South Sudan and Sudan corridors; first-phase finalisation targeted within 6 months, reported December 15, 2025. | G93: 2025 | H93: Not disclosed | J93: Distribution Center | K93: =IF(I93="",12,IF(I93>=100,40,IF(I93>=20,32,IF(I93>=5,24,IF(I93>=1,16,8))))) -> 12 | L93: =IF(G93="",5,IF(G93>=2023,25,IF(G93>=2022,20,IF(G93>=2021,14,IF(G93>=2020,8,5))))) -> 25 | M93: =IFERROR(INDEX(Methodology!$B$27:$B$36,MATCH(J93,Methodology!$A$27:$A$36,0)),12) -> 14 | N93: =IF(COUNTIF(Infrastructure!$A:$A,A93)>=4,15,IF(COUNTIF(Infrastructure!$A:$A,A93)>=2,10,IF(COUNTIF(Infrastructure!$A:$A,A93)>=1,5,0))) -> 15 | O93: =K93+L93+M93+N93 -> 66 | P93: =IF(O93>=70,"High",IF(O93>=50,"Medium","Watch")) -> Medium | Q93: Museveni Supports UAE Investors' Plan for Bukasa Inland Port to Boost Uganda's Trade | R93: https://sunrise.ug/business/202512/museveni-supports-uae-investors-plan-for-bukasa-inland-port-to-boost-uganda-s-trade | S93: December 15, 2025
A94: Uganda | B94: Uganda Airlines (Uganda National Airlines Company) | C94: Logistics | D94: Entebbe, Uganda | E94: Uganda's national carrier, based at Entebbe International Airport, expanding both passenger and cargo operations to position Entebbe as an East/Central Africa aviation and logistics gateway. | F94: Signed a major fleet-expansion commitment with Boeing including 767 and 737 Converted Freighters for cargo, alongside 787-9 and 737 MAX passenger jets - the airline's largest expansion since its 2019 revival; announced June 18, 2026. | G94: 2019 | H94: ~UGX 3.7 trillion (~US$985 million, full fleet order) | I94: 985 | J94: Distribution Center | K94: =IF(I94="",12,IF(I94>=100,40,IF(I94>=20,32,IF(I94>=5,24,IF(I94>=1,16,8))))) -> 40 | L94: =IF(G94="",5,IF(G94>=2023,25,IF(G94>=2022,20,IF(G94>=2021,14,IF(G94>=2020,8,5))))) -> 5 | M94: =IFERROR(INDEX(Methodology!$B$27:$B$36,MATCH(J94,Methodology!$A$27:$A$36,0)),12) -> 14 | N94: =IF(COUNTIF(Infrastructure!$A:$A,A94)>=4,15,IF(COUNTIF(Infrastructure!$A:$A,A94)>=2,10,IF(COUNTIF(Infrastructure!$A:$A,A94)>=1,5,0))) -> 15 | O94: =K94+L94+M94+N94 -> 74 | P94: =IF(O94>=70,"High",IF(O94>=50,"Medium","Watch")) -> High | Q94: Uganda Airlines Strengthens Cargo Ambitions with Addition of Two Boeing Converted Freighters | R94: https://cargonewswire.com/uganda-airlines-strengthens-cargo-ambitions-with-addition-of-two-boeing-converted-freighters/ | S94: June 18, 2026
A95: Uganda | B95: China Town Uganda | C95: Retail | D95: China | E95: Entered the Ugandan market in September 2024 and has grown to four Kampala-area stores within about two years, part of a wider China Town retail chain footprint in Africa. | F95: Opening its fourth Kampala store, in Kabalagala (Makindye Division), after prior outlets at Forest Mall, Akamwesi Mall and Freedom City Mall; reported August 25, 2026. | G95: 2026 | H95: Not disclosed | J95: Retail Store/Mall | K95: =IF(I95="",12,IF(I95>=100,40,IF(I95>=20,32,IF(I95>=5,24,IF(I95>=1,16,8))))) -> 12 | L95: =IF(G95="",5,IF(G95>=2023,25,IF(G95>=2022,20,IF(G95>=2021,14,IF(G95>=2020,8,5))))) -> 25 | M95: =IFERROR(INDEX(Methodology!$B$27:$B$36,MATCH(J95,Methodology!$A$27:$A$36,0)),12) -> 8 | N95: =IF(COUNTIF(Infrastructure!$A:$A,A95)>=4,15,IF(COUNTIF(Infrastructure!$A:$A,A95)>=2,10,IF(COUNTIF(Infrastructure!$A:$A,A95)>=1,5,0))) -> 15 | O95: =K95+L95+M95+N95 -> 60 | P95: =IF(O95>=70,"High",IF(O95>=50,"Medium","Watch")) -> Medium | Q95: China Town Uganda to Open Fourth Store in Kabalagala | R95: https://www.pulse.ug/story/china-town-uganda-kabalagala-new-store-kampala-2026082506490716942 | S95: August 25, 2026
A96: Uganda | B96: Vivo Energy Uganda (Shell-branded fuels/retail) | C96: Retail | D96: London, UK / Amsterdam (Vitol-Helios joint venture) | E96: Operates the Shell-branded fuel retail network across Uganda alongside operations in over a dozen African markets. | F96: Commissioned 10 new Shell service stations (incl. Kitetika, Kitemu, Masanafu), bringing its Uganda network to 191 sites, and unveiled Shell's refreshed brand identity with MTN-partnered CCTV across all stations, November 2024. | G96: 2024 | H96: Not disclosed | J96: Retail Store/Mall | K96: =IF(I96="",12,IF(I96>=100,40,IF(I96>=20,32,IF(I96>=5,24,IF(I96>=1,16,8))))) -> 12 | L96: =IF(G96="",5,IF(G96>=2023,25,IF(G96>=2022,20,IF(G96>=2021,14,IF(G96>=2020,8,5))))) -> 25 | M96: =IFERROR(INDEX(Methodology!$B$27:$B$36,MATCH(J96,Methodology!$A$27:$A$36,0)),12) -> 8 | N96: =IF(COUNTIF(Infrastructure!$A:$A,A96)>=4,15,IF(COUNTIF(Infrastructure!$A:$A,A96)>=2,10,IF(COUNTIF(Infrastructure!$A:$A,A96)>=1,5,0))) -> 15 | O96: =K96+L96+M96+N96 -> 60 | P96: =IF(O96>=70,"High",IF(O96>=50,"Medium","Watch")) -> Medium | Q96: Vivo Energy Expands Network With 10 New Service Stations, Unveils The New Look For Shell In Uganda | R96: https://businessfocus.co.ug/vivo-energy-expands-network-with-10-new-service-stations-unveils-the-new-look-for-shell-in-uganda/ | S96: November 2024
A97: Uganda | B97: Quality Chemicals Limited (Cipla Quality Chemicals Industries Ltd) | C97: Pharma | D97: Kampala, Uganda (joint venture with Cipla Ltd, Mumbai, India) | E97: Uganda's largest pharmaceutical manufacturer, producing 25 registered antiretroviral, antimalarial and other essential medicines from two existing facilities, supplying the wider East African region. | F97: Broke ground on a new manufacturing plant at Luzira Industrial and Business Park to add TB, sickle-cell and injectable production lines, reported July 16, 2026, on the company's 20th anniversary. | G97: 2026 | H97: Not disclosed | J97: Hospital/Pharma Plant | K97: =IF(I97="",12,IF(I97>=100,40,IF(I97>=20,32,IF(I97>=5,24,IF(I97>=1,16,8))))) -> 12 | L97: =IF(G97="",5,IF(G97>=2023,25,IF(G97>=2022,20,IF(G97>=2021,14,IF(G97>=2020,8,5))))) -> 25 | M97: =IFERROR(INDEX(Methodology!$B$27:$B$36,MATCH(J97,Methodology!$A$27:$A$36,0)),12) -> 18 | N97: =IF(COUNTIF(Infrastructure!$A:$A,A97)>=4,15,IF(COUNTIF(Infrastructure!$A:$A,A97)>=2,10,IF(COUNTIF(Infrastructure!$A:$A,A97)>=1,5,0))) -> 15 | O97: =K97+L97+M97+N97 -> 70 | P97: =IF(O97>=70,"High",IF(O97>=50,"Medium","Watch")) -> High | Q97: Ugandan pharma company Quality Chemicals is expanding its manufacturing capacity | R97: https://ugandainvest.go.ug/ugandan-pharma-company-quality-chemicals-is-expanding-its-manufacturing-capacity/ | S97: July 16, 2026
A98: Uganda | B98: MTN Uganda | C98: Technology | D98: Johannesburg, South Africa (MTN Group) | E98: Uganda's largest mobile network operator, part of the pan-African MTN Group footprint covering the wider East African region. | F98: Launched Uganda's first 5G network and industrial 5G use case, backed by a UGX 95.4 billion (~US$25.4 million) investment via its five-year Huawei modernisation partnership; live from early-to-May 2023. | G98: 2023 | H98: UGX 95.4 billion (~US$25.4 million) | I98: 25.4 | J98: Regional HQ / Network Infrastructure | K98: =IF(I98="",12,IF(I98>=100,40,IF(I98>=20,32,IF(I98>=5,24,IF(I98>=1,16,8))))) -> 32 | L98: =IF(G98="",5,IF(G98>=2023,25,IF(G98>=2022,20,IF(G98>=2021,14,IF(G98>=2020,8,5))))) -> 25 | M98: =IFERROR(INDEX(Methodology!$B$27:$B$36,MATCH(J98,Methodology!$A$27:$A$36,0)),12) -> 12 | N98: =IF(COUNTIF(Infrastructure!$A:$A,A98)>=4,15,IF(COUNTIF(Infrastructure!$A:$A,A98)>=2,10,IF(COUNTIF(Infrastructure!$A:$A,A98)>=1,5,0))) -> 15 | O98: =K98+L98+M98+N98 -> 84 | P98: =IF(O98>=70,"High",IF(O98>=50,"Medium","Watch")) -> High | Q98: MTN Uganda launches first 5G network, pioneering high-speed connectivity in the country | R98: https://www.techloy.com/mtn-launches-first-5g-network-in-uganda/ | S98: 2023
A99: Uganda | B99: Raxio Group (Raxio Uganda) | C99: Technology | D99: Kampala, Uganda (pan-African group backed by Roha Group and Meridiam) | E99: Operates Uganda's first Tier III-certified, carrier-neutral data centre at Namanve/KIBP (opened 2021), alongside facilities in Ethiopia, Mozambique, DRC, Cote d'Ivoire and Angola. | F99: Raised total committed capital to US$380 million (incl. $100M from IFC) to fund continued African data-centre expansion, reporting 6x power-capacity contracting growth in H1 2026 vs H1 2025; announced July 13, 2026. | G99: 2026 | H99: US$380 million (group-wide committed capital) | I99: 380 | J99: Data Centre | K99: =IF(I99="",12,IF(I99>=100,40,IF(I99>=20,32,IF(I99>=5,24,IF(I99>=1,16,8))))) -> 40 | L99: =IF(G99="",5,IF(G99>=2023,25,IF(G99>=2022,20,IF(G99>=2021,14,IF(G99>=2020,8,5))))) -> 25 | M99: =IFERROR(INDEX(Methodology!$B$27:$B$36,MATCH(J99,Methodology!$A$27:$A$36,0)),12) -> 20 | N99: =IF(COUNTIF(Infrastructure!$A:$A,A99)>=4,15,IF(COUNTIF(Infrastructure!$A:$A,A99)>=2,10,IF(COUNTIF(Infrastructure!$A:$A,A99)>=1,5,0))) -> 15 | O99: =K99+L99+M99+N99 -> 100 | P99: =IF(O99>=70,"High",IF(O99>=50,"Medium","Watch")) -> High | Q99: Raxio Tops $380 Million in Committed Capital as African Data Center Demand Surges | R99: https://convergedigest.com/raxio-tops-380-million-in-committed-capital-as-african-data-center-demand-surges/ | S99: July 13, 2026
A100: Uganda | B100: China Communications Construction Company (CCCC) | C100: Construction | D100: Beijing, China | E100: Belt and Road-financed contractor executing Uganda's flagship Entebbe International Airport modernisation, alongside other Ugandan road and infrastructure contracts. | F100: Completed a new cargo terminal (doubling capacity to 100,000 tonnes/year) at Entebbe International Airport as part of a broader US$200 million airport modernisation programme (passenger terminal/runway work continuing into 2024). | G100: 2024 | H100: US$200 million (full modernisation programme) | I100: 200 | J100: Construction Project | K100: =IF(I100="",12,IF(I100>=100,40,IF(I100>=20,32,IF(I100>=5,24,IF(I100>=1,16,8))))) -> 40 | L100: =IF(G100="",5,IF(G100>=2023,25,IF(G100>=2022,20,IF(G100>=2021,14,IF(G100>=2020,8,5))))) -> 25 | M100: =IFERROR(INDEX(Methodology!$B$27:$B$36,MATCH(J100,Methodology!$A$27:$A$36,0)),12) -> 16 | N100: =IF(COUNTIF(Infrastructure!$A:$A,A100)>=4,15,IF(COUNTIF(Infrastructure!$A:$A,A100)>=2,10,IF(COUNTIF(Infrastructure!$A:$A,A100)>=1,5,0))) -> 15 | O100: =K100+L100+M100+N100 -> 96 | P100: =IF(O100>=70,"High",IF(O100>=50,"Medium","Watch")) -> High | Q100: China Communications delivers trade-boosting cargo terminal in Uganda | R100: https://www.globalconstructionreview.com/china-communications-delivers-trade-boosting-cargo-terminal-in-uganda/ | S100: 2022 (programme ongoing through 2024)
...

Sheet Infrastructure
A1: Project Profile | F1: Status | H1: Source
A2: Country | B2: Project Name | C2: Type | D2: Location | E2: Operator / Developer | F2: Status | G2: Scale / Capacity | H2: Source Title | I2: Source URL | J2: Source Date
A3: Burundi | B3: Port of Bujumbura Modernization (Lake Tanganyika Transport Corridor Development Project, Phase I) | C3: Port | D3: Bujumbura, Burundi | E3: Government of Burundi, financed by African Development Bank Group and European Union | F3: Construction commenced August 17, 2023, with a 24-month completion timeline; project rehabilitates port equipment, access roads and staff capacity to establish Bujumbura as a Lake Tanganyika regional trade hub. | G3: €79 million total (€23.4M AfDB, €29M EU, €2M Government of Burundi) | H3: Burundi: the Port of Bujumbura will soon be renovated and modernized thanks to funding from the African Development Bank Group and the European Union | I3: https://www.afdb.org/en/news-and-events/press-releases/burundi-port-bujumbura-will-soon-be-renovated-and-modernized-thanks-funding-african-development-bank-group-and-european-union-63941 | J3: 2023-08-25
A4: Comoros | B4: Maritime Corridor and Regional Trade Facilitation Project | C4: Port | D4: Moroni, Mutsamudu and Mohéli, Comoros | E4: Government of the Union of the Comoros, financed by the African Development Bank Group and co-financiers | F4: Officially launched October 27, 2025, in Moroni (press release October 29, 2025); aims to modernize port infrastructure across the islands and position Comoros as an Africa-Asia logistics hub. | G4: $137 million total ($135M African Development Fund grant + $2M Transition Support Fund), with over $110M additional co-financing from the World Bank, Islamic Development Bank, AFD, EU and EIB | H4: Union of the Comoros: Launch of the maritime corridor project supported by the African Development Bank Group to the tune of $137 million | I4: https://www.afdb.org/en/news-and-events/press-releases/union-comoros-launch-maritime-corridor-project-supported-african-development-bank-group-tune-137-million-88185 | J4: 2025-10-29
A5: Comoros | B5: Port of Moroni Deep-Water Port Redevelopment | C5: Port | D5: Moroni, Grande Comore, Comoros | E5: China Road and Bridge Corporation (contracted); Government of Comoros | F5: Commercial contract signed March 2018 for dredging and redevelopment; as of the most recent available reporting (June 2022), construction work had reportedly not yet commenced. | G5: $165 million (contracted) | H5: Will Comoros Be China's Next "Djibouti" In Indian Ocean Region? | I5: https://channel16.dryadglobal.com/will-comoros-be-chinas-next-djibouti-in-indian-ocean-region | J5: 2022-06-10
A6: Djibouti | B6: Djibouti International Free Trade Zone (DIFTZ) | C6: SEZ | D6: Djibouti City, Djibouti | E6: Djibouti Ports & Free Zones Authority / Great Horn Investment Holding, with China Merchants Group | F6: Zone established 2015 (43.5 sq km) and operational since 2018; major expansion phase agreed January 8, 2021. | G6: 43.5 sq km; $3 billion expansion agreement (2021); $513 million initial phase (2020) | H6: China Merchants signs deal for $3bn expansion of Djibouti City port | I6: https://www.globalconstructionreview.com/china-merchants-signs-deal-3bn-expansion-djibouti/ | J6: 2021-01-08
A7: Djibouti | B7: Doraleh Port | C7: Port | D7: Doraleh, Djibouti | E7: Djibouti Ports & Free Zones Authority, with Egyptian state-linked port-development firms | F7: Operational since prior expansions; Egypt and Djibouti finalized a deal (December 31, 2025) to expand port capacity, add warship berths, a solar power station and a logistics centre. | G7: Financial figures not disclosed; scope includes capacity expansion, solar power station and new logistics centre | H7: Egypt finalises deal to develop Djibouti's port in bid to pressure Ethiopia over Nile dam | I7: https://www.thenationalnews.com/news/mena/2025/12/31/egypt-finalises-deal-to-develop-djiboutis-port-in-bid-to-pressure-ethiopia-over-nile-dam/ | J7: 2025-12-31
A8: Djibouti | B8: PAIX Djibouti Data Centre | C8: Data Centre | D8: Djibouti City, Djibouti | E8: PAIX Data Centres, with the Djibouti Sovereign Wealth Fund | F8: Under development; joint venture announced May 16, 2024, first phase expected 2026. | G8: $50 million; ~50,000 sq ft net usable space; up to 5MW critical power | H8: PAIX to Construct Carrier-neutral Data Center in Djibouti | I8: https://www.submarinenetworks.com/en/stations/africa/djibouti/paix-to-construct-carrier-neutral-data-center-in-djibouti | J8: 2024-05-16
A9: DRC Congo | B9: Maluku Special Economic Zone (ZES Maluku) | C9: SEZ | D9: Maluku, ~70km northeast of Kinshasa, DRC | E9: DRC government / Maluku SEZ authority | F9: Operational (first industrial production since 2023); new river-dock export infrastructure inaugurated 13 March 2025. | G9: New river dock enabling export logistics; zone hosts beverage, agro-processing, timber and ceramics manufacturers | H9: DRC: Maluku Special Economic Zone Gets River Dock to Ease Exports | I9: https://www.ecofinagency.com/news-infrastructures/2003-53971-drc-maluku-special-economic-zone-gets-river-dock-to-ease-exports | J9: 2025-03
A10: DRC Congo | B10: China-Congo Industrial City | C10: Industrial Park | D10: Maluku, DRC | E10: Sino-Congo Special Zone (SCSZ) consortium, with the DRC government | F10: Agreement signed / early development stage. | G10: US$12 billion mobilized for the first phase of construction | H10: DRC: $12 billion investment to build the China-Congo Industrial City in Maluku | I10: https://www.financialafrik.com/en/2025/10/27/drc-12-billion-investment-to-build-the-china-congo-industrial-city-in-maluku/ | J10: 2025-10-23
A11: Eritrea | B11: Port of Assab modernization/investment prospect | C11: Port | D11: Assab, Eritrea | E11: Government of Eritrea; prospective investor Saudi Arabia | F11: Planned / under discussion. | G11: World Bank estimates ~US$200 million needed for modernization | H11: Saudi Arabia's Strategic Investments in Eritrea's Port of Assab Amid Rising Regional Tensions | I11: https://www.faf.ae/home/2025/3/10/saudi-arabias-strategic-investments-in-eritreas-port-of-assab-amid-rising-regional-tensions | J11: 2025-03-10
A12: Ethiopia | B12: Dire Dawa Free Trade Zone | C12: SEZ | D12: Dire Dawa (~445km east of Addis Ababa) | E12: Industrial Parks Development Corporation (IPDC); industrial park built by CCECC | F12: Operational | G12: Ethiopia's first free trade zone; integrated with a dry port, rail station, and international airport | H12: Ethiopia's first free trade zone fully operational | I12: https://english.news.cn/africa/20241113/35d9f48af19345b9958690e377f61230/c.html | J12: November 13, 2024
A13: Ethiopia | B13: Gada Special Economic Zone (Lume Free Trade Zone) | C13: SEZ | D13: Lume, Oromia Region (~65km SE of Addis Ababa) | E13: China Civil Engineering Construction Corporation (CCECC) / China Railway Construction Corporation, with the Ethiopian government | F13: Under Construction | G13: Ethiopia's second free trade zone; planned focus on coffee processing, bamboo/timber processing, machinery manufacturing, and bio-pharmaceuticals (area not disclosed) | H13: Ethiopia launches construction of Chinese-contracted economic zone | I13: https://eng.yidaiyilu.gov.cn/p/0M376K98.html | J13: May 10, 2024
... A68: Zimbabwe | B68: Dandemutande Tier III Data Centre | C68: Data Centre | D68: Zimbabwe | E68: Dandemutande | F68: Under development / planned. | G68: $15 million investment; expected completion by June 2026 | H68: Zimbabwean IT provider Dandemutande plans $15m data center | I68: https://www.datacenterdynamics.com/en/news/zimbabwean-it-provider-dandemutande-plans-15m-data-center/ | J68: 2025-02-26
