Workbook

Sheet Overview
A1: East African Countries — Socio-Economic Indicators
A3: Restructured from the original UIS Data Browser export you shared, using the WITS Kenya product workbook's flat-table layout as the structural guide.
A5: How this workbook is organized
A6: This file replaces the original page-by-page (A, B, C ...) layout with a single structured dataset, modeled on the flat, one-row-per-record layout used in the WITS Kenya product-trade workbook you shared: identifier columns (Country, Year) on the left, every measure as its own column to the right, grouped and color-coded by theme instead of split into separate lettered pages.
A10: Sheet | B10: Contents
A11: Data | B11: One row per country/year, with every indicator as its own column, grouped and color-banded by theme.
A12: Latest Snapshot | B12: One row per country with each indicator's most recently available value, pulled live from the Data sheet with formulas.
A14: Theme groupings
A15: Theme | B15: Indicators included
A16: Economic Output & Growth | B16: GDP (current US$); GDP (current LCU); GDP growth (annual %); GDP, PPP (current international $); GDP at market prices (constant 2010 US$); GDP (constant LCU); GDP, PPP (constant 2011 international $); GDP deflator (base year varies by country)
A17: Income & Living Standards (Per Capita) | B17: GDP per capita (current US$); GDP per capita (current LCU); GDP per capita, PPP (current international $); GDP per capita, PPP (constant 2011 international $); GNI per capita, Atlas method (current US$); GNI per capita, PPP (current international $); GNI per capita (current LCU); GNI (current LCU)
A18: Poverty | B18: Poverty headcount ratio at $3.20 a day (PPP) (% of population)
A19: Government Finance & Debt | B19: Total debt service (% of GNI); General government total expenditure (current LCU)
A20: Prices, Exchange Rates & PPP Conversion | B20: PPP conversion factor, GDP (LCU per international $); DEC alternative conversion factor (LCU per US$); Official exchange rate (LCU per US$, period average); Price level ratio of PPP conversion factor (GDP) to market exchange rate; PPP conversion factor, private consumption (LCU per international $)
A22: Data notes (carried over from the original source files)
A23: • Source: UIS Data Browser (databrowser.uis.unesco.org). Coverage varies by indicator; some countries (notably Eritrea and South Sudan) have little or no data for most indicators.
A24: • Most GDP/GNI-based indicators (Economic Output & Growth and Income & Living Standards groups) have data for 17 of 19 countries — Eritrea and South Sudan are blank throughout.
A25: • Total debt service has no data for Eritrea, Seychelles or South Sudan (16 of 19 countries).
A26: • Poverty headcount ratio at $3.20/day has data for only 8 of 19 countries, and each of those for only one or a few years — treat as spot estimates, not a time series.
A27: • Values shown in a country's own local currency unit ("current LCU" / "constant LCU" / LCU-denominated columns) are NOT comparable across countries — only across years within the same country.
A28: • Zimbabwe underwent extreme currency instability over this period; its LCU-denominated values and GDP deflator (e.g. deflator index rising from 704.95 in 2020 to 56,369.06 in 2023) reflect hyperinflation, not real economic growth.
A29: • Ethiopia's 2023 figures are missing from the source view for several indicators, including GDP (current US$), GDP per capita (current US$) and GNI per capita, Atlas method.
A30: • Official exchange rate has no data for Somalia (18 of 19 countries).
A31: • The four Prices, Exchange Rates & PPP Conversion indicators are the only ones with at least partial data for all 19 countries; Eritrea and South Sudan's coverage there is limited to specific years only.
A32: • All blank cells reflect no data available in the original source, not a value of zero.

Sheet Data
A1: Country | B1: Year | C1: Economic Output & Growth | K1: Income & Living Standards (Per Capita) | S1: Poverty | T1: Government Finance & Debt | V1: Prices, Exchange Rates & PPP Conversion
C2: GDP (current US$) | D2: GDP (current LCU) | E2: GDP growth (annual %) | F2: GDP, PPP (current international $) | G2: GDP at market prices (constant 2010 US$) | H2: GDP (constant LCU) | I2: GDP, PPP (constant 2011 international $) | J2: GDP deflator (base year varies by country) | K2: GDP per capita (current US$) | L2: GDP per capita (current LCU) | M2: GDP per capita, PPP (current international $) | N2: GDP per capita, PPP (constant 2011 international $) | O2: GNI per capita, Atlas method (current US$) | P2: GNI per capita, PPP (current international $) | Q2: GNI per capita (current LCU) | R2: GNI (current LCU) | S2: Poverty headcount ratio at $3.20 a day (PPP) (% of population) | T2: Total debt service (% of GNI) | U2: General government total expenditure (current LCU) | V2: PPP conversion factor, GDP (LCU per international $) | W2: DEC alternative conversion factor (LCU per US$) | X2: Official exchange rate (LCU per US$, period average) | Y2: Price level ratio of PPP conversion factor (GDP) to market exchange rate | Z2: PPP conversion factor, private consumption (LCU per international $)
A3: Burundi | B3: 2020 | C3: 2649680261 | D3: 5910570000000 | E3: 0.33 | F3: 9923498550 | G3: 3218331065 | H3: 1785540000000 | I3: 10521601909 | J3: 331.02 | K3: 210.01 | L3: 468459.71 | M3: 786.52 | N3: 833.92 | O3: 210 | P3: 790 | Q3: 471031.21 | R3: 5943020000000 | S3: 87.2 | T3: 1.38 | U3: 1725699000000 | V3: 595.61 | W3: 2230.67 | X3: 1915.05 | Y3: 0.27 | Z3: 633.88
A4: Burundi | B4: 2021 | C4: 2775798697 | D4: 6612790000000 | E4: 3.1 | F4: 10847771569 | G4: 3318099328 | H4: 1840890000000 | I4: 10847771569 | J4: 359.22 | K4: 214.09 | L4: 510030.65 | M4: 836.67 | N4: 836.67 | O4: 220 | P4: 840 | Q4: 511522 | R4: 6632130000000 | T4: 1.07 | U4: 1880152000000 | V4: 609.6 | W4: 2382.3 | X4: 1975.95 | Y4: 0.26 | Z4: 657.41
A5: Burundi | B5: 2022 | C5: 3338722828 | D5: 7969720000000 | E5: 1.85 | F5: 11836036574 | G5: 3379450966 | H5: 1874930000000 | I5: 11048346804 | J5: 425.07 | K5: 250.63 | L5: 598277.77 | M5: 888.52 | N5: 829.39 | O5: 230 | P5: 890 | Q5: 600784.08 | R5: 8003100000000 | T5: 0.99 | U5: 2673964000000 | V5: 673.34 | W5: 2387.06 | X5: 2034.31 | Y5: 0.28 | Z5: 723.14
A6: Burundi | B6: 2023 | C6: 2629391600 | D6: 9071960000000 | E6: 2.67 | F6: 12588790451 | G6: 3469531570 | H6: 1924910000000 | I6: 11342844864 | J6: 471.29 | K6: 192.07 | L6: 662696.88 | M6: 919.6 | N6: 828.58 | O6: 220 | P6: 930 | Q6: 667377.91 | R6: 9136040000000 | T6: 1.68 | U6: 3101347000000 | V6: 720.64 | W6: 3450.21 | X6: 2574.05 | Y6: 0.21 | Z6: 881.67
A7: Comoros | B7: 2020 | C7: 1225039196 | D7: 527650000000 | E7: 4.01 | F7: 2616330804 | G7: 1175888998 | H7: 524140000000 | I7: 2747039030 | J7: 100.67 | K7: 1527.17 | L7: 657784.02 | M7: 3261.59 | N7: 3424.54 | O7: 1580 | P7: 3280 | Q7: 660956.9 | R7: 530195000000 | T7: 0.88 | U7: 98517000000 | V7: 201.68 | W7: 430.72 | X7: 430.72 | Y7: 0.47 | Z7: 233.77
A8: Comoros | B8: 2021 | C8: 1299039312 | D8: 540343000000 | E8: 2.73 | F8: 2821917778 | G8: 1207941362 | H8: 538427000000 | I8: 2821917778 | J8: 100.36 | K8: 1587.73 | L8: 660425.53 | M8: 3449.04 | N8: 3449.04 | O8: 1620 | P8: 3470 | Q8: 663626.35 | R8: 542962000000 | T8: 0.27 | U8: 105583000000 | V8: 191.48 | W8: 415.96 | X8: 415.96 | Y8: 0.46 | Z8: 228.05
A9: Comoros | B9: 2022 | C9: 1279542248 | D9: 597782000000 | E9: 2.82 | F9: 3108308932 | G9: 1241985921 | H9: 553602000000 | I9: 2901450569 | J9: 107.98 | K9: 1533.88 | L9: 716603.45 | M9: 3726.15 | N9: 3478.17 | O9: 1640 | P9: 3750 | Q9: 720305.04 | R9: 600870000000 | T9: 0.38 | U9: 105309000000 | V9: 192.32 | W9: 467.18 | X9: 467.18 | Y9: 0.41
A10: Comoros | B10: 2023 | C10: 1430523436 | D10: 650876000000 | E10: 3.06 | F10: 3318845024 | G10: 1280048597 | H10: 570568000000 | I10: 2990370233 | J10: 114.08 | K10: 1682.2 | L10: 765387.56 | M10: 3902.75 | N10: 3516.48 | O10: 1660 | P10: 3920 | Q10: 769337.84 | R10: 654235000000 | T10: 1.31 | U10: 107878000000 | V10: 196.12 | W10: 454.99 | X10: 454.99 | Y10: 0.43
A11: Democratic Republic of the Congo | B11: 2020 | C11: 48716961860 | D11: 90181000000000 | E11: 1.74 | F11: 109045000000 | G11: 45259708654 | H11: 128803000000000 | I11: 122640000000 | J11: 700.15 | K11: 507.52 | L11: 939483.8 | M11: 1136.01 | N11: 1277.63 | O11: 520 | P11: 1110 | Q11: 915031.97 | R11: 87833900000000 | S11: 92.5 | T11: 0.57 | U11: 11656620000000 | V11: 827 | W11: 1851.12 | X11: 1851.12 | Y11: 0.45 | Z11: 885.97
A12: Democratic Republic of the Congo | B12: 2021 | C12: 55328482784 | D12: 110115000000000 | E12: 6.2 | F12: 130244000000 | G12: 48065880295 | H12: 137689000000000 | I12: 130244000000 | J12: 805 | K12: 558.03 | L12: 1110599.4 | M12: 1313.62 | N12: 1313.62 | O12: 540 | P12: 1270 | Q12: 1070654.5 | R12: 106154000000000 | T12: 0.6 | U12: 15892293000000 | V12: 845.45 | W12: 1990.2 | X12: 1989.39 | Y12: 0.42 | Z12: 928.6
A13: Democratic Republic of the Congo | B13: 2022 | C13: 65801547756 | D13: 132064000000000 | E13: 8.92 | F13: 151982000000 | G13: 52355494716 | H13: 148997000000000 | I13: 141867000000 | J13: 886.35 | K13: 642.61 | L13: 1289722.8 | M13: 1484.24 | N13: 1385.46 | O13: 590 | P13: 1400 | Q13: 1220786.3 | R13: 125005000000000 | T13: 0.62 | U13: 24274559000000 | V13: 868.94 | W13: 2007 | X13: 2006.71 | Y13: 0.43
A14: Democratic Republic of the Congo | B14: 2023 | C14: 67006756666 | D14: 163777000000000 | E14: 8.61 | F14: 171006000000 | G14: 56862826231 | H14: 161824000000000 | I14: 154081000000 | J14: 1012.07 | K14: 633.4 | L14: 1548140.6 | M14: 1616.47 | N14: 1456.48 | O14: 640 | P14: 1570 | Q14: 1499737 | R14: 158657000000000 | T14: 0.76 | U14: 27144749000000 | V14: 957.73 | W14: 2444.19 | X14: 2340.04 | Y14: 0.39
A15: Djibouti | B15: 2020 | C15: 3144136197 | D15: 558779000000 | E15: 1.2 | F15: 6108376123 | G15: 3065135713 | H15: 528400000000 | I15: 6400671631 | J15: 105.75 | K15: 2844.89 | L15: 505596.36 | M15: 5527 | N15: 5791.48 | O15: 2780 | P15: 5350 | Q15: 489745.84 | R15: 541261000000 | T15: 2.33 | U15: 144139000000 | V15: 91.48 | W15: 177.72 | X15: 177.72 | Y15: 0.51 | Z15: 100.04
A16: Djibouti | B16: 2021 | C16: 3392796953 | D16: 602971000000 | E16: 4.41 | F16: 6682759258 | G16: 3200221046 | H16: 551687000000 | I16: 6682759258 | J16: 109.3 | K16: 3025.91 | L16: 537767.98 | M16: 5960.11 | N16: 5960.11 | O16: 2990 | P16: 5850 | Q16: 528203.63 | R16: 592247000000 | T16: 1.84 | U16: 139436000000 | V16: 90.23 | W16: 177.72 | X16: 177.72 | Y16: 0.51 | Z16: 96.93
A17: Djibouti | B17: 2022 | C17: 3562814909 | D17: 633187000000 | E17: 5.17 | F17: 7529088292 | G17: 3365561652 | H17: 580190000000 | I17: 7028026489 | J17: 109.13 | K17: 3133.26 | L17: 556845.71 | M17: 6621.33 | N17: 6180.68 | O17: 3310 | P17: 6750 | Q17: 567437.16 | R17: 645231000000 | T17: 2.14 | U17: 132736000000 | V17: 84.1 | W17: 177.72 | X17: 177.72 | Y17: 0.47 | Z17: 94.4
A18: Djibouti | B18: 2023 | C18: 3917150481 | D18: 696160000000 | E18: 7.37 | F18: 8375036989 | G18: 3613673263 | H18: 622962000000 | I18: 7546137626 | J18: 111.75 | K18: 3397.52 | L18: 603810.68 | M18: 7264.04 | N18: 6545.1 | O18: 3510 | P18: 7460 | Q18: 619685.39 | R18: 714463000000 | T18: 2.52 | U18: 149757000000 | V18: 83.12 | W18: 177.72 | X18: 177.72 | Y18: 0.47 | Z18: 92.02
A19: Eritrea | B19: 2020 | V19: 5.01 | W19: 15.07 | X19: 15.07 | Y19: 0.33 | Z19: 4.99
A20: Eritrea | B20: 2021 | V20: 4.94 | W20: 15.07 | X20: 15.07 | Y20: 0.33 | Z20: 5.2
A21: Eritrea | B21: 2022 | W21: 15.07 | X21: 15.07
A22: Eritrea | B22: 2023 | W22: 15.07 | X22: 15.07
A23: Ethiopia | B23: 2020 | C23: 107658000000 | D23: 3374750000000 | E23: 6.06 | F23: 286210000000 | G23: 95071775812 | H23: 21091800000000 | I23: 299262000000 | J23: 160 | K23: 905.31 | L23: 28378.85 | M23: 2406.79 | N23: 2516.55 | O23: 860 | P23: 2390 | Q23: 28217.37 | R23: 33555400000000 | T23: 1.89 | U23: 488243000000 | V23: 11.79 | W23: 31.35 | X23: 34.93 | Y23: 0.38 | Z23: 11.29
A24: Ethiopia | B24: 2021 | C24: 111262000000 | D24: 4341020000000 | E24: 5.64 | F24: 316145000000 | G24: 100435000000 | H24: 22281700000000 | I24: 316145000000 | J24: 194.82 | K24: 910.95 | L24: 35541.79 | M24: 2588.41 | N24: 2588.41 | O24: 930 | P24: 2580 | Q24: 35358.55 | R24: 43186400000000 | S24: 63.7 | T24: 1.82 | U24: 599007000000 | V24: 13.73 | W24: 39.02 | X24: 43.73 | Y24: 0.35 | Z24: 13.44
A25: Ethiopia | B25: 2022 | C25: 126773000000 | D25: 6157020000000 | E25: 5.32 | F25: 356709000000 | G25: 105780000000 | H25: 23467500000000 | I25: 332970000000 | J25: 262.36 | K25: 1011.07 | L25: 49105.16 | M25: 2844.92 | N25: 2655.59 | O25: 1010 | P25: 2830 | Q25: 48882.95 | R25: 61291500000000 | T25: 1.59 | U25: 781789000000 | V25: 17.26 | W25: 48.57 | X25: 51.76 | Y25: 0.36 | Z25: 16.66
A26: Ethiopia | B26: 2023 | D26: 8723120000000 | E26: 6.59 | F26: 393913000000 | G26: 112756000000 | H26: 25015000000000 | I26: 354926000000 | J26: 348.72 | L26: 67783.06 | M26: 3060.91 | N26: 2757.96 | P26: 3050 | Q26: 67597.16 | R26: 86991900000000 | U26: 943881000000 | V26: 22.14 | X26: 54.6 | Z26: 20.83
A27: Kenya | B27: 2020 | C27: 100658000000 | D27: 10715100000000 | E27: -0.27 | F27: 250255000000 | G27: 84035138347 | H27: 87330600000000 | I27: 264084000000 | J27: 122.7 | K27: 1927.66 | L27: 205201.4 | M27: 4792.57 | N27: 5057.4 | O27: 1910 | P27: 4760 | Q27: 203823.71 | R27: 10643100000000 | S27: 65.6 | T27: 2.83 | U27: 2657454000000 | V27: 42.82 | W27: 106.45 | X27: 106.45 | Y27: 0.4 | Z27: 43.22
A28: Kenya | B28: 2021 | C28: 109704000000 | D28: 12027700000000 | E28: 7.59 | F28: 284129000000 | G28: 90413816677 | H28: 93959400000000 | I28: 284129000000 | J28: 128.01 | K28: 2061.36 | L28: 226002.45 | M28: 5338.85 | N28: 5338.85 | O28: 2070 | P28: 5260 | Q28: 222852.5 | R28: 11860000000000 | S28: 67.9 | T28: 2.26 | U28: 2888491000000 | V28: 42.33 | W28: 109.64 | X28: 109.64 | Y28: 0.39 | Z28: 42.43
A29: Kenya | B29: 2022 | C29: 114449000000 | D29: 13489600000000 | E29: 4.86 | F29: 319179000000 | G29: 94807911028 | H29: 98525800000000 | I29: 297938000000 | J29: 136.91 | K29: 2109.56 | L29: 248645.72 | M29: 5883.22 | N29: 5491.69 | O29: 2170 | P29: 5790 | Q29: 244822.59 | R29: 13282200000000 | S29: 67 | T29: 2.96 | U29: 3124259000000 | V29: 42.26 | W29: 117.87 | X29: 117.87 | Y29: 0.36 | Z29: 42.29
A30: Kenya | B30: 2023 | C30: 108039000000 | D30: 15108800000000 | E30: 5.56 | F30: 349036000000 | G30: 100075000000 | H30: 104000000000000 | I30: 314491000000 | J30: 145.28 | K30: 1952.3 | L30: 273022.74 | M30: 6307.23 | N30: 5682.99 | O30: 2110 | P30: 6200 | Q30: 268254.76 | R30: 14845000000000 | T30: 3.65 | U30: 3413105000000 | V30: 43.29 | W30: 139.85 | X30: 139.85 | Y30: 0.31 | Z30: 43.74
A31: Madagascar | B31: 2020 | C31: 13051441204 | D31: 49435600000000 | E31: -7.14 | F31: 43150154156 | G31: 12245161113 | H31: 20319100000000 | I31: 44754297418 | J31: 243.3 | K31: 450.77 | L31: 1707412 | M31: 1490.32 | N31: 1545.73 | O31: 450 | P31: 1450 | Q31: 1657192.1 | R31: 47981600000000 | T31: 1.05 | U31: 8085230000000 | V31: 1145.67 | W31: 3787.75 | X31: 3787.75 | Y31: 0.3 | Z31: 1099.49
A32: Madagascar | B32: 2021 | C32: 14354731964 | D32: 54978300000000 | E32: 4.65 | F32: 46835678114 | G32: 12814644792 | H32: 21264100000000 | I32: 46835678114 | J32: 258.55 | K32: 483.47 | L32: 1851677.3 | M32: 1577.43 | N32: 1577.43 | O32: 470 | P32: 1550 | Q32: 1818145.1 | R32: 53982700000000 | S32: 83.9 | T32: 1.19 | U32: 7640824000000 | V32: 1173.86 | W32: 3829.98 | X32: 3829.98 | Y32: 0.31 | Z32: 1131.71
A33: Madagascar | B33: 2022 | C33: 15325603273 | D33: 62775500000000 | E33: 4.16 | F33: 52260133351 | G33: 13347233960 | H33: 22147900000000 | I33: 48782214694 | J33: 283.44 | K33: 503.51 | L33: 2062454 | M33: 1716.98 | N33: 1602.71 | O33: 500 | P33: 1680 | Q33: 2012745.4 | R33: 61262500000000 | T33: 1.44 | U33: 10199780000000 | V33: 1201.21 | W33: 4096.12 | X33: 4096.12 | Y33: 0.29 | Z33: 1133.36
A34: Madagascar | B34: 2023 | C34: 15869945478 | D34: 70297200000000 | E34: 4.2 | F34: 56416214294 | G34: 13908224365 | H34: 23078800000000 | I34: 50832553694 | J34: 304.6 | K34: 508.72 | L34: 2253408.6 | M34: 1808.45 | N34: 1629.46 | O34: 510 | P34: 1770 | Q34: 2204382.4 | R34: 68767800000000 | T34: 1.72 | U34: 12596877000000 | V34: 1246.05 | W34: 4429.58 | X34: 4429.58 | Y34: 0.28 | Z34: 1196.04
A35: Malawi | B35: 2020 | C35: 11769313598 | D35: 8821420000000 | E35: 0.79 | F35: 29563756336 | G35: 10928176722 | H35: 7262380000000 | I35: 32356710546 | J35: 121.47 | K35: 602.51 | L35: 451595.92 | M35: 1513.46 | N35: 1656.44 | O35: 560 | P35: 1470 | Q35: 438966.53 | R35: 8574720000000 | T35: 0.87 | U35: 2003650000000 | V35: 298.39 | W35: 749.53 | X35: 749.53 | Y35: 0.4 | Z35: 280.9
A36: Malawi | B36: 2021 | C36: 12378129751 | D36: 9975520000000 | E36: 4.56 | F36: 33831623933 | G36: 11426314940 | H36: 7593420000000 | I36: 33831623933 | J36: 131.37 | K36: 617.45 | L36: 497600.32 | M36: 1687.59 | N36: 1687.59 | O36: 600 | P36: 1640 | Q36: 482649.39 | R36: 9675800000000 | T36: 0.91 | U36: 2359358000000 | V36: 294.86 | W36: 805.9 | X36: 805.9 | Y36: 0.37 | Z36: 282.09
A37: Malawi | B37: 2022 | C37: 12429060151 | D37: 11795700000000 | E37: 0.92 | F37: 36577488742 | G37: 11531564449 | H37: 7663360000000 | I37: 34143252120 | J37: 153.92 | K37: 604.27 | L37: 573475.56 | M37: 1778.31 | N37: 1659.96 | O37: 610 | P37: 1720 | Q37: 556197.2 | R37: 11440300000000 | T37: 1.15 | U37: 3146994000000 | V37: 322.48 | W37: 949.04 | X37: 949.04 | Y37: 0.34 | Z37: 315.92
A38: Malawi | B38: 2023 | C38: 12712150082 | D38: 14760000000000 | E38: 1.89 | F38: 38610812097 | G38: 11749794461 | H38: 7808390000000 | I38: 34789398822 | J38: 189.03 | K38: 602.34 | L38: 699377.78 | M38: 1829.51 | N38: 1648.44 | O38: 600 | P38: 1780 | Q38: 679406.67 | R38: 14338500000000 | T38: 1.22 | U38: 3943286000000 | V38: 382.28 | W38: 1161.09 | X38: 1161.09 | Y38: 0.33 | Z38: 390.79
A39: Mauritius | B39: 2020 | C39: 11408106446 | D39: 448874000000 | E39: -14.55 | F39: 26999298653 | G39: 11853530019 | H39: 439662000000 | I39: 27845555062 | J39: 102.1 | K39: 9011.04 | L39: 354556.9 | M39: 21326.22 | N39: 21994.67 | O39: 10470 | P39: 22890 | Q39: 380513.96 | R39: 481736000000 | T39: 21.79 | U39: 146401000000 | V39: 16.63 | W39: 39.35 | X39: 39.35 | Y39: 0.42 | Z39: 18.63
A40: Mauritius | B40: 2021 | C40: 11484348858 | D40: 478807000000 | E40: 3.4 | F40: 28793361693 | G40: 12257000315 | H40: 454627000000 | I40: 28793361693 | J40: 105.32 | K40: 9068.97 | L40: 378104.83 | M40: 22737.57 | N40: 22737.57 | O40: 10840 | P40: 25280 | Q40: 420303.02 | R40: 532244000000 | T40: 21.98 | U40: 147548000000 | V40: 16.63 | W40: 41.69 | X40: 41.69 | Y40: 0.4 | Z40: 18.77
A41: Mauritius | B41: 2022 | C41: 12907767790 | D41: 570301000000 | E41: 8.69 | F41: 33527657824 | G41: 13322509534 | H41: 494148000000 | I41: 31296387845 | J41: 115.41 | K41: 10223.79 | L41: 451715.34 | M41: 26556.08 | N41: 24788.77 | O41: 11620 | P41: 29260 | Q41: 497710.54 | R41: 628371000000 | T41: 6.37 | U41: 167410000000 | V41: 17.01 | W41: 44.18 | X41: 44.18 | Y41: 0.38 | Z41: 19.25
A42: Mauritius | B42: 2023 | C42: 14101195733 | D42: 638322000000 | E42: 5.01 | F42: 36473533933 | G42: 13989676007 | H42: 518894000000 | I42: 32863652680 | J42: 123.02 | K42: 11182.19 | L42: 506186.56 | M42: 28923.35 | N42: 26060.73 | O42: 12070 | P42: 31670 | Q42: 554172.31 | R42: 698834000000 | T42: 12.6 | U42: 191021000000 | V42: 17.5 | W42: 45.27 | X42: 45.27 | Y42: 0.39 | Z42: 19.79
A43: Mozambique | B43: 2020 | C43: 14235420174 | D43: 988863000000 | E43: -1.22 | F43: 43454882039 | G43: 18217911540 | H43: 958464000000 | I43: 45132727327 | J43: 103.17 | K43: 462.43 | L43: 32122.97 | M43: 1411.62 | N43: 1466.12 | O43: 480 | P43: 1380 | Q43: 31475.97 | R43: 968946000000 | T43: 8.83 | U43: 334810000000 | V43: 22.76 | W43: 69.47 | X43: 69.47 | Y43: 0.33 | Z43: 23.39
A44: Mozambique | B44: 2021 | C44: 16168055475 | D44: 1058440000000 | E44: 2.38 | F44: 46205728911 | G44: 18651030678 | H44: 981251000000 | I44: 46205728911 | J44: 107.87 | K44: 509.91 | L44: 33381.12 | M44: 1457.24 | N44: 1457.24 | O44: 490 | P44: 1430 | Q44: 32679.43 | R44: 1036190000000 | T44: 44.76 | U44: 339994000000 | V44: 22.91 | W44: 65.47 | X44: 65.47 | Y44: 0.35 | Z44: 23.62
A45: Mozambique | B45: 2022 | C45: 18883528581 | D45: 1205730000000 | E45: 4.36 | F45: 51660358771 | G45: 19465045725 | H45: 1024080000000 | I45: 48222355191 | J45: 117.74 | K45: 578.25 | L45: 36921.85 | M45: 1581.94 | N45: 1476.67 | O45: 500 | P45: 1460 | Q45: 34141.7 | R45: 1114940000000 | S45: 89.1 | T45: 33.02 | U45: 396664000000 | V45: 23.34 | W45: 63.85 | X45: 63.85 | Y45: 0.37 | Z45: 24.12
A46: Mozambique | B46: 2023 | C46: 20954220984 | D46: 1338680000000 | E46: 5.44 | F46: 56429069635 | G46: 20523332839 | H46: 1079750000000 | I46: 50844136708 | J46: 123.98 | K46: 622.99 | L46: 39799.96 | M46: 1677.68 | N46: 1511.64 | O46: 540 | P46: 1530 | Q46: 36310.41 | R46: 1221310000000 | T46: 22.7 | U46: 445500000000 | V46: 23.72 | W46: 63.89 | X46: 63.89 | Y46: 0.37 | Z46: 24.82
A47: Rwanda | B47: 2020 | C47: 10174386855 | D47: 9597280000000 | E47: -3.37 | F47: 29854116562 | G47: 10797494132 | H47: 8830020000000 | I47: 32930056262 | J47: 108.69 | K47: 778.7 | L47: 734532.03 | M47: 2284.9 | N47: 2520.32 | O47: 770 | P47: 2230 | Q47: 717442.01 | R47: 9373980000000 | T47: 2.85 | U47: 3211170000000 | V47: 321.47 | W47: 943.28 | X47: 943.28 | Y47: 0.34 | Z47: 305.23
A48: Rwanda | B48: 2021 | C48: 11078787095 | D48: 10952800000000 | E48: 10.86 | F48: 36505744034 | G48: 11969932692 | H48: 9788830000000 | I48: 36505744034 | J48: 111.89 | K48: 829.54 | L48: 820108.61 | M48: 2733.44 | N48: 2733.44 | O48: 840 | P48: 2680 | Q48: 803371.93 | R48: 10729200000000 | T48: 5.71 | U48: 3453932000000 | V48: 300.03 | W48: 988.62 | X48: 988.62 | Y48: 0.3 | Z48: 291.6
A49: Rwanda | B49: 2022 | C49: 13316161006 | D49: 13719800000000 | E49: 8.16 | F49: 42300132774 | G49: 12946823702 | H49: 10587700000000 | I49: 39485053448 | J49: 129.58 | K49: 975.47 | L49: 1005034.1 | M49: 3098.68 | N49: 2892.46 | O49: 940 | P49: 3030 | Q49: 983911.14 | R49: 13431400000000 | S49: 62.2 | T49: 2.68 | U49: 4068556000000 | V49: 324.34 | W49: 1030.31 | X49: 1030.31 | Y49: 0.31 | Z49: 317.75
A50: Rwanda | B50: 2023 | C50: 14331722700 | D50: 16626200000000 | E50: 8.25 | F50: 47437550806 | G50: 14014924102 | H50: 11461200000000 | I50: 42742532065 | J50: 145.07 | K50: 1027.03 | L50: 1191461.3 | M50: 3399.45 | N50: 3063 | O50: 1000 | P50: 3330 | Q50: 1168170.4 | R50: 16301200000000 | T50: 3.88 | U50: 4492736000000 | V50: 350.49 | W50: 1160.1 | X50: 1160.1 | Y50: 0.3 | Z50: 365.58
A51: Seychelles | B51: 2020 | C51: 1382551752 | D51: 24355749200 | E51: -11.74 | F51: 3057830378 | G51: 1678615793 | H51: 22575438500 | I51: 2959393508 | J51: 107.89 | K51: 14041.48 | L51: 247361.92 | M51: 31055.94 | N51: 30056.2 | O51: 15400 | P51: 29950 | Q51: 238579.35 | R51: 23491000000 | U51: 11377000000 | V51: 7.97 | W51: 17.62 | X51: 17.62 | Y51: 0.45 | Z51: 9.4
A52: Seychelles | B52: 2021 | C52: 1487173795 | D52: 25163758400 | E52: 0.55 | F52: 2975737695 | G52: 1687886479 | H52: 22700118500 | I52: 2975737695 | J52: 110.85 | K52: 14982.91 | L52: 253518.69 | M52: 29979.83 | N52: 29979.83 | O52: 14950 | P52: 28720 | Q52: 242892.26 | R52: 24109000000 | U52: 9771000000 | V52: 8.46 | W52: 16.92 | X52: 16.92 | Y52: 0.5 | Z52: 9.83
A53: Seychelles | B53: 2022 | C53: 2018346589 | D53: 28807447100 | E53: 12.71 | F53: 3593088409 | G53: 1902424765 | H53: 25585410000 | I53: 3353967909 | J53: 112.59 | K53: 16836.67 | L53: 240306.37 | M53: 29972.88 | N53: 27978.18 | O53: 14700 | P53: 29030 | Q53: 232757.03 | R53: 27902447100 | U53: 9016000000 | V53: 8.02 | W53: 14.27 | X53: 14.27 | Y53: 0.56 | Z53: 9.34
A54: Seychelles | B54: 2023 | C54: 2187379755 | D54: 30662932200 | E54: 2.26 | F54: 3806479822 | G54: 1945405358 | H54: 26163449200 | I54: 3429742537 | J54: 117.2 | K54: 18262.71 | L54: 256008.72 | M54: 31780.78 | N54: 28635.36 | O54: 16400 | P54: 30920 | Q54: 249062.24 | R54: 29830932200 | U54: 10077000000 | V54: 8.06 | W54: 14.02 | X54: 14.02 | Y54: 0.57 | Z54: 8.88
A55: Somalia | B55: 2020 | C55: 8628393720 | D55: 222278000000000 | E55: -2.75 | F55: 24216384567 | G55: 7710043010 | H55: 257590000000000 | I55: 23245952366 | J55: 86.29 | K55: 518.18 | L55: 1349046.2 | M55: 1454.33 | N55: 1396.05 | O55: 500 | P55: 1450 | Q55: 13290206 | R55: 221298000000000 | T55: 9.56 | U55: 472000000 | V55: 9178.81 | W55: 25761.17 | Y55: 0.36 | Z55: 10373.88
A56: Somalia | B56: 2021 | C56: 9483997390 | D56: 246954000000000 | E56: 3.46 | F56: 24049850384 | G56: 7976673871 | H56: 264498000000000 | I56: 24049850384 | J56: 92.67 | K56: 549.11 | L56: 14298404 | M56: 1392.46 | N56: 1392.46 | O56: 540 | P56: 1390 | Q56: 14235064 | R56: 245860000000000 | T56: 0.18 | U56: 460000000 | V56: 10268.42 | W56: 26039.01 | Y56: 0.39 | Z56: 10392.25
A57: Somalia | B57: 2022 | C57: 10202767270 | D57: 273766000000000 | E57: 2.73 | F57: 26467106676 | G57: 8194206885 | H57: 273766000000000 | I57: 24705717292 | J57: 100 | K57: 573.13 | L57: 15378471 | M57: 1486.76 | N57: 1387.81 | O57: 570 | P57: 1480 | Q57: 15312150 | R57: 272585000000000 | T57: 0.2 | U57: 720000000 | V57: 10343.63 | W57: 26832.52 | Y57: 0.39
A58: Somalia | B58: 2023 | C58: 10968517090 | D58: 298621000000000 | E58: 4.22 | F58: 28575608117 | G58: 8539706139 | H58: 285309000000000 | I58: 25747405283 | J58: 104.67 | K58: 597.46 | L58: 16266003 | M58: 1556.52 | N58: 1402.47 | O58: 590 | P58: 1550 | Q58: 16203718 | R58: 297478000000000 | T58: 3.32 | U58: 733000000 | V58: 10450.22 | W58: 27225.31 | Y58: 0.38
A59: South Sudan | B59: 2020 | U59: 30814000000 | W59: 161.02 | X59: 165.91
A60: South Sudan | B60: 2021 | U60: 810721000000 | V60: 126.74 | W60: 190.2 | X60: 306.35 | Y60: 0.67 | Z60: 158.05
A61: South Sudan | B61: 2022 | U61: 1186283000000 | W61: 422.49 | X61: 534.51
A62: South Sudan | B62: 2023 | U62: 1478329000000 | W62: 730.83 | X62: 930.33
A63: Uganda | B63: 2020 | C63: 37600368240 | D63: 139689000000000 | E63: 2.95 | F63: 112575000000 | G63: 40768765796 | H63: 126410000000000 | I63: 119057000000 | J63: 110.5 | K63: 845.77 | L63: 3142105.1 | M63: 2532.22 | N63: 2678.01 | O63: 820 | P63: 2480 | Q63: 3077785.1 | R63: 136830000000000 | T63: 1.88 | U63: 30271076000000 | V63: 1240.85 | W63: 3715.1 | X63: 3718.25 | Y63: 0.33 | Z63: 1315.93
A64: Uganda | B64: 2021 | C64: 40529788744 | D64: 148310000000000 | E64: 3.54 | F64: 123267000000 | G64: 42210585953 | H64: 130881000000000 | I64: 123267000000 | J64: 113.32 | K64: 882.79 | L64: 3230390.8 | M64: 2684.92 | N64: 2684.92 | O64: 860 | P64: 2630 | Q64: 3159743.6 | R64: 145067000000000 | T64: 1.95 | U64: 33726522000000 | V64: 1203.16 | W64: 3659.29 | X64: 3587.05 | Y64: 0.33 | Z64: 1315.27
A65: Uganda | B65: 2022 | C65: 45565333216 | D65: 162750000000000 | E65: 4.59 | F65: 138114000000 | G65: 44147216890 | H65: 136886000000000 | I65: 128923000000 | J65: 118.89 | K65: 963.07 | L65: 3439877.3 | M65: 2919.18 | N65: 2724.91 | O65: 930 | P65: 2860 | Q65: 3366668 | R65: 159286000000000 | T65: 2.09 | U65: 33979770000000 | V65: 1178.37 | W65: 3571.79 | X65: 3689.82 | Y65: 0.33 | Z65: 1305.44
A66: Uganda | B66: 2023 | C66: 48768955859 | D66: 183004000000000 | E66: 5.34 | F66: 150720000000 | G66: 46503341915 | H66: 144191000000000 | I66: 135803000000 | J66: 126.92 | K66: 1002.31 | L66: 3761142 | M66: 3097.64 | N66: 2791.06 | O66: 970 | P66: 3020 | Q66: 3666392.9 | R66: 178394000000000 | T66: 4.99 | U66: 37342452000000 | V66: 1214.2 | W66: 3752.48 | X66: 3726.14 | Y66: 0.32 | Z66: 1320.92
A67: United Republic of Tanzania | B67: 2020 | C67: 66068737786 | D67: 151571000000000 | E67: 1.99 | F67: 194562000000 | G67: 61565931105 | H67: 122511000000000 | I67: 203976000000 | J67: 123.72 | K67: 1117.42 | L67: 2563514 | M67: 3290.61 | N67: 3449.82 | O67: 1060 | P67: 3230 | Q67: 2514446.8 | R67: 148670000000000 | T67: 1.96 | U67: 25356724000000 | V67: 779.04 | W67: 2294.15 | X67: 2294.15 | Y67: 0.34 | Z67: 694.78
A68: United Republic of Tanzania | B68: 2021 | C68: 70655628148 | D68: 162350000000000 | E68: 4.32 | F68: 212790000000 | G68: 64226431583 | H68: 127805000000000 | I68: 212790000000 | J68: 127.03 | K68: 1159.86 | L68: 2665077 | M68: 3493.08 | N68: 3493.08 | O68: 1130 | P68: 3430 | Q68: 2620133 | R68: 159612000000000 | T68: 2.82 | U68: 28738012000000 | V68: 762.96 | W68: 2297.76 | X68: 2297.76 | Y68: 0.33 | Z68: 681.85
A69: United Republic of Tanzania | B69: 2022 | C69: 75769974505 | D69: 174453000000000 | E69: 4.57 | F69: 238370000000 | G69: 67159014151 | H69: 133640000000000 | I69: 222506000000 | J69: 130.54 | K69: 1207.85 | L69: 2780960.8 | M69: 3799.86 | N69: 3546.98 | O69: 1210 | P69: 3730 | Q69: 2729809.5 | R69: 171244000000000 | T69: 2.68 | U69: 32661233000000 | V69: 731.86 | W69: 2302.4 | X69: 2303.03 | Y69: 0.32 | Z69: 658.79
A70: United Republic of Tanzania | B70: 2023 | C70: 79062403837 | D70: 183334000000000 | E70: 5.07 | F70: 259466000000 | G70: 70563656178 | H70: 140415000000000 | I70: 233786000000 | J70: 134.13 | K70: 1224.49 | L70: 2916849.5 | M70: 4018.52 | N70: 3620.79 | O70: 1220 | P70: 3940 | Q70: 2861169.2 | R70: 184739000000000 | T70: 2.89 | U70: 35499690000000 | V70: 725.85 | W70: 2382.09 | X70: 2383.04 | Y70: 0.3 | Z70: 656.79
A71: Zambia | B71: 2020 | C71: 18137764931 | D71: 332721000000 | E71: -2.79 | F71: 60176229608 | G71: 23418945737 | H71: 137755000000 | I71: 64641756629 | J71: 241.53 | K71: 951.64 | L71: 17457.05 | M71: 3157.3 | N71: 3391.6 | O71: 1120 | P71: 3070 | Q71: 16967.18 | R71: 323338000000 | T71: 11.61 | U71: 113227000000 | V71: 5.53 | W71: 18.34 | X71: 18.34 | Y71: 0.3 | Z71: 5.36
A72: Zambia | B72: 2021 | C72: 22096416932 | D72: 442337000000 | E72: 6.23 | F72: 68672119765 | G72: 24879098748 | H72: 146344000000 | I72: 68672119765 | J72: 302.26 | K72: 1127.16 | L72: 22564.05 | M72: 3503.03 | N72: 3503.03 | O72: 1040 | P72: 3200 | Q72: 20601.54 | R72: 403864000000 | T72: 8.54 | U72: 134929000000 | V72: 6.44 | W72: 20.02 | X72: 20.02 | Y72: 0.32 | Z72: 6.19
A73: Zambia | B73: 2022 | C73: 29163782140 | D73: 493964000000 | E73: 5.21 | F73: 77401882827 | G73: 26175604214 | H73: 153970000000 | I73: 72250777479 | J73: 320.82 | K73: 1447.12 | L73: 24510.78 | M73: 3840.72 | N73: 3585.12 | O73: 1160 | P73: 3610 | Q73: 23041.98 | R73: 464364000000 | S73: 81.4 | T73: 5.34 | U73: 139315000000 | V73: 6.38 | W73: 16.94 | X73: 16.94 | Y73: 0.38 | Z73: 6.36
A74: Zambia | B74: 2023 | C74: 27577956471 | D74: 557406000000 | E74: 5.37 | F74: 84491503485 | G74: 27580695690 | H74: 162235000000 | I74: 76129157927 | J74: 343.58 | K74: 1330.73 | L74: 26896.69 | M74: 4077 | N74: 3673.48 | O74: 1290 | P74: 3880 | Q74: 25622.81 | R74: 531006000000 | T74: 3.61 | U74: 152642000000 | V74: 6.6 | W74: 20.21 | X74: 20.21 | Y74: 0.33 | Z74: 6.77
A75: Zimbabwe | B75: 2020 | C75: 26868564055 | D75: 551799700 | E75: -7.82 | F75: 54509873680 | G75: 19101046520 | H75: 78275500 | I75: 46382982069 | J75: 704.95 | K75: 1730.45 | L75: 35.54 | M75: 3510.68 | N75: 2987.27 | O75: 1690 | P75: 3440 | Q75: 34.83 | R75: 540746600 | T75: 3.74 | U75: 76000000 | V75: 0.01 | W75: 0.02 | X75: 51.33 | Y75: 0.49 | Z75: 0.01
A76: Zimbabwe | B76: 2021 | C76: 27240507842 | D76: 1276626400 | E76: 8.47 | F76: 50310711159 | G76: 20718530621 | H76: 84903900 | I76: 50310711159 | J76: 1503.61 | K76: 1724.39 | L76: 80.81 | M76: 3184.78 | N76: 3184.78 | O76: 1740 | P76: 3110 | Q76: 78.98 | R76: 1247629600 | T76: 2.28 | U76: 238000000 | V76: 0.03 | W76: 0.05 | X76: 88.55 | Y76: 0.54 | Z76: 0.03
A77: Zimbabwe | B77: 2022 | C77: 32789657378 | D77: 4972682700 | E77: 6.14 | F77: 57206472522 | G77: 21990477716 | H77: 90116300 | I77: 53399374351 | J77: 5518.07 | K77: 2040.55 | L77: 309.46 | M77: 3560.04 | N77: 3323.12 | O77: 1960 | P77: 3480 | Q77: 302.26 | R77: 4856999700 | T77: 1.42 | U77: 1067000000 | V77: 0.09 | W77: 0.15 | X77: 374.95 | Y77: 0.57
A78: Zimbabwe | B78: 2023 | C78: 35231369343 | D78: 53508663900 | E78: 5.34 | F78: 62427821460 | G78: 23164059016 | H78: 94925600 | I78: 56249176341 | J78: 56369.06 | K78: 2156.03 | L78: 3274.54 | M78: 3820.36 | N78: 3442.25 | O78: 2060 | P78: 3770 | Q78: 3234.08 | R78: 52847537600 | T78: 3.34 | U78: 10476000000 | V78: 0.86 | W78: 1.52 | X78: 3509.17 | Y78: 0.56

Sheet 2023 Latest Snapshot
A1: Country | B1: Economic Output & Growth | J1: Income & Living Standards (Per Capita) | R1: Poverty | S1: Government Finance & Debt | U1: Prices, Exchange Rates & PPP Conversion
B2: GDP (current US$) | C2: GDP (current LCU) | D2: GDP growth (annual %) | E2: GDP, PPP (current international $) | F2: GDP at market prices (constant 2010 US$) | G2: GDP (constant LCU) | H2: GDP, PPP (constant 2011 international $) | I2: GDP deflator (base year varies by country) | J2: GDP per capita (current US$) | K2: GDP per capita (current LCU) | L2: GDP per capita, PPP (current international $) | M2: GDP per capita, PPP (constant 2011 international $) | N2: GNI per capita, Atlas method (current US$) | O2: GNI per capita, PPP (current international $) | P2: GNI per capita (current LCU) | Q2: GNI (current LCU) | R2: Poverty headcount ratio at $3.20 a day (PPP) (% of population) | S2: Total debt service (% of GNI) | T2: General government total expenditure (current LCU) | U2: PPP conversion factor, GDP (LCU per international $) | V2: DEC alternative conversion factor (LCU per US$) | W2: Official exchange rate (LCU per US$, period average) | X2: Price level ratio of PPP conversion factor (GDP) to market exchange rate | Y2: PPP conversion factor, private consumption (LCU per international $)
A3: Burundi | B3: =IFERROR(SUMIFS(Data!C$3:C$78,Data!$A$3:$A$78,$A3,Data!$B$3:$B$78,2023),"n/a") -> 2629391600 | C3: =IFERROR(SUMIFS(Data!D$3:D$78,Data!$A$3:$A$78,$A3,Data!$B$3:$B$78,2023),"n/a") -> 9071960000000 | D3: =IFERROR(SUMIFS(Data!E$3:E$78,Data!$A$3:$A$78,$A3,Data!$B$3:$B$78,2023),"n/a") -> 2.67 | E3: =IFERROR(SUMIFS(Data!F$3:F$78,Data!$A$3:$A$78,$A3,Data!$B$3:$B$78,2023),"n/a") -> 12588790451 | F3: =IFERROR(SUMIFS(Data!G$3:G$78,Data!$A$3:$A$78,$A3,Data!$B$3:$B$78,2023),"n/a") -> 3469531570 | G3: =IFERROR(SUMIFS(Data!H$3:H$78,Data!$A$3:$A$78,$A3,Data!$B$3:$B$78,2023),"n/a") -> 1924910000000 | H3: =IFERROR(SUMIFS(Data!I$3:I$78,Data!$A$3:$A$78,$A3,Data!$B$3:$B$78,2023),"n/a") -> 11342844864 | I3: =IFERROR(SUMIFS(Data!J$3:J$78,Data!$A$3:$A$78,$A3,Data!$B$3:$B$78,2023),"n/a") -> 471.29 | ... Q3: =IFERROR(SUMIFS(Data!R$3:R$78,Data!$A$3:$A$78,$A3,Data!$B$3:$B$78,2023),"n/a") -> 9136040000000 | R3: =IFERROR(SUMIFS(Data!S$3:S$78,Data!$A$3:$A$78,$A3,Data!$B$3:$B$78,2020),"n/a") -> 87.2 | S3: =IFERROR(SUMIFS(Data!T$3:T$78,Data!$A$3:$A$78,$A3,Data!$B$3:$B$78,2023),"n/a") -> 1.68 | T3: =IFERROR(SUMIFS(Data!U$3:U$78,Data!$A$3:$A$78,$A3,Data!$B$3:$B$78,2023),"n/a") -> 3101347000000 | U3: =IFERROR(SUMIFS(Data!V$3:V$78,Data!$A$3:$A$78,$A3,Data!$B$3:$B$78,2023),"n/a") -> 720.64 | V3: =IFERROR(SUMIFS(Data!W$3:W$78,Data!$A$3:$A$78,$A3,Data!$B$3:$B$78,2023),"n/a") -> 3450.21 | W3: =IFERROR(SUMIFS(Data!X$3:X$78,Data!$A$3:$A$78,$A3,Data!$B$3:$B$78,2023),"n/a") -> 2574.05 | X3: =IFERROR(SUMIFS(Data!Y$3:Y$78,Data!$A$3:$A$78,$A3,Data!$B$3:$B$78,2023),"n/a") -> 0.21 | Y3: =IFERROR(SUMIFS(Data!Z$3:Z$78,Data!$A$3:$A$78,$A3,Data!$B$3:$B$78,2023),"n/a") -> 881.67
A4: Comoros | B4: =IFERROR(SUMIFS(Data!C$3:C$78,Data!$A$3:$A$78,$A4,Data!$B$3:$B$78,2023),"n/a") -> 1430523436 | C4: =IFERROR(SUMIFS(Data!D$3:D$78,Data!$A$3:$A$78,$A4,Data!$B$3:$B$78,2023),"n/a") -> 650876000000 | D4: =IFERROR(SUMIFS(Data!E$3:E$78,Data!$A$3:$A$78,$A4,Data!$B$3:$B$78,2023),"n/a") -> 3.06 | E4: =IFERROR(SUMIFS(Data!F$3:F$78,Data!$A$3:$A$78,$A4,Data!$B$3:$B$78,2023),"n/a") -> 3318845024 | F4: =IFERROR(SUMIFS(Data!G$3:G$78,Data!$A$3:$A$78,$A4,Data!$B$3:$B$78,2023),"n/a") -> 1280048597 | G4: =IFERROR(SUMIFS(Data!H$3:H$78,Data!$A$3:$A$78,$A4,Data!$B$3:$B$78,2023),"n/a") -> 570568000000 | H4: =IFERROR(SUMIFS(Data!I$3:I$78,Data!$A$3:$A$78,$A4,Data!$B$3:$B$78,2023),"n/a") -> 2990370233 | I4: =IFERROR(SUMIFS(Data!J$3:J$78,Data!$A$3:$A$78,$A4,Data!$B$3:$B$78,2023),"n/a") -> 114.08 | ... Q4: =IFERROR(SUMIFS(Data!R$3:R$78,Data!$A$3:$A$78,$A4,Data!$B$3:$B$78,2023),"n/a") -> 654235000000 | R4: n/a | S4: =IFERROR(SUMIFS(Data!T$3:T$78,Data!$A$3:$A$78,$A4,Data!$B$3:$B$78,2023),"n/a") -> 1.31 | T4: =IFERROR(SUMIFS(Data!U$3:U$78,Data!$A$3:$A$78,$A4,Data!$B$3:$B$78,2023),"n/a") -> 107878000000 | U4: =IFERROR(SUMIFS(Data!V$3:V$78,Data!$A$3:$A$78,$A4,Data!$B$3:$B$78,2023),"n/a") -> 196.12 | V4: =IFERROR(SUMIFS(Data!W$3:W$78,Data!$A$3:$A$78,$A4,Data!$B$3:$B$78,2023),"n/a") -> 454.99 | W4: =IFERROR(SUMIFS(Data!X$3:X$78,Data!$A$3:$A$78,$A4,Data!$B$3:$B$78,2023),"n/a") -> 454.99 | X4: =IFERROR(SUMIFS(Data!Y$3:Y$78,Data!$A$3:$A$78,$A4,Data!$B$3:$B$78,2023),"n/a") -> 0.43 | Y4: =IFERROR(SUMIFS(Data!Z$3:Z$78,Data!$A$3:$A$78,$A4,Data!$B$3:$B$78,2021),"n/a") -> 228.05
A5: Democratic Republic of the Congo | B5: =IFERROR(SUMIFS(Data!C$3:C$78,Data!$A$3:$A$78,$A5,Data!$B$3:$B$78,2023),"n/a") -> 67006756666 | C5: =IFERROR(SUMIFS(Data!D$3:D$78,Data!$A$3:$A$78,$A5,Data!$B$3:$B$78,2023),"n/a") -> 163777000000000 | D5: =IFERROR(SUMIFS(Data!E$3:E$78,Data!$A$3:$A$78,$A5,Data!$B$3:$B$78,2023),"n/a") -> 8.61 | E5: =IFERROR(SUMIFS(Data!F$3:F$78,Data!$A$3:$A$78,$A5,Data!$B$3:$B$78,2023),"n/a") -> 171006000000 | F5: =IFERROR(SUMIFS(Data!G$3:G$78,Data!$A$3:$A$78,$A5,Data!$B$3:$B$78,2023),"n/a") -> 56862826231 | G5: =IFERROR(SUMIFS(Data!H$3:H$78,Data!$A$3:$A$78,$A5,Data!$B$3:$B$78,2023),"n/a") -> 161824000000000 | H5: =IFERROR(SUMIFS(Data!I$3:I$78,Data!$A$3:$A$78,$A5,Data!$B$3:$B$78,2023),"n/a") -> 154081000000 | I5: =IFERROR(SUMIFS(Data!J$3:J$78,Data!$A$3:$A$78,$A5,Data!$B$3:$B$78,2023),"n/a") -> 1012.07 | ... Q5: =IFERROR(SUMIFS(Data!R$3:R$78,Data!$A$3:$A$78,$A5,Data!$B$3:$B$78,2023),"n/a") -> 158657000000000 | R5: =IFERROR(SUMIFS(Data!S$3:S$78,Data!$A$3:$A$78,$A5,Data!$B$3:$B$78,2020),"n/a") -> 92.5 | S5: =IFERROR(SUMIFS(Data!T$3:T$78,Data!$A$3:$A$78,$A5,Data!$B$3:$B$78,2023),"n/a") -> 0.76 | T5: =IFERROR(SUMIFS(Data!U$3:U$78,Data!$A$3:$A$78,$A5,Data!$B$3:$B$78,2023),"n/a") -> 27144749000000 | U5: =IFERROR(SUMIFS(Data!V$3:V$78,Data!$A$3:$A$78,$A5,Data!$B$3:$B$78,2023),"n/a") -> 957.73 | V5: =IFERROR(SUMIFS(Data!W$3:W$78,Data!$A$3:$A$78,$A5,Data!$B$3:$B$78,2023),"n/a") -> 2444.19 | W5: =IFERROR(SUMIFS(Data!X$3:X$78,Data!$A$3:$A$78,$A5,Data!$B$3:$B$78,2023),"n/a") -> 2340.04 | X5: =IFERROR(SUMIFS(Data!Y$3:Y$78,Data!$A$3:$A$78,$A5,Data!$B$3:$B$78,2023),"n/a") -> 0.39 | Y5: =IFERROR(SUMIFS(Data!Z$3:Z$78,Data!$A$3:$A$78,$A5,Data!$B$3:$B$78,2021),"n/a") -> 928.6
A6: Djibouti | B6: =IFERROR(SUMIFS(Data!C$3:C$78,Data!$A$3:$A$78,$A6,Data!$B$3:$B$78,2023),"n/a") -> 3917150481 | C6: =IFERROR(SUMIFS(Data!D$3:D$78,Data!$A$3:$A$78,$A6,Data!$B$3:$B$78,2023),"n/a") -> 696160000000 | D6: =IFERROR(SUMIFS(Data!E$3:E$78,Data!$A$3:$A$78,$A6,Data!$B$3:$B$78,2023),"n/a") -> 7.37 | E6: =IFERROR(SUMIFS(Data!F$3:F$78,Data!$A$3:$A$78,$A6,Data!$B$3:$B$78,2023),"n/a") -> 8375036989 | F6: =IFERROR(SUMIFS(Data!G$3:G$78,Data!$A$3:$A$78,$A6,Data!$B$3:$B$78,2023),"n/a") -> 3613673263 | G6: =IFERROR(SUMIFS(Data!H$3:H$78,Data!$A$3:$A$78,$A6,Data!$B$3:$B$78,2023),"n/a") -> 622962000000 | H6: =IFERROR(SUMIFS(Data!I$3:I$78,Data!$A$3:$A$78,$A6,Data!$B$3:$B$78,2023),"n/a") -> 7546137626 | I6: =IFERROR(SUMIFS(Data!J$3:J$78,Data!$A$3:$A$78,$A6,Data!$B$3:$B$78,2023),"n/a") -> 111.75 | ... Q6: =IFERROR(SUMIFS(Data!R$3:R$78,Data!$A$3:$A$78,$A6,Data!$B$3:$B$78,2023),"n/a") -> 714463000000 | R6: n/a | S6: =IFERROR(SUMIFS(Data!T$3:T$78,Data!$A$3:$A$78,$A6,Data!$B$3:$B$78,2023),"n/a") -> 2.52 | T6: =IFERROR(SUMIFS(Data!U$3:U$78,Data!$A$3:$A$78,$A6,Data!$B$3:$B$78,2023),"n/a") -> 149757000000 | U6: =IFERROR(SUMIFS(Data!V$3:V$78,Data!$A$3:$A$78,$A6,Data!$B$3:$B$78,2023),"n/a") -> 83.12 | V6: =IFERROR(SUMIFS(Data!W$3:W$78,Data!$A$3:$A$78,$A6,Data!$B$3:$B$78,2023),"n/a") -> 177.72 | W6: =IFERROR(SUMIFS(Data!X$3:X$78,Data!$A$3:$A$78,$A6,Data!$B$3:$B$78,2023),"n/a") -> 177.72 | X6: =IFERROR(SUMIFS(Data!Y$3:Y$78,Data!$A$3:$A$78,$A6,Data!$B$3:$B$78,2023),"n/a") -> 0.47 | Y6: =IFERROR(SUMIFS(Data!Z$3:Z$78,Data!$A$3:$A$78,$A6,Data!$B$3:$B$78,2023),"n/a") -> 92.02
A7: Eritrea | B7: n/a | C7: n/a | D7: n/a | E7: n/a | F7: n/a | G7: n/a | H7: n/a | I7: n/a | J7: n/a | K7: n/a | L7: n/a | M7: n/a | N7: n/a | O7: n/a | P7: n/a | Q7: n/a | R7: n/a | S7: n/a | T7: n/a | U7: =IFERROR(SUMIFS(Data!V$3:V$78,Data!$A$3:$A$78,$A7,Data!$B$3:$B$78,2021),"n/a") -> 4.94 | V7: =IFERROR(SUMIFS(Data!W$3:W$78,Data!$A$3:$A$78,$A7,Data!$B$3:$B$78,2023),"n/a") -> 15.07 | W7: =IFERROR(SUMIFS(Data!X$3:X$78,Data!$A$3:$A$78,$A7,Data!$B$3:$B$78,2023),"n/a") -> 15.07 | X7: =IFERROR(SUMIFS(Data!Y$3:Y$78,Data!$A$3:$A$78,$A7,Data!$B$3:$B$78,2021),"n/a") -> 0.33 | Y7: =IFERROR(SUMIFS(Data!Z$3:Z$78,Data!$A$3:$A$78,$A7,Data!$B$3:$B$78,2021),"n/a") -> 5.2
A8: Ethiopia | B8: =IFERROR(SUMIFS(Data!C$3:C$78,Data!$A$3:$A$78,$A8,Data!$B$3:$B$78,2022),"n/a") -> 126773000000 | C8: =IFERROR(SUMIFS(Data!D$3:D$78,Data!$A$3:$A$78,$A8,Data!$B$3:$B$78,2023),"n/a") -> 8723120000000 | D8: =IFERROR(SUMIFS(Data!E$3:E$78,Data!$A$3:$A$78,$A8,Data!$B$3:$B$78,2023),"n/a") -> 6.59 | E8: =IFERROR(SUMIFS(Data!F$3:F$78,Data!$A$3:$A$78,$A8,Data!$B$3:$B$78,2023),"n/a") -> 393913000000 | F8: =IFERROR(SUMIFS(Data!G$3:G$78,Data!$A$3:$A$78,$A8,Data!$B$3:$B$78,2023),"n/a") -> 112756000000 | G8: =IFERROR(SUMIFS(Data!H$3:H$78,Data!$A$3:$A$78,$A8,Data!$B$3:$B$78,2023),"n/a") -> 25015000000000 | H8: =IFERROR(SUMIFS(Data!I$3:I$78,Data!$A$3:$A$78,$A8,Data!$B$3:$B$78,2023),"n/a") -> 354926000000 | I8: =IFERROR(SUMIFS(Data!J$3:J$78,Data!$A$3:$A$78,$A8,Data!$B$3:$B$78,2023),"n/a") -> 348.72 | J8: =IFERROR(SUMIFS(Data!K$3:K$78,Data!$A$3:$A$78,$A8,Data!$B$3:$B$78,2022),"n/a") -> 1011.07 | K8: =IFERROR(SUMIFS(Data!L$3:L$78,Data!$A$3:$A$78,$A8,Data!$B$3:$B$78,2023),"n/a") -> 67783.06 | L8: =IFERROR(SUMIFS(Data!M$3:M$78,Data!$A$3:$A$78,$A8,Data!$B$3:$B$78,2023),"n/a") -> 3060.91 | M8: =IFERROR(SUMIFS(Data!N$3:N$78,Data!$A$3:$A$78,$A8,Data!$B$3:$B$78,2023),"n/a") -> 2757.96 | N8: =IFERROR(SUMIFS(Data!O$3:O$78,Data!$A$3:$A$78,$A8,Data!$B$3:$B$78,2022),"n/a") -> 1010 | O8: =IFERROR(SUMIFS(Data!P$3:P$78,Data!$A$3:$A$78,$A8,Data!$B$3:$B$78,2023),"n/a") -> 3050 | P8: =IFERROR(SUMIFS(Data!Q$3:Q$78,Data!$A$3:$A$78,$A8,Data!$B$3:$B$78,2023),"n/a") -> 67597.16 | Q8: =IFERROR(SUMIFS(Data!R$3:R$78,Data!$A$3:$A$78,$A8,Data!$B$3:$B$78,2023),"n/a") -> 86991900000000 | R8: =IFERROR(SUMIFS(Data!S$3:S$78,Data!$A$3:$A$78,$A8,Data!$B$3:$B$78,2021),"n/a") -> 63.7 | S8: =IFERROR(SUMIFS(Data!T$3:T$78,Data!$A$3:$A$78,$A8,Data!$B$3:$B$78,2022),"n/a") -> 1.59 | T8: =IFERROR(SUMIFS(Data!U$3:U$78,Data!$A$3:$A$78,$A8,Data!$B$3:$B$78,2023),"n/a") -> 943881000000 | U8: =IFERROR(SUMIFS(Data!V$3:V$78,Data!$A$3:$A$78,$A8,Data!$B$3:$B$78,2023),"n/a") -> 22.14 | V8: =IFERROR(SUMIFS(Data!W$3:W$78,Data!$A$3:$A$78,$A8,Data!$B$3:$B$78,2022),"n/a") -> 48.57 | W8: =IFERROR(SUMIFS(Data!X$3:X$78,Data!$A$3:$A$78,$A8,Data!$B$3:$B$78,2023),"n/a") -> 54.6 | X8: =IFERROR(SUMIFS(Data!Y$3:Y$78,Data!$A$3:$A$78,$A8,Data!$B$3:$B$78,2022),"n/a") -> 0.36 | Y8: =IFERROR(SUMIFS(Data!Z$3:Z$78,Data!$A$3:$A$78,$A8,Data!$B$3:$B$78,2023),"n/a") -> 20.83
A9: Kenya | B9: =IFERROR(SUMIFS(Data!C$3:C$78,Data!$A$3:$A$78,$A9,Data!$B$3:$B$78,2023),"n/a") -> 108039000000 | C9: =IFERROR(SUMIFS(Data!D$3:D$78,Data!$A$3:$A$78,$A9,Data!$B$3:$B$78,2023),"n/a") -> 15108800000000 | D9: =IFERROR(SUMIFS(Data!E$3:E$78,Data!$A$3:$A$78,$A9,Data!$B$3:$B$78,2023),"n/a") -> 5.56 | E9: =IFERROR(SUMIFS(Data!F$3:F$78,Data!$A$3:$A$78,$A9,Data!$B$3:$B$78,2023),"n/a") -> 349036000000 | F9: =IFERROR(SUMIFS(Data!G$3:G$78,Data!$A$3:$A$78,$A9,Data!$B$3:$B$78,2023),"n/a") -> 100075000000 | G9: =IFERROR(SUMIFS(Data!H$3:H$78,Data!$A$3:$A$78,$A9,Data!$B$3:$B$78,2023),"n/a") -> 104000000000000 | H9: =IFERROR(SUMIFS(Data!I$3:I$78,Data!$A$3:$A$78,$A9,Data!$B$3:$B$78,2023),"n/a") -> 314491000000 | I9: =IFERROR(SUMIFS(Data!J$3:J$78,Data!$A$3:$A$78,$A9,Data!$B$3:$B$78,2023),"n/a") -> 145.28 | ... Q9: =IFERROR(SUMIFS(Data!R$3:R$78,Data!$A$3:$A$78,$A9,Data!$B$3:$B$78,2023),"n/a") -> 14845000000000 | R9: =IFERROR(SUMIFS(Data!S$3:S$78,Data!$A$3:$A$78,$A9,Data!$B$3:$B$78,2022),"n/a") -> 67 | S9: =IFERROR(SUMIFS(Data!T$3:T$78,Data!$A$3:$A$78,$A9,Data!$B$3:$B$78,2023),"n/a") -> 3.65 | T9: =IFERROR(SUMIFS(Data!U$3:U$78,Data!$A$3:$A$78,$A9,Data!$B$3:$B$78,2023),"n/a") -> 3413105000000 | U9: =IFERROR(SUMIFS(Data!V$3:V$78,Data!$A$3:$A$78,$A9,Data!$B$3:$B$78,2023),"n/a") -> 43.29 | V9: =IFERROR(SUMIFS(Data!W$3:W$78,Data!$A$3:$A$78,$A9,Data!$B$3:$B$78,2023),"n/a") -> 139.85 | W9: =IFERROR(SUMIFS(Data!X$3:X$78,Data!$A$3:$A$78,$A9,Data!$B$3:$B$78,2023),"n/a") -> 139.85 | X9: =IFERROR(SUMIFS(Data!Y$3:Y$78,Data!$A$3:$A$78,$A9,Data!$B$3:$B$78,2023),"n/a") -> 0.31 | Y9: =IFERROR(SUMIFS(Data!Z$3:Z$78,Data!$A$3:$A$78,$A9,Data!$B$3:$B$78,2023),"n/a") -> 43.74
A10: Madagascar | B10: =IFERROR(SUMIFS(Data!C$3:C$78,Data!$A$3:$A$78,$A10,Data!$B$3:$B$78,2023),"n/a") -> 15869945478 | C10: =IFERROR(SUMIFS(Data!D$3:D$78,Data!$A$3:$A$78,$A10,Data!$B$3:$B$78,2023),"n/a") -> 70297200000000 | D10: =IFERROR(SUMIFS(Data!E$3:E$78,Data!$A$3:$A$78,$A10,Data!$B$3:$B$78,2023),"n/a") -> 4.2 | E10: =IFERROR(SUMIFS(Data!F$3:F$78,Data!$A$3:$A$78,$A10,Data!$B$3:$B$78,2023),"n/a") -> 56416214294 | F10: =IFERROR(SUMIFS(Data!G$3:G$78,Data!$A$3:$A$78,$A10,Data!$B$3:$B$78,2023),"n/a") -> 13908224365 | G10: =IFERROR(SUMIFS(Data!H$3:H$78,Data!$A$3:$A$78,$A10,Data!$B$3:$B$78,2023),"n/a") -> 23078800000000 | H10: =IFERROR(SUMIFS(Data!I$3:I$78,Data!$A$3:$A$78,$A10,Data!$B$3:$B$78,2023),"n/a") -> 50832553694 | I10: =IFERROR(SUMIFS(Data!J$3:J$78,Data!$A$3:$A$78,$A10,Data!$B$3:$B$78,2023),"n/a") -> 304.6 | ... Q10: =IFERROR(SUMIFS(Data!R$3:R$78,Data!$A$3:$A$78,$A10,Data!$B$3:$B$78,2023),"n/a") -> 68767800000000 | R10: =IFERROR(SUMIFS(Data!S$3:S$78,Data!$A$3:$A$78,$A10,Data!$B$3:$B$78,2021),"n/a") -> 83.9 | S10: =IFERROR(SUMIFS(Data!T$3:T$78,Data!$A$3:$A$78,$A10,Data!$B$3:$B$78,2023),"n/a") -> 1.72 | T10: =IFERROR(SUMIFS(Data!U$3:U$78,Data!$A$3:$A$78,$A10,Data!$B$3:$B$78,2023),"n/a") -> 12596877000000 | U10: =IFERROR(SUMIFS(Data!V$3:V$78,Data!$A$3:$A$78,$A10,Data!$B$3:$B$78,2023),"n/a") -> 1246.05 | V10: =IFERROR(SUMIFS(Data!W$3:W$78,Data!$A$3:$A$78,$A10,Data!$B$3:$B$78,2023),"n/a") -> 4429.58 | W10: =IFERROR(SUMIFS(Data!X$3:X$78,Data!$A$3:$A$78,$A10,Data!$B$3:$B$78,2023),"n/a") -> 4429.58 | X10: =IFERROR(SUMIFS(Data!Y$3:Y$78,Data!$A$3:$A$78,$A10,Data!$B$3:$B$78,2023),"n/a") -> 0.28 | Y10: =IFERROR(SUMIFS(Data!Z$3:Z$78,Data!$A$3:$A$78,$A10,Data!$B$3:$B$78,2023),"n/a") -> 1196.04
A11: Malawi | B11: =IFERROR(SUMIFS(Data!C$3:C$78,Data!$A$3:$A$78,$A11,Data!$B$3:$B$78,2023),"n/a") -> 12712150082 | C11: =IFERROR(SUMIFS(Data!D$3:D$78,Data!$A$3:$A$78,$A11,Data!$B$3:$B$78,2023),"n/a") -> 14760000000000 | D11: =IFERROR(SUMIFS(Data!E$3:E$78,Data!$A$3:$A$78,$A11,Data!$B$3:$B$78,2023),"n/a") -> 1.89 | E11: =IFERROR(SUMIFS(Data!F$3:F$78,Data!$A$3:$A$78,$A11,Data!$B$3:$B$78,2023),"n/a") -> 38610812097 | F11: =IFERROR(SUMIFS(Data!G$3:G$78,Data!$A$3:$A$78,$A11,Data!$B$3:$B$78,2023),"n/a") -> 11749794461 | G11: =IFERROR(SUMIFS(Data!H$3:H$78,Data!$A$3:$A$78,$A11,Data!$B$3:$B$78,2023),"n/a") -> 7808390000000 | H11: =IFERROR(SUMIFS(Data!I$3:I$78,Data!$A$3:$A$78,$A11,Data!$B$3:$B$78,2023),"n/a") -> 34789398822 | I11: =IFERROR(SUMIFS(Data!J$3:J$78,Data!$A$3:$A$78,$A11,Data!$B$3:$B$78,2023),"n/a") -> 189.03 | ... Q11: =IFERROR(SUMIFS(Data!R$3:R$78,Data!$A$3:$A$78,$A11,Data!$B$3:$B$78,2023),"n/a") -> 14338500000000 | R11: n/a | S11: =IFERROR(SUMIFS(Data!T$3:T$78,Data!$A$3:$A$78,$A11,Data!$B$3:$B$78,2023),"n/a") -> 1.22 | T11: =IFERROR(SUMIFS(Data!U$3:U$78,Data!$A$3:$A$78,$A11,Data!$B$3:$B$78,2023),"n/a") -> 3943286000000 | U11: =IFERROR(SUMIFS(Data!V$3:V$78,Data!$A$3:$A$78,$A11,Data!$B$3:$B$78,2023),"n/a") -> 382.28 | V11: =IFERROR(SUMIFS(Data!W$3:W$78,Data!$A$3:$A$78,$A11,Data!$B$3:$B$78,2023),"n/a") -> 1161.09 | W11: =IFERROR(SUMIFS(Data!X$3:X$78,Data!$A$3:$A$78,$A11,Data!$B$3:$B$78,2023),"n/a") -> 1161.09 | X11: =IFERROR(SUMIFS(Data!Y$3:Y$78,Data!$A$3:$A$78,$A11,Data!$B$3:$B$78,2023),"n/a") -> 0.33 | Y11: =IFERROR(SUMIFS(Data!Z$3:Z$78,Data!$A$3:$A$78,$A11,Data!$B$3:$B$78,2023),"n/a") -> 390.79
A12: Mauritius | B12: =IFERROR(SUMIFS(Data!C$3:C$78,Data!$A$3:$A$78,$A12,Data!$B$3:$B$78,2023),"n/a") -> 14101195733 | C12: =IFERROR(SUMIFS(Data!D$3:D$78,Data!$A$3:$A$78,$A12,Data!$B$3:$B$78,2023),"n/a") -> 638322000000 | D12: =IFERROR(SUMIFS(Data!E$3:E$78,Data!$A$3:$A$78,$A12,Data!$B$3:$B$78,2023),"n/a") -> 5.01 | E12: =IFERROR(SUMIFS(Data!F$3:F$78,Data!$A$3:$A$78,$A12,Data!$B$3:$B$78,2023),"n/a") -> 36473533933 | F12: =IFERROR(SUMIFS(Data!G$3:G$78,Data!$A$3:$A$78,$A12,Data!$B$3:$B$78,2023),"n/a") -> 13989676007 | G12: =IFERROR(SUMIFS(Data!H$3:H$78,Data!$A$3:$A$78,$A12,Data!$B$3:$B$78,2023),"n/a") -> 518894000000 | H12: =IFERROR(SUMIFS(Data!I$3:I$78,Data!$A$3:$A$78,$A12,Data!$B$3:$B$78,2023),"n/a") -> 32863652680 | I12: =IFERROR(SUMIFS(Data!J$3:J$78,Data!$A$3:$A$78,$A12,Data!$B$3:$B$78,2023),"n/a") -> 123.02 | ... Q12: =IFERROR(SUMIFS(Data!R$3:R$78,Data!$A$3:$A$78,$A12,Data!$B$3:$B$78,2023),"n/a") -> 698834000000 | R12: n/a | S12: =IFERROR(SUMIFS(Data!T$3:T$78,Data!$A$3:$A$78,$A12,Data!$B$3:$B$78,2023),"n/a") -> 12.6 | T12: =IFERROR(SUMIFS(Data!U$3:U$78,Data!$A$3:$A$78,$A12,Data!$B$3:$B$78,2023),"n/a") -> 191021000000 | U12: =IFERROR(SUMIFS(Data!V$3:V$78,Data!$A$3:$A$78,$A12,Data!$B$3:$B$78,2023),"n/a") -> 17.5 | V12: =IFERROR(SUMIFS(Data!W$3:W$78,Data!$A$3:$A$78,$A12,Data!$B$3:$B$78,2023),"n/a") -> 45.27 | W12: =IFERROR(SUMIFS(Data!X$3:X$78,Data!$A$3:$A$78,$A12,Data!$B$3:$B$78,2023),"n/a") -> 45.27 | X12: =IFERROR(SUMIFS(Data!Y$3:Y$78,Data!$A$3:$A$78,$A12,Data!$B$3:$B$78,2023),"n/a") -> 0.39 | Y12: =IFERROR(SUMIFS(Data!Z$3:Z$78,Data!$A$3:$A$78,$A12,Data!$B$3:$B$78,2023),"n/a") -> 19.79
A13: Mozambique | B13: =IFERROR(SUMIFS(Data!C$3:C$78,Data!$A$3:$A$78,$A13,Data!$B$3:$B$78,2023),"n/a") -> 20954220984 | C13: =IFERROR(SUMIFS(Data!D$3:D$78,Data!$A$3:$A$78,$A13,Data!$B$3:$B$78,2023),"n/a") -> 1338680000000 | D13: =IFERROR(SUMIFS(Data!E$3:E$78,Data!$A$3:$A$78,$A13,Data!$B$3:$B$78,2023),"n/a") -> 5.44 | E13: =IFERROR(SUMIFS(Data!F$3:F$78,Data!$A$3:$A$78,$A13,Data!$B$3:$B$78,2023),"n/a") -> 56429069635 | F13: =IFERROR(SUMIFS(Data!G$3:G$78,Data!$A$3:$A$78,$A13,Data!$B$3:$B$78,2023),"n/a") -> 20523332839 | G13: =IFERROR(SUMIFS(Data!H$3:H$78,Data!$A$3:$A$78,$A13,Data!$B$3:$B$78,2023),"n/a") -> 1079750000000 | H13: =IFERROR(SUMIFS(Data!I$3:I$78,Data!$A$3:$A$78,$A13,Data!$B$3:$B$78,2023),"n/a") -> 50844136708 | I13: =IFERROR(SUMIFS(Data!J$3:J$78,Data!$A$3:$A$78,$A13,Data!$B$3:$B$78,2023),"n/a") -> 123.98 | ... Q13: =IFERROR(SUMIFS(Data!R$3:R$78,Data!$A$3:$A$78,$A13,Data!$B$3:$B$78,2023),"n/a") -> 1221310000000 | R13: =IFERROR(SUMIFS(Data!S$3:S$78,Data!$A$3:$A$78,$A13,Data!$B$3:$B$78,2022),"n/a") -> 89.1 | S13: =IFERROR(SUMIFS(Data!T$3:T$78,Data!$A$3:$A$78,$A13,Data!$B$3:$B$78,2023),"n/a") -> 22.7 | T13: =IFERROR(SUMIFS(Data!U$3:U$78,Data!$A$3:$A$78,$A13,Data!$B$3:$B$78,2023),"n/a") -> 445500000000 | U13: =IFERROR(SUMIFS(Data!V$3:V$78,Data!$A$3:$A$78,$A13,Data!$B$3:$B$78,2023),"n/a") -> 23.72 | V13: =IFERROR(SUMIFS(Data!W$3:W$78,Data!$A$3:$A$78,$A13,Data!$B$3:$B$78,2023),"n/a") -> 63.89 | W13: =IFERROR(SUMIFS(Data!X$3:X$78,Data!$A$3:$A$78,$A13,Data!$B$3:$B$78,2023),"n/a") -> 63.89 | X13: =IFERROR(SUMIFS(Data!Y$3:Y$78,Data!$A$3:$A$78,$A13,Data!$B$3:$B$78,2023),"n/a") -> 0.37 | Y13: =IFERROR(SUMIFS(Data!Z$3:Z$78,Data!$A$3:$A$78,$A13,Data!$B$3:$B$78,2023),"n/a") -> 24.82
A14: Rwanda | B14: =IFERROR(SUMIFS(Data!C$3:C$78,Data!$A$3:$A$78,$A14,Data!$B$3:$B$78,2023),"n/a") -> 14331722700 | C14: =IFERROR(SUMIFS(Data!D$3:D$78,Data!$A$3:$A$78,$A14,Data!$B$3:$B$78,2023),"n/a") -> 16626200000000 | D14: =IFERROR(SUMIFS(Data!E$3:E$78,Data!$A$3:$A$78,$A14,Data!$B$3:$B$78,2023),"n/a") -> 8.25 | E14: =IFERROR(SUMIFS(Data!F$3:F$78,Data!$A$3:$A$78,$A14,Data!$B$3:$B$78,2023),"n/a") -> 47437550806 | F14: =IFERROR(SUMIFS(Data!G$3:G$78,Data!$A$3:$A$78,$A14,Data!$B$3:$B$78,2023),"n/a") -> 14014924102 | G14: =IFERROR(SUMIFS(Data!H$3:H$78,Data!$A$3:$A$78,$A14,Data!$B$3:$B$78,2023),"n/a") -> 11461200000000 | H14: =IFERROR(SUMIFS(Data!I$3:I$78,Data!$A$3:$A$78,$A14,Data!$B$3:$B$78,2023),"n/a") -> 42742532065 | I14: =IFERROR(SUMIFS(Data!J$3:J$78,Data!$A$3:$A$78,$A14,Data!$B$3:$B$78,2023),"n/a") -> 145.07 | ... Q14: =IFERROR(SUMIFS(Data!R$3:R$78,Data!$A$3:$A$78,$A14,Data!$B$3:$B$78,2023),"n/a") -> 16301200000000 | R14: =IFERROR(SUMIFS(Data!S$3:S$78,Data!$A$3:$A$78,$A14,Data!$B$3:$B$78,2022),"n/a") -> 62.2 | S14: =IFERROR(SUMIFS(Data!T$3:T$78,Data!$A$3:$A$78,$A14,Data!$B$3:$B$78,2023),"n/a") -> 3.88 | T14: =IFERROR(SUMIFS(Data!U$3:U$78,Data!$A$3:$A$78,$A14,Data!$B$3:$B$78,2023),"n/a") -> 4492736000000 | U14: =IFERROR(SUMIFS(Data!V$3:V$78,Data!$A$3:$A$78,$A14,Data!$B$3:$B$78,2023),"n/a") -> 350.49 | V14: =IFERROR(SUMIFS(Data!W$3:W$78,Data!$A$3:$A$78,$A14,Data!$B$3:$B$78,2023),"n/a") -> 1160.1 | W14: =IFERROR(SUMIFS(Data!X$3:X$78,Data!$A$3:$A$78,$A14,Data!$B$3:$B$78,2023),"n/a") -> 1160.1 | X14: =IFERROR(SUMIFS(Data!Y$3:Y$78,Data!$A$3:$A$78,$A14,Data!$B$3:$B$78,2023),"n/a") -> 0.3 | Y14: =IFERROR(SUMIFS(Data!Z$3:Z$78,Data!$A$3:$A$78,$A14,Data!$B$3:$B$78,2023),"n/a") -> 365.58
A15: Seychelles | B15: =IFERROR(SUMIFS(Data!C$3:C$78,Data!$A$3:$A$78,$A15,Data!$B$3:$B$78,2023),"n/a") -> 2187379755 | C15: =IFERROR(SUMIFS(Data!D$3:D$78,Data!$A$3:$A$78,$A15,Data!$B$3:$B$78,2023),"n/a") -> 30662932200 | D15: =IFERROR(SUMIFS(Data!E$3:E$78,Data!$A$3:$A$78,$A15,Data!$B$3:$B$78,2023),"n/a") -> 2.26 | E15: =IFERROR(SUMIFS(Data!F$3:F$78,Data!$A$3:$A$78,$A15,Data!$B$3:$B$78,2023),"n/a") -> 3806479822 | F15: =IFERROR(SUMIFS(Data!G$3:G$78,Data!$A$3:$A$78,$A15,Data!$B$3:$B$78,2023),"n/a") -> 1945405358 | G15: =IFERROR(SUMIFS(Data!H$3:H$78,Data!$A$3:$A$78,$A15,Data!$B$3:$B$78,2023),"n/a") -> 26163449200 | H15: =IFERROR(SUMIFS(Data!I$3:I$78,Data!$A$3:$A$78,$A15,Data!$B$3:$B$78,2023),"n/a") -> 3429742537 | I15: =IFERROR(SUMIFS(Data!J$3:J$78,Data!$A$3:$A$78,$A15,Data!$B$3:$B$78,2023),"n/a") -> 117.2 | ... Q15: =IFERROR(SUMIFS(Data!R$3:R$78,Data!$A$3:$A$78,$A15,Data!$B$3:$B$78,2023),"n/a") -> 29830932200 | R15: n/a | S15: n/a | T15: =IFERROR(SUMIFS(Data!U$3:U$78,Data!$A$3:$A$78,$A15,Data!$B$3:$B$78,2023),"n/a") -> 10077000000 | U15: =IFERROR(SUMIFS(Data!V$3:V$78,Data!$A$3:$A$78,$A15,Data!$B$3:$B$78,2023),"n/a") -> 8.06 | V15: =IFERROR(SUMIFS(Data!W$3:W$78,Data!$A$3:$A$78,$A15,Data!$B$3:$B$78,2023),"n/a") -> 14.02 | W15: =IFERROR(SUMIFS(Data!X$3:X$78,Data!$A$3:$A$78,$A15,Data!$B$3:$B$78,2023),"n/a") -> 14.02 | X15: =IFERROR(SUMIFS(Data!Y$3:Y$78,Data!$A$3:$A$78,$A15,Data!$B$3:$B$78,2023),"n/a") -> 0.57 | Y15: =IFERROR(SUMIFS(Data!Z$3:Z$78,Data!$A$3:$A$78,$A15,Data!$B$3:$B$78,2023),"n/a") -> 8.88
A16: Somalia | B16: =IFERROR(SUMIFS(Data!C$3:C$78,Data!$A$3:$A$78,$A16,Data!$B$3:$B$78,2023),"n/a") -> 10968517090 | C16: =IFERROR(SUMIFS(Data!D$3:D$78,Data!$A$3:$A$78,$A16,Data!$B$3:$B$78,2023),"n/a") -> 298621000000000 | D16: =IFERROR(SUMIFS(Data!E$3:E$78,Data!$A$3:$A$78,$A16,Data!$B$3:$B$78,2023),"n/a") -> 4.22 | E16: =IFERROR(SUMIFS(Data!F$3:F$78,Data!$A$3:$A$78,$A16,Data!$B$3:$B$78,2023),"n/a") -> 28575608117 | F16: =IFERROR(SUMIFS(Data!G$3:G$78,Data!$A$3:$A$78,$A16,Data!$B$3:$B$78,2023),"n/a") -> 8539706139 | G16: =IFERROR(SUMIFS(Data!H$3:H$78,Data!$A$3:$A$78,$A16,Data!$B$3:$B$78,2023),"n/a") -> 285309000000000 | H16: =IFERROR(SUMIFS(Data!I$3:I$78,Data!$A$3:$A$78,$A16,Data!$B$3:$B$78,2023),"n/a") -> 25747405283 | I16: =IFERROR(SUMIFS(Data!J$3:J$78,Data!$A$3:$A$78,$A16,Data!$B$3:$B$78,2023),"n/a") -> 104.67 | ... Q16: =IFERROR(SUMIFS(Data!R$3:R$78,Data!$A$3:$A$78,$A16,Data!$B$3:$B$78,2023),"n/a") -> 297478000000000 | R16: n/a | S16: =IFERROR(SUMIFS(Data!T$3:T$78,Data!$A$3:$A$78,$A16,Data!$B$3:$B$78,2023),"n/a") -> 3.32 | T16: =IFERROR(SUMIFS(Data!U$3:U$78,Data!$A$3:$A$78,$A16,Data!$B$3:$B$78,2023),"n/a") -> 733000000 | U16: =IFERROR(SUMIFS(Data!V$3:V$78,Data!$A$3:$A$78,$A16,Data!$B$3:$B$78,2023),"n/a") -> 10450.22 | V16: =IFERROR(SUMIFS(Data!W$3:W$78,Data!$A$3:$A$78,$A16,Data!$B$3:$B$78,2023),"n/a") -> 27225.31 | W16: n/a | X16: =IFERROR(SUMIFS(Data!Y$3:Y$78,Data!$A$3:$A$78,$A16,Data!$B$3:$B$78,2023),"n/a") -> 0.38 | Y16: =IFERROR(SUMIFS(Data!Z$3:Z$78,Data!$A$3:$A$78,$A16,Data!$B$3:$B$78,2021),"n/a") -> 10392.25
A17: South Sudan | B17: n/a | C17: n/a | D17: n/a | E17: n/a | F17: n/a | G17: n/a | H17: n/a | I17: n/a | J17: n/a | K17: n/a | L17: n/a | M17: n/a | N17: n/a | O17: n/a | P17: n/a | Q17: n/a | R17: n/a | S17: n/a | T17: =IFERROR(SUMIFS(Data!U$3:U$78,Data!$A$3:$A$78,$A17,Data!$B$3:$B$78,2023),"n/a") -> 1478329000000 | U17: =IFERROR(SUMIFS(Data!V$3:V$78,Data!$A$3:$A$78,$A17,Data!$B$3:$B$78,2021),"n/a") -> 126.74 | V17: =IFERROR(SUMIFS(Data!W$3:W$78,Data!$A$3:$A$78,$A17,Data!$B$3:$B$78,2023),"n/a") -> 730.83 | W17: =IFERROR(SUMIFS(Data!X$3:X$78,Data!$A$3:$A$78,$A17,Data!$B$3:$B$78,2023),"n/a") -> 930.33 | X17: =IFERROR(SUMIFS(Data!Y$3:Y$78,Data!$A$3:$A$78,$A17,Data!$B$3:$B$78,2021),"n/a") -> 0.67 | Y17: =IFERROR(SUMIFS(Data!Z$3:Z$78,Data!$A$3:$A$78,$A17,Data!$B$3:$B$78,2021),"n/a") -> 158.05
A18: Uganda | B18: =IFERROR(SUMIFS(Data!C$3:C$78,Data!$A$3:$A$78,$A18,Data!$B$3:$B$78,2023),"n/a") -> 48768955859 | C18: =IFERROR(SUMIFS(Data!D$3:D$78,Data!$A$3:$A$78,$A18,Data!$B$3:$B$78,2023),"n/a") -> 183004000000000 | D18: =IFERROR(SUMIFS(Data!E$3:E$78,Data!$A$3:$A$78,$A18,Data!$B$3:$B$78,2023),"n/a") -> 5.34 | E18: =IFERROR(SUMIFS(Data!F$3:F$78,Data!$A$3:$A$78,$A18,Data!$B$3:$B$78,2023),"n/a") -> 150720000000 | F18: =IFERROR(SUMIFS(Data!G$3:G$78,Data!$A$3:$A$78,$A18,Data!$B$3:$B$78,2023),"n/a") -> 46503341915 | G18: =IFERROR(SUMIFS(Data!H$3:H$78,Data!$A$3:$A$78,$A18,Data!$B$3:$B$78,2023),"n/a") -> 144191000000000 | H18: =IFERROR(SUMIFS(Data!I$3:I$78,Data!$A$3:$A$78,$A18,Data!$B$3:$B$78,2023),"n/a") -> 135803000000 | I18: =IFERROR(SUMIFS(Data!J$3:J$78,Data!$A$3:$A$78,$A18,Data!$B$3:$B$78,2023),"n/a") -> 126.92 | ... Q18: =IFERROR(SUMIFS(Data!R$3:R$78,Data!$A$3:$A$78,$A18,Data!$B$3:$B$78,2023),"n/a") -> 178394000000000 | R18: n/a | S18: =IFERROR(SUMIFS(Data!T$3:T$78,Data!$A$3:$A$78,$A18,Data!$B$3:$B$78,2023),"n/a") -> 4.99 | T18: =IFERROR(SUMIFS(Data!U$3:U$78,Data!$A$3:$A$78,$A18,Data!$B$3:$B$78,2023),"n/a") -> 37342452000000 | U18: =IFERROR(SUMIFS(Data!V$3:V$78,Data!$A$3:$A$78,$A18,Data!$B$3:$B$78,2023),"n/a") -> 1214.2 | V18: =IFERROR(SUMIFS(Data!W$3:W$78,Data!$A$3:$A$78,$A18,Data!$B$3:$B$78,2023),"n/a") -> 3752.48 | W18: =IFERROR(SUMIFS(Data!X$3:X$78,Data!$A$3:$A$78,$A18,Data!$B$3:$B$78,2023),"n/a") -> 3726.14 | X18: =IFERROR(SUMIFS(Data!Y$3:Y$78,Data!$A$3:$A$78,$A18,Data!$B$3:$B$78,2023),"n/a") -> 0.32 | Y18: =IFERROR(SUMIFS(Data!Z$3:Z$78,Data!$A$3:$A$78,$A18,Data!$B$3:$B$78,2023),"n/a") -> 1320.92
A19: United Republic of Tanzania | B19: =IFERROR(SUMIFS(Data!C$3:C$78,Data!$A$3:$A$78,$A19,Data!$B$3:$B$78,2023),"n/a") -> 79062403837 | C19: =IFERROR(SUMIFS(Data!D$3:D$78,Data!$A$3:$A$78,$A19,Data!$B$3:$B$78,2023),"n/a") -> 183334000000000 | D19: =IFERROR(SUMIFS(Data!E$3:E$78,Data!$A$3:$A$78,$A19,Data!$B$3:$B$78,2023),"n/a") -> 5.07 | E19: =IFERROR(SUMIFS(Data!F$3:F$78,Data!$A$3:$A$78,$A19,Data!$B$3:$B$78,2023),"n/a") -> 259466000000 | F19: =IFERROR(SUMIFS(Data!G$3:G$78,Data!$A$3:$A$78,$A19,Data!$B$3:$B$78,2023),"n/a") -> 70563656178 | G19: =IFERROR(SUMIFS(Data!H$3:H$78,Data!$A$3:$A$78,$A19,Data!$B$3:$B$78,2023),"n/a") -> 140415000000000 | H19: =IFERROR(SUMIFS(Data!I$3:I$78,Data!$A$3:$A$78,$A19,Data!$B$3:$B$78,2023),"n/a") -> 233786000000 | I19: =IFERROR(SUMIFS(Data!J$3:J$78,Data!$A$3:$A$78,$A19,Data!$B$3:$B$78,2023),"n/a") -> 134.13 | ... Q19: =IFERROR(SUMIFS(Data!R$3:R$78,Data!$A$3:$A$78,$A19,Data!$B$3:$B$78,2023),"n/a") -> 184739000000000 | R19: n/a | S19: =IFERROR(SUMIFS(Data!T$3:T$78,Data!$A$3:$A$78,$A19,Data!$B$3:$B$78,2023),"n/a") -> 2.89 | T19: =IFERROR(SUMIFS(Data!U$3:U$78,Data!$A$3:$A$78,$A19,Data!$B$3:$B$78,2023),"n/a") -> 35499690000000 | U19: =IFERROR(SUMIFS(Data!V$3:V$78,Data!$A$3:$A$78,$A19,Data!$B$3:$B$78,2023),"n/a") -> 725.85 | V19: =IFERROR(SUMIFS(Data!W$3:W$78,Data!$A$3:$A$78,$A19,Data!$B$3:$B$78,2023),"n/a") -> 2382.09 | W19: =IFERROR(SUMIFS(Data!X$3:X$78,Data!$A$3:$A$78,$A19,Data!$B$3:$B$78,2023),"n/a") -> 2383.04 | X19: =IFERROR(SUMIFS(Data!Y$3:Y$78,Data!$A$3:$A$78,$A19,Data!$B$3:$B$78,2023),"n/a") -> 0.3 | Y19: =IFERROR(SUMIFS(Data!Z$3:Z$78,Data!$A$3:$A$78,$A19,Data!$B$3:$B$78,2023),"n/a") -> 656.79
A20: Zambia | B20: =IFERROR(SUMIFS(Data!C$3:C$78,Data!$A$3:$A$78,$A20,Data!$B$3:$B$78,2023),"n/a") -> 27577956471 | C20: =IFERROR(SUMIFS(Data!D$3:D$78,Data!$A$3:$A$78,$A20,Data!$B$3:$B$78,2023),"n/a") -> 557406000000 | D20: =IFERROR(SUMIFS(Data!E$3:E$78,Data!$A$3:$A$78,$A20,Data!$B$3:$B$78,2023),"n/a") -> 5.37 | E20: =IFERROR(SUMIFS(Data!F$3:F$78,Data!$A$3:$A$78,$A20,Data!$B$3:$B$78,2023),"n/a") -> 84491503485 | F20: =IFERROR(SUMIFS(Data!G$3:G$78,Data!$A$3:$A$78,$A20,Data!$B$3:$B$78,2023),"n/a") -> 27580695690 | G20: =IFERROR(SUMIFS(Data!H$3:H$78,Data!$A$3:$A$78,$A20,Data!$B$3:$B$78,2023),"n/a") -> 162235000000 | H20: =IFERROR(SUMIFS(Data!I$3:I$78,Data!$A$3:$A$78,$A20,Data!$B$3:$B$78,2023),"n/a") -> 76129157927 | I20: =IFERROR(SUMIFS(Data!J$3:J$78,Data!$A$3:$A$78,$A20,Data!$B$3:$B$78,2023),"n/a") -> 343.58 | ... Q20: =IFERROR(SUMIFS(Data!R$3:R$78,Data!$A$3:$A$78,$A20,Data!$B$3:$B$78,2023),"n/a") -> 531006000000 | R20: =IFERROR(SUMIFS(Data!S$3:S$78,Data!$A$3:$A$78,$A20,Data!$B$3:$B$78,2022),"n/a") -> 81.4 | S20: =IFERROR(SUMIFS(Data!T$3:T$78,Data!$A$3:$A$78,$A20,Data!$B$3:$B$78,2023),"n/a") -> 3.61 | T20: =IFERROR(SUMIFS(Data!U$3:U$78,Data!$A$3:$A$78,$A20,Data!$B$3:$B$78,2023),"n/a") -> 152642000000 | U20: =IFERROR(SUMIFS(Data!V$3:V$78,Data!$A$3:$A$78,$A20,Data!$B$3:$B$78,2023),"n/a") -> 6.6 | V20: =IFERROR(SUMIFS(Data!W$3:W$78,Data!$A$3:$A$78,$A20,Data!$B$3:$B$78,2023),"n/a") -> 20.21 | W20: =IFERROR(SUMIFS(Data!X$3:X$78,Data!$A$3:$A$78,$A20,Data!$B$3:$B$78,2023),"n/a") -> 20.21 | X20: =IFERROR(SUMIFS(Data!Y$3:Y$78,Data!$A$3:$A$78,$A20,Data!$B$3:$B$78,2023),"n/a") -> 0.33 | Y20: =IFERROR(SUMIFS(Data!Z$3:Z$78,Data!$A$3:$A$78,$A20,Data!$B$3:$B$78,2023),"n/a") -> 6.77
A21: Zimbabwe | B21: =IFERROR(SUMIFS(Data!C$3:C$78,Data!$A$3:$A$78,$A21,Data!$B$3:$B$78,2023),"n/a") -> 35231369343 | C21: =IFERROR(SUMIFS(Data!D$3:D$78,Data!$A$3:$A$78,$A21,Data!$B$3:$B$78,2023),"n/a") -> 53508663900 | D21: =IFERROR(SUMIFS(Data!E$3:E$78,Data!$A$3:$A$78,$A21,Data!$B$3:$B$78,2023),"n/a") -> 5.34 | E21: =IFERROR(SUMIFS(Data!F$3:F$78,Data!$A$3:$A$78,$A21,Data!$B$3:$B$78,2023),"n/a") -> 62427821460 | F21: =IFERROR(SUMIFS(Data!G$3:G$78,Data!$A$3:$A$78,$A21,Data!$B$3:$B$78,2023),"n/a") -> 23164059016 | G21: =IFERROR(SUMIFS(Data!H$3:H$78,Data!$A$3:$A$78,$A21,Data!$B$3:$B$78,2023),"n/a") -> 94925600 | H21: =IFERROR(SUMIFS(Data!I$3:I$78,Data!$A$3:$A$78,$A21,Data!$B$3:$B$78,2023),"n/a") -> 56249176341 | I21: =IFERROR(SUMIFS(Data!J$3:J$78,Data!$A$3:$A$78,$A21,Data!$B$3:$B$78,2023),"n/a") -> 56369.06 | ... Q21: =IFERROR(SUMIFS(Data!R$3:R$78,Data!$A$3:$A$78,$A21,Data!$B$3:$B$78,2023),"n/a") -> 52847537600 | R21: n/a | S21: =IFERROR(SUMIFS(Data!T$3:T$78,Data!$A$3:$A$78,$A21,Data!$B$3:$B$78,2023),"n/a") -> 3.34 | T21: =IFERROR(SUMIFS(Data!U$3:U$78,Data!$A$3:$A$78,$A21,Data!$B$3:$B$78,2023),"n/a") -> 10476000000 | U21: =IFERROR(SUMIFS(Data!V$3:V$78,Data!$A$3:$A$78,$A21,Data!$B$3:$B$78,2023),"n/a") -> 0.86 | V21: =IFERROR(SUMIFS(Data!W$3:W$78,Data!$A$3:$A$78,$A21,Data!$B$3:$B$78,2023),"n/a") -> 1.52 | W21: =IFERROR(SUMIFS(Data!X$3:X$78,Data!$A$3:$A$78,$A21,Data!$B$3:$B$78,2023),"n/a") -> 3509.17 | X21: =IFERROR(SUMIFS(Data!Y$3:Y$78,Data!$A$3:$A$78,$A21,Data!$B$3:$B$78,2023),"n/a") -> 0.56 | Y21: =IFERROR(SUMIFS(Data!Z$3:Z$78,Data!$A$3:$A$78,$A21,Data!$B$3:$B$78,2021),"n/a") -> 0.03
